Workbook

Sheet Resumen
A1: PINCH LAB
A2: Integración energética · Cp constante · Contracorriente · División de corrientes por intervalos
A3: ='Entradas'!A7 -> Datos válidos
A5: Calor disponible | B5: =SUMIFS('Entradas'!$F$11:$F$14,'Entradas'!$E$11:$E$14,"HOT") -> 530000 | C5: kJ/h
A6: Demanda de calor | B6: =SUMIFS('Entradas'!$F$11:$F$14,'Entradas'!$E$11:$E$14,"COLD") -> 540000 | C6: kJ/h
A7: Calentamiento mínimo | B7: =MAX(0,-MIN('Cascada'!H4:H11)) -> 70000 | C7: kJ/h
A8: Refrigeración mínima | B8: ='Cascada'!H11+B7 -> 60000 | C8: kJ/h
A9: Calor recuperado | B9: =B5-B8 -> 470000 | C9: kJ/h
A10: Demanda cubierta | B10: =IF(B6=0,0,B9/B6) -> 0.87037037
A11: ΔT mínimo | B11: ='Entradas'!B4 -> 10 | C11: K
A12: Balance global | B12: =B5+B7-B6-B8 -> 0 | C12: kJ/h
A14: Tolerancia numérica | B14: =MAX(1,B5,B6)*0.000000001 -> 0.00054 | C14: kJ/h
A16: Equipos de proceso | B16: =COUNTIFS('Equipos'!E4:E183,">"&B14) -> 22
A18: Conversión a kW
A19: Calentamiento | B19: =B7/3600 -> 19.444444 | C19: kW
A20: Refrigeración | B20: =B8/3600 -> 16.666667 | C20: kW
A21: Recuperación | B21: =B9/3600 -> 130.55556 | C21: kW
A24: Para editar: Entradas, celdas azules. El pinch es un resultado. Encontrarás todos sus nodos en Cascada, columnas J:L. En umbrales o zonas pinch puede haber varios nodos.
A30: Red ideal de máxima recuperación con ramas y mezclas a igual temperatura. No minimiza equipos ni costes. Área solo si introduces U. Servicios externos sin temperaturas especificadas: se calcula su carga, no su área.
A36: Cambiar el número de corrientes requiere regenerar el Excel desde Python. En este libro sí puedes cambiar ID, CP, Tin, Tout, ΔT y U. No insertes filas dentro de los cálculos.
A42: Calor sensible y CP constante por corriente. Para cp variable, discretiza por intervalos. No introducir cambios de fase como Tin=Tout.

Sheet Entradas
A1: Datos del proceso
A2: Edita las celdas azules. CP = caudal × calor específico. Unidades originales del PDF.
A4: ΔT mínimo (K) | B4: 10
A5: U (kJ/h·m²·K) | B5: 0 | C5: U=0: área sin calcular. U no viene en el PDF; introduce tu hipótesis si la conoces.
A7: =IF(AND(ISNUMBER(B4),B4>=0,ISNUMBER(B5),B5>=0,COUNT(B11:D14)=12,MIN(B11:B14)>0,MIN(C11:D14)>=-273.15,SUMPRODUCT(--(C11:C14=D11:D14))=0,COUNTA(A11:A14)=4,SUMPRODUCT(1/COUNTIF(A11:A14,A11:A14))=4),"Datos válidos","REVISAR ENTRADAS: números, CP, Tin ≠ Tout e identificadores únicos") -> Datos válidos
A8: Fuente: PDF aportado · Synthesis of Heat Exchanger Networks · diapositivas 27 y 30. H1/H2/C3/C4 corresponden a 1/2/3/4.
A10: ID | B10: CP (kJ/h·K) | C10: Tin (°C) | D10: Tout (°C) | E10: Tipo calculado | F10: |Q| (kJ/h) | G10: Q con signo | H10: T baja | I10: T alta | J10: T* baja | K10: T* alta
A11: H1 | B11: 1000 | C11: 250 | D11: 120 | E11: =IF(C11>D11,"HOT",IF(C11<D11,"COLD","ERROR")) -> HOT | F11: =B11*ABS(C11-D11) -> 130000 | G11: =B11*(C11-D11) -> 130000 | H11: =MIN(C11,D11) -> 120 | I11: =MAX(C11,D11) -> 250 | J11: =H11+IF(E11="HOT",-$B$4/2,$B$4/2) -> 115 | K11: =I11+IF(E11="HOT",-$B$4/2,$B$4/2) -> 245
A12: H2 | B12: 4000 | C12: 200 | D12: 100 | E12: =IF(C12>D12,"HOT",IF(C12<D12,"COLD","ERROR")) -> HOT | F12: =B12*ABS(C12-D12) -> 400000 | G12: =B12*(C12-D12) -> 400000 | H12: =MIN(C12,D12) -> 100 | I12: =MAX(C12,D12) -> 200 | J12: =H12+IF(E12="HOT",-$B$4/2,$B$4/2) -> 95 | K12: =I12+IF(E12="HOT",-$B$4/2,$B$4/2) -> 195
A13: C3 | B13: 3000 | C13: 90 | D13: 150 | E13: =IF(C13>D13,"HOT",IF(C13<D13,"COLD","ERROR")) -> COLD | F13: =B13*ABS(C13-D13) -> 180000 | G13: =B13*(C13-D13) -> -180000 | H13: =MIN(C13,D13) -> 90 | I13: =MAX(C13,D13) -> 150 | J13: =H13+IF(E13="HOT",-$B$4/2,$B$4/2) -> 95 | K13: =I13+IF(E13="HOT",-$B$4/2,$B$4/2) -> 155
A14: C4 | B14: 6000 | C14: 130 | D14: 190 | E14: =IF(C14>D14,"HOT",IF(C14<D14,"COLD","ERROR")) -> COLD | F14: =B14*ABS(C14-D14) -> 360000 | G14: =B14*(C14-D14) -> -360000 | H14: =MIN(C14,D14) -> 130 | I14: =MAX(C14,D14) -> 190 | J14: =H14+IF(E14="HOT",-$B$4/2,$B$4/2) -> 135 | K14: =I14+IF(E14="HOT",-$B$4/2,$B$4/2) -> 195

Sheet Matriz_Q
A1: Intercambios entre corrientes
A2: Q en kJ/h. Filas: donantes calientes. Columnas: receptoras frías. La matriz suma todos los tramos.
A3: Donante / receptora | B3: ='Entradas'!A11 -> H1 | C3: ='Entradas'!A12 -> H2 | D3: ='Entradas'!A13 -> C3 | E3: ='Entradas'!A14 -> C4 | F3: Refrigeración | G3: Calentamiento | H3: |Q| corriente | I3: Error balance
A4: ='Entradas'!A11 -> H1 | B4: =SUMPRODUCT('Tramos_red'!$M$4:$M$18,'Tramos_red'!$T$4:$T$18,'Tramos_red'!$X$4:$X$18) -> 0 | C4: =SUMPRODUCT('Tramos_red'!$M$4:$M$18,'Tramos_red'!$T$4:$T$18,'Tramos_red'!$Y$4:$Y$18) -> 0 | D4: =SUMPRODUCT('Tramos_red'!$M$4:$M$18,'Tramos_red'!$T$4:$T$18,'Tramos_red'!$Z$4:$Z$18) -> 32000 | E4: =SUMPRODUCT('Tramos_red'!$M$4:$M$18,'Tramos_red'!$T$4:$T$18,'Tramos_red'!$AA$4:$AA$18) -> 98000 | F4: =SUMPRODUCT('Tramos_red'!$N$4:$N$18,'Tramos_red'!$T$4:$T$18) -> 0 | G4: =SUMPRODUCT('Tramos_red'!$O$4:$O$18,'Tramos_red'!$X$4:$X$18) -> 0 | H4: ='Entradas'!F11 -> 130000 | I4: =IF('Entradas'!E11="HOT",SUM(B4:E4)+F4,SUM(B$4:B$7)+G4)-H4 -> 0
A5: ='Entradas'!A12 -> H2 | B5: =SUMPRODUCT('Tramos_red'!$M$4:$M$18,'Tramos_red'!$U$4:$U$18,'Tramos_red'!$X$4:$X$18) -> 0 | C5: =SUMPRODUCT('Tramos_red'!$M$4:$M$18,'Tramos_red'!$U$4:$U$18,'Tramos_red'!$Y$4:$Y$18) -> 0 | D5: =SUMPRODUCT('Tramos_red'!$M$4:$M$18,'Tramos_red'!$U$4:$U$18,'Tramos_red'!$Z$4:$Z$18) -> 148000 | E5: =SUMPRODUCT('Tramos_red'!$M$4:$M$18,'Tramos_red'!$U$4:$U$18,'Tramos_red'!$AA$4:$AA$18) -> 192000 | F5: =SUMPRODUCT('Tramos_red'!$N$4:$N$18,'Tramos_red'!$U$4:$U$18) -> 60000 | G5: =SUMPRODUCT('Tramos_red'!$O$4:$O$18,'Tramos_red'!$Y$4:$Y$18) -> 0 | H5: ='Entradas'!F12 -> 400000 | I5: =IF('Entradas'!E12="HOT",SUM(B5:E5)+F5,SUM(C$4:C$7)+G5)-H5 -> 0
A6: ='Entradas'!A13 -> C3 | B6: =SUMPRODUCT('Tramos_red'!$M$4:$M$18,'Tramos_red'!$V$4:$V$18,'Tramos_red'!$X$4:$X$18) -> 0 | C6: =SUMPRODUCT('Tramos_red'!$M$4:$M$18,'Tramos_red'!$V$4:$V$18,'Tramos_red'!$Y$4:$Y$18) -> 0 | D6: =SUMPRODUCT('Tramos_red'!$M$4:$M$18,'Tramos_red'!$V$4:$V$18,'Tramos_red'!$Z$4:$Z$18) -> 0 | E6: =SUMPRODUCT('Tramos_red'!$M$4:$M$18,'Tramos_red'!$V$4:$V$18,'Tramos_red'!$AA$4:$AA$18) -> 0 | F6: =SUMPRODUCT('Tramos_red'!$N$4:$N$18,'Tramos_red'!$V$4:$V$18) -> 0 | G6: =SUMPRODUCT('Tramos_red'!$O$4:$O$18,'Tramos_red'!$Z$4:$Z$18) -> 0 | H6: ='Entradas'!F13 -> 180000 | I6: =IF('Entradas'!E13="HOT",SUM(B6:E6)+F6,SUM(D$4:D$7)+G6)-H6 -> 0
A7: ='Entradas'!A14 -> C4 | B7: =SUMPRODUCT('Tramos_red'!$M$4:$M$18,'Tramos_red'!$W$4:$W$18,'Tramos_red'!$X$4:$X$18) -> 0 | C7: =SUMPRODUCT('Tramos_red'!$M$4:$M$18,'Tramos_red'!$W$4:$W$18,'Tramos_red'!$Y$4:$Y$18) -> 0 | D7: =SUMPRODUCT('Tramos_red'!$M$4:$M$18,'Tramos_red'!$W$4:$W$18,'Tramos_red'!$Z$4:$Z$18) -> 0 | E7: =SUMPRODUCT('Tramos_red'!$M$4:$M$18,'Tramos_red'!$W$4:$W$18,'Tramos_red'!$AA$4:$AA$18) -> 0 | F7: =SUMPRODUCT('Tramos_red'!$N$4:$N$18,'Tramos_red'!$W$4:$W$18) -> 0 | G7: =SUMPRODUCT('Tramos_red'!$O$4:$O$18,'Tramos_red'!$AA$4:$AA$18) -> 70000 | H7: ='Entradas'!F14 -> 360000 | I7: =IF('Entradas'!E14="HOT",SUM(B7:E7)+F7,SUM(E$4:E$7)+G7)-H7 -> 0

Sheet Equipos
A1: Intercambiadores de ramas
A2: Filtra Q > 0 para ver los equipos activos. Si cambias entradas, vuelve a aplicar el filtro. Las fracciones se refieren a cada corriente original.
A3: ID candidato | B3: Tramo | C3: Caliente | D3: Fría | E3: Q (kJ/h) | F3: Th entrada | G3: Th salida | H3: Tc entrada | I3: Tc salida | J3: Rama hot | K3: Rama cold | L3: CP rama hot | M3: CP rama cold | N3: ΔT extremo 1 | O3: ΔT extremo 2 | P3: ΔT log media | Q3: Área (m²)
A4: B1-P1-2 | B4: 1 | C4: ='Entradas'!A11 -> H1 | D4: ='Entradas'!A12 -> H2 | E4: ='Tramos_red'!M4*'Tramos_red'!T4*'Tramos_red'!Y4 -> 0 | F4: =IF(E4>'Resumen'!$B$14,'Tramos_red'!J4,"") | G4: =IF(E4>'Resumen'!$B$14,'Tramos_red'!I4,"") | H4: =IF(E4>'Resumen'!$B$14,'Tramos_red'!K4,"") | I4: =IF(E4>'Resumen'!$B$14,'Tramos_red'!L4,"") | J4: =IF(E4>'Resumen'!$B$14,'Tramos_red'!Y4,0) -> 0 | K4: =IF(E4>'Resumen'!$B$14,'Tramos_red'!T4,0) -> 0 | L4: =J4*'Entradas'!B11 -> 0 | M4: =K4*'Entradas'!B12 -> 0 | N4: =IF(E4>'Resumen'!$B$14,'Tramos_red'!P4,0) -> 0 | O4: =IF(E4>'Resumen'!$B$14,'Tramos_red'!Q4,0) -> 0 | P4: =IF(E4>'Resumen'!$B$14,'Tramos_red'!R4,0) -> 0 | Q4: =IF(E4<='Resumen'!$B$14,0,IF('Entradas'!$B$5=0,"sin U",IF(P4=0,"infinita",E4/('Entradas'!$B$5*P4)))) -> 0
A5: B1-P1-3 | B5: 1 | C5: ='Entradas'!A11 -> H1 | D5: ='Entradas'!A13 -> C3 | E5: ='Tramos_red'!M4*'Tramos_red'!T4*'Tramos_red'!Z4 -> 0 | F5: =IF(E5>'Resumen'!$B$14,'Tramos_red'!J4,"") | G5: =IF(E5>'Resumen'!$B$14,'Tramos_red'!I4,"") | H5: =IF(E5>'Resumen'!$B$14,'Tramos_red'!K4,"") | I5: =IF(E5>'Resumen'!$B$14,'Tramos_red'!L4,"") | J5: =IF(E5>'Resumen'!$B$14,'Tramos_red'!Z4,0) -> 0 | K5: =IF(E5>'Resumen'!$B$14,'Tramos_red'!T4,0) -> 0 | L5: =J5*'Entradas'!B11 -> 0 | M5: =K5*'Entradas'!B13 -> 0 | N5: =IF(E5>'Resumen'!$B$14,'Tramos_red'!P4,0) -> 0 | O5: =IF(E5>'Resumen'!$B$14,'Tramos_red'!Q4,0) -> 0 | P5: =IF(E5>'Resumen'!$B$14,'Tramos_red'!R4,0) -> 0 | Q5: =IF(E5<='Resumen'!$B$14,0,IF('Entradas'!$B$5=0,"sin U",IF(P5=0,"infinita",E5/('Entradas'!$B$5*P5)))) -> 0
A6: B1-P1-4 | B6: 1 | C6: ='Entradas'!A11 -> H1 | D6: ='Entradas'!A14 -> C4 | E6: ='Tramos_red'!M4*'Tramos_red'!T4*'Tramos_red'!AA4 -> 0 | F6: =IF(E6>'Resumen'!$B$14,'Tramos_red'!J4,"") | G6: =IF(E6>'Resumen'!$B$14,'Tramos_red'!I4,"") | H6: =IF(E6>'Resumen'!$B$14,'Tramos_red'!K4,"") | I6: =IF(E6>'Resumen'!$B$14,'Tramos_red'!L4,"") | J6: =IF(E6>'Resumen'!$B$14,'Tramos_red'!AA4,0) -> 0 | K6: =IF(E6>'Resumen'!$B$14,'Tramos_red'!T4,0) -> 0 | L6: =J6*'Entradas'!B11 -> 0 | M6: =K6*'Entradas'!B14 -> 0 | N6: =IF(E6>'Resumen'!$B$14,'Tramos_red'!P4,0) -> 0 | O6: =IF(E6>'Resumen'!$B$14,'Tramos_red'!Q4,0) -> 0 | P6: =IF(E6>'Resumen'!$B$14,'Tramos_red'!R4,0) -> 0 | Q6: =IF(E6<='Resumen'!$B$14,0,IF('Entradas'!$B$5=0,"sin U",IF(P6=0,"infinita",E6/('Entradas'!$B$5*P6)))) -> 0
A7: B1-P2-1 | B7: 1 | C7: ='Entradas'!A12 -> H2 | D7: ='Entradas'!A11 -> H1 | E7: ='Tramos_red'!M4*'Tramos_red'!U4*'Tramos_red'!X4 -> 0 | F7: =IF(E7>'Resumen'!$B$14,'Tramos_red'!J4,"") | G7: =IF(E7>'Resumen'!$B$14,'Tramos_red'!I4,"") | H7: =IF(E7>'Resumen'!$B$14,'Tramos_red'!K4,"") | I7: =IF(E7>'Resumen'!$B$14,'Tramos_red'!L4,"") | J7: =IF(E7>'Resumen'!$B$14,'Tramos_red'!X4,0) -> 0 | K7: =IF(E7>'Resumen'!$B$14,'Tramos_red'!U4,0) -> 0 | L7: =J7*'Entradas'!B12 -> 0 | M7: =K7*'Entradas'!B11 -> 0 | N7: =IF(E7>'Resumen'!$B$14,'Tramos_red'!P4,0) -> 0 | O7: =IF(E7>'Resumen'!$B$14,'Tramos_red'!Q4,0) -> 0 | P7: =IF(E7>'Resumen'!$B$14,'Tramos_red'!R4,0) -> 0 | Q7: =IF(E7<='Resumen'!$B$14,0,IF('Entradas'!$B$5=0,"sin U",IF(P7=0,"infinita",E7/('Entradas'!$B$5*P7)))) -> 0
A8: B1-P2-3 | B8: 1 | C8: ='Entradas'!A12 -> H2 | D8: ='Entradas'!A13 -> C3 | E8: ='Tramos_red'!M4*'Tramos_red'!U4*'Tramos_red'!Z4 -> 0 | F8: =IF(E8>'Resumen'!$B$14,'Tramos_red'!J4,"") | G8: =IF(E8>'Resumen'!$B$14,'Tramos_red'!I4,"") | H8: =IF(E8>'Resumen'!$B$14,'Tramos_red'!K4,"") | I8: =IF(E8>'Resumen'!$B$14,'Tramos_red'!L4,"") | J8: =IF(E8>'Resumen'!$B$14,'Tramos_red'!Z4,0) -> 0 | K8: =IF(E8>'Resumen'!$B$14,'Tramos_red'!U4,0) -> 0 | L8: =J8*'Entradas'!B12 -> 0 | M8: =K8*'Entradas'!B13 -> 0 | N8: =IF(E8>'Resumen'!$B$14,'Tramos_red'!P4,0) -> 0 | O8: =IF(E8>'Resumen'!$B$14,'Tramos_red'!Q4,0) -> 0 | P8: =IF(E8>'Resumen'!$B$14,'Tramos_red'!R4,0) -> 0 | Q8: =IF(E8<='Resumen'!$B$14,0,IF('Entradas'!$B$5=0,"sin U",IF(P8=0,"infinita",E8/('Entradas'!$B$5*P8)))) -> 0
A9: B1-P2-4 | B9: 1 | C9: ='Entradas'!A12 -> H2 | D9: ='Entradas'!A14 -> C4 | E9: ='Tramos_red'!M4*'Tramos_red'!U4*'Tramos_red'!AA4 -> 0 | F9: =IF(E9>'Resumen'!$B$14,'Tramos_red'!J4,"") | G9: =IF(E9>'Resumen'!$B$14,'Tramos_red'!I4,"") | H9: =IF(E9>'Resumen'!$B$14,'Tramos_red'!K4,"") | I9: =IF(E9>'Resumen'!$B$14,'Tramos_red'!L4,"") | J9: =IF(E9>'Resumen'!$B$14,'Tramos_red'!AA4,0) -> 0 | K9: =IF(E9>'Resumen'!$B$14,'Tramos_red'!U4,0) -> 0 | L9: =J9*'Entradas'!B12 -> 0 | M9: =K9*'Entradas'!B14 -> 0 | N9: =IF(E9>'Resumen'!$B$14,'Tramos_red'!P4,0) -> 0 | O9: =IF(E9>'Resumen'!$B$14,'Tramos_red'!Q4,0) -> 0 | P9: =IF(E9>'Resumen'!$B$14,'Tramos_red'!R4,0) -> 0 | Q9: =IF(E9<='Resumen'!$B$14,0,IF('Entradas'!$B$5=0,"sin U",IF(P9=0,"infinita",E9/('Entradas'!$B$5*P9)))) -> 0
A10: B1-P3-1 | B10: 1 | C10: ='Entradas'!A13 -> C3 | D10: ='Entradas'!A11 -> H1 | E10: ='Tramos_red'!M4*'Tramos_red'!V4*'Tramos_red'!X4 -> 0 | F10: =IF(E10>'Resumen'!$B$14,'Tramos_red'!J4,"") | G10: =IF(E10>'Resumen'!$B$14,'Tramos_red'!I4,"") | H10: =IF(E10>'Resumen'!$B$14,'Tramos_red'!K4,"") | I10: =IF(E10>'Resumen'!$B$14,'Tramos_red'!L4,"") | J10: =IF(E10>'Resumen'!$B$14,'Tramos_red'!X4,0) -> 0 | K10: =IF(E10>'Resumen'!$B$14,'Tramos_red'!V4,0) -> 0 | L10: =J10*'Entradas'!B13 -> 0 | M10: =K10*'Entradas'!B11 -> 0 | N10: =IF(E10>'Resumen'!$B$14,'Tramos_red'!P4,0) -> 0 | O10: =IF(E10>'Resumen'!$B$14,'Tramos_red'!Q4,0) -> 0 | P10: =IF(E10>'Resumen'!$B$14,'Tramos_red'!R4,0) -> 0 | Q10: =IF(E10<='Resumen'!$B$14,0,IF('Entradas'!$B$5=0,"sin U",IF(P10=0,"infinita",E10/('Entradas'!$B$5*P10)))) -> 0
A11: B1-P3-2 | B11: 1 | C11: ='Entradas'!A13 -> C3 | D11: ='Entradas'!A12 -> H2 | E11: ='Tramos_red'!M4*'Tramos_red'!V4*'Tramos_red'!Y4 -> 0 | F11: =IF(E11>'Resumen'!$B$14,'Tramos_red'!J4,"") | G11: =IF(E11>'Resumen'!$B$14,'Tramos_red'!I4,"") | H11: =IF(E11>'Resumen'!$B$14,'Tramos_red'!K4,"") | I11: =IF(E11>'Resumen'!$B$14,'Tramos_red'!L4,"") | J11: =IF(E11>'Resumen'!$B$14,'Tramos_red'!Y4,0) -> 0 | K11: =IF(E11>'Resumen'!$B$14,'Tramos_red'!V4,0) -> 0 | L11: =J11*'Entradas'!B13 -> 0 | M11: =K11*'Entradas'!B12 -> 0 | N11: =IF(E11>'Resumen'!$B$14,'Tramos_red'!P4,0) -> 0 | O11: =IF(E11>'Resumen'!$B$14,'Tramos_red'!Q4,0) -> 0 | P11: =IF(E11>'Resumen'!$B$14,'Tramos_red'!R4,0) -> 0 | Q11: =IF(E11<='Resumen'!$B$14,0,IF('Entradas'!$B$5=0,"sin U",IF(P11=0,"infinita",E11/('Entradas'!$B$5*P11)))) -> 0
A12: B1-P3-4 | B12: 1 | C12: ='Entradas'!A13 -> C3 | D12: ='Entradas'!A14 -> C4 | E12: ='Tramos_red'!M4*'Tramos_red'!V4*'Tramos_red'!AA4 -> 0 | F12: =IF(E12>'Resumen'!$B$14,'Tramos_red'!J4,"") | G12: =IF(E12>'Resumen'!$B$14,'Tramos_red'!I4,"") | H12: =IF(E12>'Resumen'!$B$14,'Tramos_red'!K4,"") | I12: =IF(E12>'Resumen'!$B$14,'Tramos_red'!L4,"") | J12: =IF(E12>'Resumen'!$B$14,'Tramos_red'!AA4,0) -> 0 | K12: =IF(E12>'Resumen'!$B$14,'Tramos_red'!V4,0) -> 0 | L12: =J12*'Entradas'!B13 -> 0 | M12: =K12*'Entradas'!B14 -> 0 | N12: =IF(E12>'Resumen'!$B$14,'Tramos_red'!P4,0) -> 0 | O12: =IF(E12>'Resumen'!$B$14,'Tramos_red'!Q4,0) -> 0 | P12: =IF(E12>'Resumen'!$B$14,'Tramos_red'!R4,0) -> 0 | Q12: =IF(E12<='Resumen'!$B$14,0,IF('Entradas'!$B$5=0,"sin U",IF(P12=0,"infinita",E12/('Entradas'!$B$5*P12)))) -> 0
A13: B1-P4-1 | B13: 1 | C13: ='Entradas'!A14 -> C4 | D13: ='Entradas'!A11 -> H1 | E13: ='Tramos_red'!M4*'Tramos_red'!W4*'Tramos_red'!X4 -> 0 | F13: =IF(E13>'Resumen'!$B$14,'Tramos_red'!J4,"") | G13: =IF(E13>'Resumen'!$B$14,'Tramos_red'!I4,"") | H13: =IF(E13>'Resumen'!$B$14,'Tramos_red'!K4,"") | I13: =IF(E13>'Resumen'!$B$14,'Tramos_red'!L4,"") | J13: =IF(E13>'Resumen'!$B$14,'Tramos_red'!X4,0) -> 0 | K13: =IF(E13>'Resumen'!$B$14,'Tramos_red'!W4,0) -> 0 | L13: =J13*'Entradas'!B14 -> 0 | M13: =K13*'Entradas'!B11 -> 0 | N13: =IF(E13>'Resumen'!$B$14,'Tramos_red'!P4,0) -> 0 | O13: =IF(E13>'Resumen'!$B$14,'Tramos_red'!Q4,0) -> 0 | P13: =IF(E13>'Resumen'!$B$14,'Tramos_red'!R4,0) -> 0 | Q13: =IF(E13<='Resumen'!$B$14,0,IF('Entradas'!$B$5=0,"sin U",IF(P13=0,"infinita",E13/('Entradas'!$B$5*P13)))) -> 0
A14: B1-P4-2 | B14: 1 | C14: ='Entradas'!A14 -> C4 | D14: ='Entradas'!A12 -> H2 | E14: ='Tramos_red'!M4*'Tramos_red'!W4*'Tramos_red'!Y4 -> 0 | F14: =IF(E14>'Resumen'!$B$14,'Tramos_red'!J4,"") | G14: =IF(E14>'Resumen'!$B$14,'Tramos_red'!I4,"") | H14: =IF(E14>'Resumen'!$B$14,'Tramos_red'!K4,"") | I14: =IF(E14>'Resumen'!$B$14,'Tramos_red'!L4,"") | J14: =IF(E14>'Resumen'!$B$14,'Tramos_red'!Y4,0) -> 0 | K14: =IF(E14>'Resumen'!$B$14,'Tramos_red'!W4,0) -> 0 | L14: =J14*'Entradas'!B14 -> 0 | M14: =K14*'Entradas'!B12 -> 0 | N14: =IF(E14>'Resumen'!$B$14,'Tramos_red'!P4,0) -> 0 | O14: =IF(E14>'Resumen'!$B$14,'Tramos_red'!Q4,0) -> 0 | P14: =IF(E14>'Resumen'!$B$14,'Tramos_red'!R4,0) -> 0 | Q14: =IF(E14<='Resumen'!$B$14,0,IF('Entradas'!$B$5=0,"sin U",IF(P14=0,"infinita",E14/('Entradas'!$B$5*P14)))) -> 0
A15: B1-P4-3 | B15: 1 | C15: ='Entradas'!A14 -> C4 | D15: ='Entradas'!A13 -> C3 | E15: ='Tramos_red'!M4*'Tramos_red'!W4*'Tramos_red'!Z4 -> 0 | F15: =IF(E15>'Resumen'!$B$14,'Tramos_red'!J4,"") | G15: =IF(E15>'Resumen'!$B$14,'Tramos_red'!I4,"") | H15: =IF(E15>'Resumen'!$B$14,'Tramos_red'!K4,"") | I15: =IF(E15>'Resumen'!$B$14,'Tramos_red'!L4,"") | J15: =IF(E15>'Resumen'!$B$14,'Tramos_red'!Z4,0) -> 0 | K15: =IF(E15>'Resumen'!$B$14,'Tramos_red'!W4,0) -> 0 | L15: =J15*'Entradas'!B14 -> 0 | M15: =K15*'Entradas'!B13 -> 0 | N15: =IF(E15>'Resumen'!$B$14,'Tramos_red'!P4,0) -> 0 | O15: =IF(E15>'Resumen'!$B$14,'Tramos_red'!Q4,0) -> 0 | P15: =IF(E15>'Resumen'!$B$14,'Tramos_red'!R4,0) -> 0 | Q15: =IF(E15<='Resumen'!$B$14,0,IF('Entradas'!$B$5=0,"sin U",IF(P15=0,"infinita",E15/('Entradas'!$B$5*P15)))) -> 0
A16: B2-P1-2 | B16: 2 | C16: ='Entradas'!A11 -> H1 | D16: ='Entradas'!A12 -> H2 | E16: ='Tramos_red'!M5*'Tramos_red'!T5*'Tramos_red'!Y5 -> 0 | F16: =IF(E16>'Resumen'!$B$14,'Tramos_red'!J5,"") | G16: =IF(E16>'Resumen'!$B$14,'Tramos_red'!I5,"") | H16: =IF(E16>'Resumen'!$B$14,'Tramos_red'!K5,"") | I16: =IF(E16>'Resumen'!$B$14,'Tramos_red'!L5,"") | J16: =IF(E16>'Resumen'!$B$14,'Tramos_red'!Y5,0) -> 0 | K16: =IF(E16>'Resumen'!$B$14,'Tramos_red'!T5,0) -> 0 | L16: =J16*'Entradas'!B11 -> 0 | M16: =K16*'Entradas'!B12 -> 0 | N16: =IF(E16>'Resumen'!$B$14,'Tramos_red'!P5,0) -> 0 | O16: =IF(E16>'Resumen'!$B$14,'Tramos_red'!Q5,0) -> 0 | P16: =IF(E16>'Resumen'!$B$14,'Tramos_red'!R5,0) -> 0 | Q16: =IF(E16<='Resumen'!$B$14,0,IF('Entradas'!$B$5=0,"sin U",IF(P16=0,"infinita",E16/('Entradas'!$B$5*P16)))) -> 0
A17: B2-P1-3 | B17: 2 | C17: ='Entradas'!A11 -> H1 | D17: ='Entradas'!A13 -> C3 | E17: ='Tramos_red'!M5*'Tramos_red'!T5*'Tramos_red'!Z5 -> 0 | F17: =IF(E17>'Resumen'!$B$14,'Tramos_red'!J5,"") | G17: =IF(E17>'Resumen'!$B$14,'Tramos_red'!I5,"") | H17: =IF(E17>'Resumen'!$B$14,'Tramos_red'!K5,"") | I17: =IF(E17>'Resumen'!$B$14,'Tramos_red'!L5,"") | J17: =IF(E17>'Resumen'!$B$14,'Tramos_red'!Z5,0) -> 0 | K17: =IF(E17>'Resumen'!$B$14,'Tramos_red'!T5,0) -> 0 | L17: =J17*'Entradas'!B11 -> 0 | M17: =K17*'Entradas'!B13 -> 0 | N17: =IF(E17>'Resumen'!$B$14,'Tramos_red'!P5,0) -> 0 | O17: =IF(E17>'Resumen'!$B$14,'Tramos_red'!Q5,0) -> 0 | P17: =IF(E17>'Resumen'!$B$14,'Tramos_red'!R5,0) -> 0 | Q17: =IF(E17<='Resumen'!$B$14,0,IF('Entradas'!$B$5=0,"sin U",IF(P17=0,"infinita",E17/('Entradas'!$B$5*P17)))) -> 0
A18: B2-P1-4 | B18: 2 | C18: ='Entradas'!A11 -> H1 | D18: ='Entradas'!A14 -> C4 | E18: ='Tramos_red'!M5*'Tramos_red'!T5*'Tramos_red'!AA5 -> 0 | F18: =IF(E18>'Resumen'!$B$14,'Tramos_red'!J5,"") | G18: =IF(E18>'Resumen'!$B$14,'Tramos_red'!I5,"") | H18: =IF(E18>'Resumen'!$B$14,'Tramos_red'!K5,"") | I18: =IF(E18>'Resumen'!$B$14,'Tramos_red'!L5,"") | J18: =IF(E18>'Resumen'!$B$14,'Tramos_red'!AA5,0) -> 0 | K18: =IF(E18>'Resumen'!$B$14,'Tramos_red'!T5,0) -> 0 | L18: =J18*'Entradas'!B11 -> 0 | M18: =K18*'Entradas'!B14 -> 0 | N18: =IF(E18>'Resumen'!$B$14,'Tramos_red'!P5,0) -> 0 | O18: =IF(E18>'Resumen'!$B$14,'Tramos_red'!Q5,0) -> 0 | P18: =IF(E18>'Resumen'!$B$14,'Tramos_red'!R5,0) -> 0 | Q18: =IF(E18<='Resumen'!$B$14,0,IF('Entradas'!$B$5=0,"sin U",IF(P18=0,"infinita",E18/('Entradas'!$B$5*P18)))) -> 0
A19: B2-P2-1 | B19: 2 | C19: ='Entradas'!A12 -> H2 | D19: ='Entradas'!A11 -> H1 | E19: ='Tramos_red'!M5*'Tramos_red'!U5*'Tramos_red'!X5 -> 0 | F19: =IF(E19>'Resumen'!$B$14,'Tramos_red'!J5,"") | G19: =IF(E19>'Resumen'!$B$14,'Tramos_red'!I5,"") | H19: =IF(E19>'Resumen'!$B$14,'Tramos_red'!K5,"") | I19: =IF(E19>'Resumen'!$B$14,'Tramos_red'!L5,"") | J19: =IF(E19>'Resumen'!$B$14,'Tramos_red'!X5,0) -> 0 | K19: =IF(E19>'Resumen'!$B$14,'Tramos_red'!U5,0) -> 0 | L19: =J19*'Entradas'!B12 -> 0 | M19: =K19*'Entradas'!B11 -> 0 | N19: =IF(E19>'Resumen'!$B$14,'Tramos_red'!P5,0) -> 0 | O19: =IF(E19>'Resumen'!$B$14,'Tramos_red'!Q5,0) -> 0 | P19: =IF(E19>'Resumen'!$B$14,'Tramos_red'!R5,0) -> 0 | Q19: =IF(E19<='Resumen'!$B$14,0,IF('Entradas'!$B$5=0,"sin U",IF(P19=0,"infinita",E19/('Entradas'!$B$5*P19)))) -> 0
A20: B2-P2-3 | B20: 2 | C20: ='Entradas'!A12 -> H2 | D20: ='Entradas'!A13 -> C3 | E20: ='Tramos_red'!M5*'Tramos_red'!U5*'Tramos_red'!Z5 -> 0 | F20: =IF(E20>'Resumen'!$B$14,'Tramos_red'!J5,"") | G20: =IF(E20>'Resumen'!$B$14,'Tramos_red'!I5,"") | H20: =IF(E20>'Resumen'!$B$14,'Tramos_red'!K5,"") | I20: =IF(E20>'Resumen'!$B$14,'Tramos_red'!L5,"") | J20: =IF(E20>'Resumen'!$B$14,'Tramos_red'!Z5,0) -> 0 | K20: =IF(E20>'Resumen'!$B$14,'Tramos_red'!U5,0) -> 0 | L20: =J20*'Entradas'!B12 -> 0 | M20: =K20*'Entradas'!B13 -> 0 | N20: =IF(E20>'Resumen'!$B$14,'Tramos_red'!P5,0) -> 0 | O20: =IF(E20>'Resumen'!$B$14,'Tramos_red'!Q5,0) -> 0 | P20: =IF(E20>'Resumen'!$B$14,'Tramos_red'!R5,0) -> 0 | Q20: =IF(E20<='Resumen'!$B$14,0,IF('Entradas'!$B$5=0,"sin U",IF(P20=0,"infinita",E20/('Entradas'!$B$5*P20)))) -> 0
A21: B2-P2-4 | B21: 2 | C21: ='Entradas'!A12 -> H2 | D21: ='Entradas'!A14 -> C4 | E21: ='Tramos_red'!M5*'Tramos_red'!U5*'Tramos_red'!AA5 -> 0 | F21: =IF(E21>'Resumen'!$B$14,'Tramos_red'!J5,"") | G21: =IF(E21>'Resumen'!$B$14,'Tramos_red'!I5,"") | H21: =IF(E21>'Resumen'!$B$14,'Tramos_red'!K5,"") | I21: =IF(E21>'Resumen'!$B$14,'Tramos_red'!L5,"") | J21: =IF(E21>'Resumen'!$B$14,'Tramos_red'!AA5,0) -> 0 | K21: =IF(E21>'Resumen'!$B$14,'Tramos_red'!U5,0) -> 0 | L21: =J21*'Entradas'!B12 -> 0 | M21: =K21*'Entradas'!B14 -> 0 | N21: =IF(E21>'Resumen'!$B$14,'Tramos_red'!P5,0) -> 0 | O21: =IF(E21>'Resumen'!$B$14,'Tramos_red'!Q5,0) -> 0 | P21: =IF(E21>'Resumen'!$B$14,'Tramos_red'!R5,0) -> 0 | Q21: =IF(E21<='Resumen'!$B$14,0,IF('Entradas'!$B$5=0,"sin U",IF(P21=0,"infinita",E21/('Entradas'!$B$5*P21)))) -> 0
A22: B2-P3-1 | B22: 2 | C22: ='Entradas'!A13 -> C3 | D22: ='Entradas'!A11 -> H1 | E22: ='Tramos_red'!M5*'Tramos_red'!V5*'Tramos_red'!X5 -> 0 | F22: =IF(E22>'Resumen'!$B$14,'Tramos_red'!J5,"") | G22: =IF(E22>'Resumen'!$B$14,'Tramos_red'!I5,"") | H22: =IF(E22>'Resumen'!$B$14,'Tramos_red'!K5,"") | I22: =IF(E22>'Resumen'!$B$14,'Tramos_red'!L5,"") | J22: =IF(E22>'Resumen'!$B$14,'Tramos_red'!X5,0) -> 0 | K22: =IF(E22>'Resumen'!$B$14,'Tramos_red'!V5,0) -> 0 | L22: =J22*'Entradas'!B13 -> 0 | M22: =K22*'Entradas'!B11 -> 0 | N22: =IF(E22>'Resumen'!$B$14,'Tramos_red'!P5,0) -> 0 | O22: =IF(E22>'Resumen'!$B$14,'Tramos_red'!Q5,0) -> 0 | P22: =IF(E22>'Resumen'!$B$14,'Tramos_red'!R5,0) -> 0 | Q22: =IF(E22<='Resumen'!$B$14,0,IF('Entradas'!$B$5=0,"sin U",IF(P22=0,"infinita",E22/('Entradas'!$B$5*P22)))) -> 0
A23: B2-P3-2 | B23: 2 | C23: ='Entradas'!A13 -> C3 | D23: ='Entradas'!A12 -> H2 | E23: ='Tramos_red'!M5*'Tramos_red'!V5*'Tramos_red'!Y5 -> 0 | F23: =IF(E23>'Resumen'!$B$14,'Tramos_red'!J5,"") | G23: =IF(E23>'Resumen'!$B$14,'Tramos_red'!I5,"") | H23: =IF(E23>'Resumen'!$B$14,'Tramos_red'!K5,"") | I23: =IF(E23>'Resumen'!$B$14,'Tramos_red'!L5,"") | J23: =IF(E23>'Resumen'!$B$14,'Tramos_red'!Y5,0) -> 0 | K23: =IF(E23>'Resumen'!$B$14,'Tramos_red'!V5,0) -> 0 | L23: =J23*'Entradas'!B13 -> 0 | M23: =K23*'Entradas'!B12 -> 0 | N23: =IF(E23>'Resumen'!$B$14,'Tramos_red'!P5,0) -> 0 | O23: =IF(E23>'Resumen'!$B$14,'Tramos_red'!Q5,0) -> 0 | P23: =IF(E23>'Resumen'!$B$14,'Tramos_red'!R5,0) -> 0 | Q23: =IF(E23<='Resumen'!$B$14,0,IF('Entradas'!$B$5=0,"sin U",IF(P23=0,"infinita",E23/('Entradas'!$B$5*P23)))) -> 0
A24: B2-P3-4 | B24: 2 | C24: ='Entradas'!A13 -> C3 | D24: ='Entradas'!A14 -> C4 | E24: ='Tramos_red'!M5*'Tramos_red'!V5*'Tramos_red'!AA5 -> 0 | F24: =IF(E24>'Resumen'!$B$14,'Tramos_red'!J5,"") | G24: =IF(E24>'Resumen'!$B$14,'Tramos_red'!I5,"") | H24: =IF(E24>'Resumen'!$B$14,'Tramos_red'!K5,"") | I24: =IF(E24>'Resumen'!$B$14,'Tramos_red'!L5,"") | J24: =IF(E24>'Resumen'!$B$14,'Tramos_red'!AA5,0) -> 0 | K24: =IF(E24>'Resumen'!$B$14,'Tramos_red'!V5,0) -> 0 | L24: =J24*'Entradas'!B13 -> 0 | M24: =K24*'Entradas'!B14 -> 0 | N24: =IF(E24>'Resumen'!$B$14,'Tramos_red'!P5,0) -> 0 | O24: =IF(E24>'Resumen'!$B$14,'Tramos_red'!Q5,0) -> 0 | P24: =IF(E24>'Resumen'!$B$14,'Tramos_red'!R5,0) -> 0 | Q24: =IF(E24<='Resumen'!$B$14,0,IF('Entradas'!$B$5=0,"sin U",IF(P24=0,"infinita",E24/('Entradas'!$B$5*P24)))) -> 0
A25: B2-P4-1 | B25: 2 | C25: ='Entradas'!A14 -> C4 | D25: ='Entradas'!A11 -> H1 | E25: ='Tramos_red'!M5*'Tramos_red'!W5*'Tramos_red'!X5 -> 0 | F25: =IF(E25>'Resumen'!$B$14,'Tramos_red'!J5,"") | G25: =IF(E25>'Resumen'!$B$14,'Tramos_red'!I5,"") | H25: =IF(E25>'Resumen'!$B$14,'Tramos_red'!K5,"") | I25: =IF(E25>'Resumen'!$B$14,'Tramos_red'!L5,"") | J25: =IF(E25>'Resumen'!$B$14,'Tramos_red'!X5,0) -> 0 | K25: =IF(E25>'Resumen'!$B$14,'Tramos_red'!W5,0) -> 0 | L25: =J25*'Entradas'!B14 -> 0 | M25: =K25*'Entradas'!B11 -> 0 | N25: =IF(E25>'Resumen'!$B$14,'Tramos_red'!P5,0) -> 0 | O25: =IF(E25>'Resumen'!$B$14,'Tramos_red'!Q5,0) -> 0 | P25: =IF(E25>'Resumen'!$B$14,'Tramos_red'!R5,0) -> 0 | Q25: =IF(E25<='Resumen'!$B$14,0,IF('Entradas'!$B$5=0,"sin U",IF(P25=0,"infinita",E25/('Entradas'!$B$5*P25)))) -> 0
A26: B2-P4-2 | B26: 2 | C26: ='Entradas'!A14 -> C4 | D26: ='Entradas'!A12 -> H2 | E26: ='Tramos_red'!M5*'Tramos_red'!W5*'Tramos_red'!Y5 -> 0 | F26: =IF(E26>'Resumen'!$B$14,'Tramos_red'!J5,"") | G26: =IF(E26>'Resumen'!$B$14,'Tramos_red'!I5,"") | H26: =IF(E26>'Resumen'!$B$14,'Tramos_red'!K5,"") | I26: =IF(E26>'Resumen'!$B$14,'Tramos_red'!L5,"") | J26: =IF(E26>'Resumen'!$B$14,'Tramos_red'!Y5,0) -> 0 | K26: =IF(E26>'Resumen'!$B$14,'Tramos_red'!W5,0) -> 0 | L26: =J26*'Entradas'!B14 -> 0 | M26: =K26*'Entradas'!B12 -> 0 | N26: =IF(E26>'Resumen'!$B$14,'Tramos_red'!P5,0) -> 0 | O26: =IF(E26>'Resumen'!$B$14,'Tramos_red'!Q5,0) -> 0 | P26: =IF(E26>'Resumen'!$B$14,'Tramos_red'!R5,0) -> 0 | Q26: =IF(E26<='Resumen'!$B$14,0,IF('Entradas'!$B$5=0,"sin U",IF(P26=0,"infinita",E26/('Entradas'!$B$5*P26)))) -> 0
A27: B2-P4-3 | B27: 2 | C27: ='Entradas'!A14 -> C4 | D27: ='Entradas'!A13 -> C3 | E27: ='Tramos_red'!M5*'Tramos_red'!W5*'Tramos_red'!Z5 -> 0 | F27: =IF(E27>'Resumen'!$B$14,'Tramos_red'!J5,"") | G27: =IF(E27>'Resumen'!$B$14,'Tramos_red'!I5,"") | H27: =IF(E27>'Resumen'!$B$14,'Tramos_red'!K5,"") | I27: =IF(E27>'Resumen'!$B$14,'Tramos_red'!L5,"") | J27: =IF(E27>'Resumen'!$B$14,'Tramos_red'!Z5,0) -> 0 | K27: =IF(E27>'Resumen'!$B$14,'Tramos_red'!W5,0) -> 0 | L27: =J27*'Entradas'!B14 -> 0 | M27: =K27*'Entradas'!B13 -> 0 | N27: =IF(E27>'Resumen'!$B$14,'Tramos_red'!P5,0) -> 0 | O27: =IF(E27>'Resumen'!$B$14,'Tramos_red'!Q5,0) -> 0 | P27: =IF(E27>'Resumen'!$B$14,'Tramos_red'!R5,0) -> 0 | Q27: =IF(E27<='Resumen'!$B$14,0,IF('Entradas'!$B$5=0,"sin U",IF(P27=0,"infinita",E27/('Entradas'!$B$5*P27)))) -> 0
A28: B3-P1-2 | B28: 3 | C28: ='Entradas'!A11 -> H1 | D28: ='Entradas'!A12 -> H2 | E28: ='Tramos_red'!M6*'Tramos_red'!T6*'Tramos_red'!Y6 -> 0 | F28: =IF(E28>'Resumen'!$B$14,'Tramos_red'!J6,"") | G28: =IF(E28>'Resumen'!$B$14,'Tramos_red'!I6,"") | H28: =IF(E28>'Resumen'!$B$14,'Tramos_red'!K6,"") | I28: =IF(E28>'Resumen'!$B$14,'Tramos_red'!L6,"") | J28: =IF(E28>'Resumen'!$B$14,'Tramos_red'!Y6,0) -> 0 | K28: =IF(E28>'Resumen'!$B$14,'Tramos_red'!T6,0) -> 0 | L28: =J28*'Entradas'!B11 -> 0 | M28: =K28*'Entradas'!B12 -> 0 | N28: =IF(E28>'Resumen'!$B$14,'Tramos_red'!P6,0) -> 0 | O28: =IF(E28>'Resumen'!$B$14,'Tramos_red'!Q6,0) -> 0 | P28: =IF(E28>'Resumen'!$B$14,'Tramos_red'!R6,0) -> 0 | Q28: =IF(E28<='Resumen'!$B$14,0,IF('Entradas'!$B$5=0,"sin U",IF(P28=0,"infinita",E28/('Entradas'!$B$5*P28)))) -> 0
A29: B3-P1-3 | B29: 3 | C29: ='Entradas'!A11 -> H1 | D29: ='Entradas'!A13 -> C3 | E29: ='Tramos_red'!M6*'Tramos_red'!T6*'Tramos_red'!Z6 -> 0 | F29: =IF(E29>'Resumen'!$B$14,'Tramos_red'!J6,"") | G29: =IF(E29>'Resumen'!$B$14,'Tramos_red'!I6,"") | H29: =IF(E29>'Resumen'!$B$14,'Tramos_red'!K6,"") | I29: =IF(E29>'Resumen'!$B$14,'Tramos_red'!L6,"") | J29: =IF(E29>'Resumen'!$B$14,'Tramos_red'!Z6,0) -> 0 | K29: =IF(E29>'Resumen'!$B$14,'Tramos_red'!T6,0) -> 0 | L29: =J29*'Entradas'!B11 -> 0 | M29: =K29*'Entradas'!B13 -> 0 | N29: =IF(E29>'Resumen'!$B$14,'Tramos_red'!P6,0) -> 0 | O29: =IF(E29>'Resumen'!$B$14,'Tramos_red'!Q6,0) -> 0 | P29: =IF(E29>'Resumen'!$B$14,'Tramos_red'!R6,0) -> 0 | Q29: =IF(E29<='Resumen'!$B$14,0,IF('Entradas'!$B$5=0,"sin U",IF(P29=0,"infinita",E29/('Entradas'!$B$5*P29)))) -> 0
A30: B3-P1-4 | B30: 3 | C30: ='Entradas'!A11 -> H1 | D30: ='Entradas'!A14 -> C4 | E30: ='Tramos_red'!M6*'Tramos_red'!T6*'Tramos_red'!AA6 -> 0 | F30: =IF(E30>'Resumen'!$B$14,'Tramos_red'!J6,"") | G30: =IF(E30>'Resumen'!$B$14,'Tramos_red'!I6,"") | H30: =IF(E30>'Resumen'!$B$14,'Tramos_red'!K6,"") | I30: =IF(E30>'Resumen'!$B$14,'Tramos_red'!L6,"") | J30: =IF(E30>'Resumen'!$B$14,'Tramos_red'!AA6,0) -> 0 | K30: =IF(E30>'Resumen'!$B$14,'Tramos_red'!T6,0) -> 0 | L30: =J30*'Entradas'!B11 -> 0 | M30: =K30*'Entradas'!B14 -> 0 | N30: =IF(E30>'Resumen'!$B$14,'Tramos_red'!P6,0) -> 0 | O30: =IF(E30>'Resumen'!$B$14,'Tramos_red'!Q6,0) -> 0 | P30: =IF(E30>'Resumen'!$B$14,'Tramos_red'!R6,0) -> 0 | Q30: =IF(E30<='Resumen'!$B$14,0,IF('Entradas'!$B$5=0,"sin U",IF(P30=0,"infinita",E30/('Entradas'!$B$5*P30)))) -> 0
A31: B3-P2-1 | B31: 3 | C31: ='Entradas'!A12 -> H2 | D31: ='Entradas'!A11 -> H1 | E31: ='Tramos_red'!M6*'Tramos_red'!U6*'Tramos_red'!X6 -> 0 | F31: =IF(E31>'Resumen'!$B$14,'Tramos_red'!J6,"") | G31: =IF(E31>'Resumen'!$B$14,'Tramos_red'!I6,"") | H31: =IF(E31>'Resumen'!$B$14,'Tramos_red'!K6,"") | I31: =IF(E31>'Resumen'!$B$14,'Tramos_red'!L6,"") | J31: =IF(E31>'Resumen'!$B$14,'Tramos_red'!X6,0) -> 0 | K31: =IF(E31>'Resumen'!$B$14,'Tramos_red'!U6,0) -> 0 | L31: =J31*'Entradas'!B12 -> 0 | M31: =K31*'Entradas'!B11 -> 0 | N31: =IF(E31>'Resumen'!$B$14,'Tramos_red'!P6,0) -> 0 | O31: =IF(E31>'Resumen'!$B$14,'Tramos_red'!Q6,0) -> 0 | P31: =IF(E31>'Resumen'!$B$14,'Tramos_red'!R6,0) -> 0 | Q31: =IF(E31<='Resumen'!$B$14,0,IF('Entradas'!$B$5=0,"sin U",IF(P31=0,"infinita",E31/('Entradas'!$B$5*P31)))) -> 0
A32: B3-P2-3 | B32: 3 | C32: ='Entradas'!A12 -> H2 | D32: ='Entradas'!A13 -> C3 | E32: ='Tramos_red'!M6*'Tramos_red'!U6*'Tramos_red'!Z6 -> 20000 | F32: =IF(E32>'Resumen'!$B$14,'Tramos_red'!J6,"") -> 120 | G32: =IF(E32>'Resumen'!$B$14,'Tramos_red'!I6,"") -> 115 | H32: =IF(E32>'Resumen'!$B$14,'Tramos_red'!K6,"") -> 90 | I32: =IF(E32>'Resumen'!$B$14,'Tramos_red'!L6,"") -> 96.666667 | J32: =IF(E32>'Resumen'!$B$14,'Tramos_red'!Z6,0) -> 1 | K32: =IF(E32>'Resumen'!$B$14,'Tramos_red'!U6,0) -> 1 | L32: =J32*'Entradas'!B12 -> 4000 | M32: =K32*'Entradas'!B13 -> 3000 | N32: =IF(E32>'Resumen'!$B$14,'Tramos_red'!P6,0) -> 23.333333 | O32: =IF(E32>'Resumen'!$B$14,'Tramos_red'!Q6,0) -> 25 | P32: =IF(E32>'Resumen'!$B$14,'Tramos_red'!R6,0) -> 24.157085 | Q32: =IF(E32<='Resumen'!$B$14,0,IF('Entradas'!$B$5=0,"sin U",IF(P32=0,"infinita",E32/('Entradas'!$B$5*P32)))) -> sin U
A33: B3-P2-4 | B33: 3 | C33: ='Entradas'!A12 -> H2 | D33: ='Entradas'!A14 -> C4 | E33: ='Tramos_red'!M6*'Tramos_red'!U6*'Tramos_red'!AA6 -> 0 | F33: =IF(E33>'Resumen'!$B$14,'Tramos_red'!J6,"") | G33: =IF(E33>'Resumen'!$B$14,'Tramos_red'!I6,"") | H33: =IF(E33>'Resumen'!$B$14,'Tramos_red'!K6,"") | I33: =IF(E33>'Resumen'!$B$14,'Tramos_red'!L6,"") | J33: =IF(E33>'Resumen'!$B$14,'Tramos_red'!AA6,0) -> 0 | K33: =IF(E33>'Resumen'!$B$14,'Tramos_red'!U6,0) -> 0 | L33: =J33*'Entradas'!B12 -> 0 | M33: =K33*'Entradas'!B14 -> 0 | N33: =IF(E33>'Resumen'!$B$14,'Tramos_red'!P6,0) -> 0 | O33: =IF(E33>'Resumen'!$B$14,'Tramos_red'!Q6,0) -> 0 | P33: =IF(E33>'Resumen'!$B$14,'Tramos_red'!R6,0) -> 0 | Q33: =IF(E33<='Resumen'!$B$14,0,IF('Entradas'!$B$5=0,"sin U",IF(P33=0,"infinita",E33/('Entradas'!$B$5*P33)))) -> 0
A34: B3-P3-1 | B34: 3 | C34: ='Entradas'!A13 -> C3 | D34: ='Entradas'!A11 -> H1 | E34: ='Tramos_red'!M6*'Tramos_red'!V6*'Tramos_red'!X6 -> 0 | F34: =IF(E34>'Resumen'!$B$14,'Tramos_red'!J6,"") | G34: =IF(E34>'Resumen'!$B$14,'Tramos_red'!I6,"") | H34: =IF(E34>'Resumen'!$B$14,'Tramos_red'!K6,"") | I34: =IF(E34>'Resumen'!$B$14,'Tramos_red'!L6,"") | J34: =IF(E34>'Resumen'!$B$14,'Tramos_red'!X6,0) -> 0 | K34: =IF(E34>'Resumen'!$B$14,'Tramos_red'!V6,0) -> 0 | L34: =J34*'Entradas'!B13 -> 0 | M34: =K34*'Entradas'!B11 -> 0 | N34: =IF(E34>'Resumen'!$B$14,'Tramos_red'!P6,0) -> 0 | O34: =IF(E34>'Resumen'!$B$14,'Tramos_red'!Q6,0) -> 0 | P34: =IF(E34>'Resumen'!$B$14,'Tramos_red'!R6,0) -> 0 | Q34: =IF(E34<='Resumen'!$B$14,0,IF('Entradas'!$B$5=0,"sin U",IF(P34=0,"infinita",E34/('Entradas'!$B$5*P34)))) -> 0
A35: B3-P3-2 | B35: 3 | C35: ='Entradas'!A13 -> C3 | D35: ='Entradas'!A12 -> H2 | E35: ='Tramos_red'!M6*'Tramos_red'!V6*'Tramos_red'!Y6 -> 0 | F35: =IF(E35>'Resumen'!$B$14,'Tramos_red'!J6,"") | G35: =IF(E35>'Resumen'!$B$14,'Tramos_red'!I6,"") | H35: =IF(E35>'Resumen'!$B$14,'Tramos_red'!K6,"") | I35: =IF(E35>'Resumen'!$B$14,'Tramos_red'!L6,"") | J35: =IF(E35>'Resumen'!$B$14,'Tramos_red'!Y6,0) -> 0 | K35: =IF(E35>'Resumen'!$B$14,'Tramos_red'!V6,0) -> 0 | L35: =J35*'Entradas'!B13 -> 0 | M35: =K35*'Entradas'!B12 -> 0 | N35: =IF(E35>'Resumen'!$B$14,'Tramos_red'!P6,0) -> 0 | O35: =IF(E35>'Resumen'!$B$14,'Tramos_red'!Q6,0) -> 0 | P35: =IF(E35>'Resumen'!$B$14,'Tramos_red'!R6,0) -> 0 | Q35: =IF(E35<='Resumen'!$B$14,0,IF('Entradas'!$B$5=0,"sin U",IF(P35=0,"infinita",E35/('Entradas'!$B$5*P35)))) -> 0
A36: B3-P3-4 | B36: 3 | C36: ='Entradas'!A13 -> C3 | D36: ='Entradas'!A14 -> C4 | E36: ='Tramos_red'!M6*'Tramos_red'!V6*'Tramos_red'!AA6 -> 0 | F36: =IF(E36>'Resumen'!$B$14,'Tramos_red'!J6,"") | G36: =IF(E36>'Resumen'!$B$14,'Tramos_red'!I6,"") | H36: =IF(E36>'Resumen'!$B$14,'Tramos_red'!K6,"") | I36: =IF(E36>'Resumen'!$B$14,'Tramos_red'!L6,"") | J36: =IF(E36>'Resumen'!$B$14,'Tramos_red'!AA6,0) -> 0 | K36: =IF(E36>'Resumen'!$B$14,'Tramos_red'!V6,0) -> 0 | L36: =J36*'Entradas'!B13 -> 0 | M36: =K36*'Entradas'!B14 -> 0 | N36: =IF(E36>'Resumen'!$B$14,'Tramos_red'!P6,0) -> 0 | O36: =IF(E36>'Resumen'!$B$14,'Tramos_red'!Q6,0) -> 0 | P36: =IF(E36>'Resumen'!$B$14,'Tramos_red'!R6,0) -> 0 | Q36: =IF(E36<='Resumen'!$B$14,0,IF('Entradas'!$B$5=0,"sin U",IF(P36=0,"infinita",E36/('Entradas'!$B$5*P36)))) -> 0
A37: B3-P4-1 | B37: 3 | C37: ='Entradas'!A14 -> C4 | D37: ='Entradas'!A11 -> H1 | E37: ='Tramos_red'!M6*'Tramos_red'!W6*'Tramos_red'!X6 -> 0 | F37: =IF(E37>'Resumen'!$B$14,'Tramos_red'!J6,"") | G37: =IF(E37>'Resumen'!$B$14,'Tramos_red'!I6,"") | H37: =IF(E37>'Resumen'!$B$14,'Tramos_red'!K6,"") | I37: =IF(E37>'Resumen'!$B$14,'Tramos_red'!L6,"") | J37: =IF(E37>'Resumen'!$B$14,'Tramos_red'!X6,0) -> 0 | K37: =IF(E37>'Resumen'!$B$14,'Tramos_red'!W6,0) -> 0 | L37: =J37*'Entradas'!B14 -> 0 | M37: =K37*'Entradas'!B11 -> 0 | N37: =IF(E37>'Resumen'!$B$14,'Tramos_red'!P6,0) -> 0 | O37: =IF(E37>'Resumen'!$B$14,'Tramos_red'!Q6,0) -> 0 | P37: =IF(E37>'Resumen'!$B$14,'Tramos_red'!R6,0) -> 0 | Q37: =IF(E37<='Resumen'!$B$14,0,IF('Entradas'!$B$5=0,"sin U",IF(P37=0,"infinita",E37/('Entradas'!$B$5*P37)))) -> 0
A38: B3-P4-2 | B38: 3 | C38: ='Entradas'!A14 -> C4 | D38: ='Entradas'!A12 -> H2 | E38: ='Tramos_red'!M6*'Tramos_red'!W6*'Tramos_red'!Y6 -> 0 | F38: =IF(E38>'Resumen'!$B$14,'Tramos_red'!J6,"") | G38: =IF(E38>'Resumen'!$B$14,'Tramos_red'!I6,"") | H38: =IF(E38>'Resumen'!$B$14,'Tramos_red'!K6,"") | I38: =IF(E38>'Resumen'!$B$14,'Tramos_red'!L6,"") | J38: =IF(E38>'Resumen'!$B$14,'Tramos_red'!Y6,0) -> 0 | K38: =IF(E38>'Resumen'!$B$14,'Tramos_red'!W6,0) -> 0 | L38: =J38*'Entradas'!B14 -> 0 | M38: =K38*'Entradas'!B12 -> 0 | N38: =IF(E38>'Resumen'!$B$14,'Tramos_red'!P6,0) -> 0 | O38: =IF(E38>'Resumen'!$B$14,'Tramos_red'!Q6,0) -> 0 | P38: =IF(E38>'Resumen'!$B$14,'Tramos_red'!R6,0) -> 0 | Q38: =IF(E38<='Resumen'!$B$14,0,IF('Entradas'!$B$5=0,"sin U",IF(P38=0,"infinita",E38/('Entradas'!$B$5*P38)))) -> 0
A39: B3-P4-3 | B39: 3 | C39: ='Entradas'!A14 -> C4 | D39: ='Entradas'!A13 -> C3 | E39: ='Tramos_red'!M6*'Tramos_red'!W6*'Tramos_red'!Z6 -> 0 | F39: =IF(E39>'Resumen'!$B$14,'Tramos_red'!J6,"") | G39: =IF(E39>'Resumen'!$B$14,'Tramos_red'!I6,"") | H39: =IF(E39>'Resumen'!$B$14,'Tramos_red'!K6,"") | I39: =IF(E39>'Resumen'!$B$14,'Tramos_red'!L6,"") | J39: =IF(E39>'Resumen'!$B$14,'Tramos_red'!Z6,0) -> 0 | K39: =IF(E39>'Resumen'!$B$14,'Tramos_red'!W6,0) -> 0 | L39: =J39*'Entradas'!B14 -> 0 | M39: =K39*'Entradas'!B13 -> 0 | N39: =IF(E39>'Resumen'!$B$14,'Tramos_red'!P6,0) -> 0 | O39: =IF(E39>'Resumen'!$B$14,'Tramos_red'!Q6,0) -> 0 | P39: =IF(E39>'Resumen'!$B$14,'Tramos_red'!R6,0) -> 0 | Q39: =IF(E39<='Resumen'!$B$14,0,IF('Entradas'!$B$5=0,"sin U",IF(P39=0,"infinita",E39/('Entradas'!$B$5*P39)))) -> 0
A40: B4-P1-2 | B40: 4 | C40: ='Entradas'!A11 -> H1 | D40: ='Entradas'!A12 -> H2 | E40: ='Tramos_red'!M7*'Tramos_red'!T7*'Tramos_red'!Y7 -> 0 | F40: =IF(E40>'Resumen'!$B$14,'Tramos_red'!J7,"") | G40: =IF(E40>'Resumen'!$B$14,'Tramos_red'!I7,"") | H40: =IF(E40>'Resumen'!$B$14,'Tramos_red'!K7,"") | I40: =IF(E40>'Resumen'!$B$14,'Tramos_red'!L7,"") | J40: =IF(E40>'Resumen'!$B$14,'Tramos_red'!Y7,0) -> 0 | K40: =IF(E40>'Resumen'!$B$14,'Tramos_red'!T7,0) -> 0 | L40: =J40*'Entradas'!B11 -> 0 | M40: =K40*'Entradas'!B12 -> 0 | N40: =IF(E40>'Resumen'!$B$14,'Tramos_red'!P7,0) -> 0 | O40: =IF(E40>'Resumen'!$B$14,'Tramos_red'!Q7,0) -> 0 | P40: =IF(E40>'Resumen'!$B$14,'Tramos_red'!R7,0) -> 0 | Q40: =IF(E40<='Resumen'!$B$14,0,IF('Entradas'!$B$5=0,"sin U",IF(P40=0,"infinita",E40/('Entradas'!$B$5*P40)))) -> 0
A41: B4-P1-3 | B41: 4 | C41: ='Entradas'!A11 -> H1 | D41: ='Entradas'!A13 -> C3 | E41: ='Tramos_red'!M7*'Tramos_red'!T7*'Tramos_red'!Z7 -> 2000 | F41: =IF(E41>'Resumen'!$B$14,'Tramos_red'!J7,"") -> 122 | G41: =IF(E41>'Resumen'!$B$14,'Tramos_red'!I7,"") -> 120 | H41: =IF(E41>'Resumen'!$B$14,'Tramos_red'!K7,"") -> 96.666667 | I41: =IF(E41>'Resumen'!$B$14,'Tramos_red'!L7,"") -> 100 | J41: =IF(E41>'Resumen'!$B$14,'Tramos_red'!Z7,0) -> 1 | K41: =IF(E41>'Resumen'!$B$14,'Tramos_red'!T7,0) -> 0.2 | L41: =J41*'Entradas'!B11 -> 1000 | M41: =K41*'Entradas'!B13 -> 600 | N41: =IF(E41>'Resumen'!$B$14,'Tramos_red'!P7,0) -> 22 | O41: =IF(E41>'Resumen'!$B$14,'Tramos_red'!Q7,0) -> 23.333333 | P41: =IF(E41>'Resumen'!$B$14,'Tramos_red'!R7,0) -> 22.660129 | Q41: =IF(E41<='Resumen'!$B$14,0,IF('Entradas'!$B$5=0,"sin U",IF(P41=0,"infinita",E41/('Entradas'!$B$5*P41)))) -> sin U
A42: B4-P1-4 | B42: 4 | C42: ='Entradas'!A11 -> H1 | D42: ='Entradas'!A14 -> C4 | E42: ='Tramos_red'!M7*'Tramos_red'!T7*'Tramos_red'!AA7 -> 0 | F42: =IF(E42>'Resumen'!$B$14,'Tramos_red'!J7,"") | G42: =IF(E42>'Resumen'!$B$14,'Tramos_red'!I7,"") | H42: =IF(E42>'Resumen'!$B$14,'Tramos_red'!K7,"") | I42: =IF(E42>'Resumen'!$B$14,'Tramos_red'!L7,"") | J42: =IF(E42>'Resumen'!$B$14,'Tramos_red'!AA7,0) -> 0 | K42: =IF(E42>'Resumen'!$B$14,'Tramos_red'!T7,0) -> 0 | L42: =J42*'Entradas'!B11 -> 0 | M42: =K42*'Entradas'!B14 -> 0 | N42: =IF(E42>'Resumen'!$B$14,'Tramos_red'!P7,0) -> 0 | O42: =IF(E42>'Resumen'!$B$14,'Tramos_red'!Q7,0) -> 0 | P42: =IF(E42>'Resumen'!$B$14,'Tramos_red'!R7,0) -> 0 | Q42: =IF(E42<='Resumen'!$B$14,0,IF('Entradas'!$B$5=0,"sin U",IF(P42=0,"infinita",E42/('Entradas'!$B$5*P42)))) -> 0
A43: B4-P2-1 | B43: 4 | C43: ='Entradas'!A12 -> H2 | D43: ='Entradas'!A11 -> H1 | E43: ='Tramos_red'!M7*'Tramos_red'!U7*'Tramos_red'!X7 -> 0 | F43: =IF(E43>'Resumen'!$B$14,'Tramos_red'!J7,"") | G43: =IF(E43>'Resumen'!$B$14,'Tramos_red'!I7,"") | H43: =IF(E43>'Resumen'!$B$14,'Tramos_red'!K7,"") | I43: =IF(E43>'Resumen'!$B$14,'Tramos_red'!L7,"") | J43: =IF(E43>'Resumen'!$B$14,'Tramos_red'!X7,0) -> 0 | K43: =IF(E43>'Resumen'!$B$14,'Tramos_red'!U7,0) -> 0 | L43: =J43*'Entradas'!B12 -> 0 | M43: =K43*'Entradas'!B11 -> 0 | N43: =IF(E43>'Resumen'!$B$14,'Tramos_red'!P7,0) -> 0 | O43: =IF(E43>'Resumen'!$B$14,'Tramos_red'!Q7,0) -> 0 | P43: =IF(E43>'Resumen'!$B$14,'Tramos_red'!R7,0) -> 0 | Q43: =IF(E43<='Resumen'!$B$14,0,IF('Entradas'!$B$5=0,"sin U",IF(P43=0,"infinita",E43/('Entradas'!$B$5*P43)))) -> 0
A44: B4-P2-3 | B44: 4 | C44: ='Entradas'!A12 -> H2 | D44: ='Entradas'!A13 -> C3 | E44: ='Tramos_red'!M7*'Tramos_red'!U7*'Tramos_red'!Z7 -> 8000 | F44: =IF(E44>'Resumen'!$B$14,'Tramos_red'!J7,"") -> 122 | G44: =IF(E44>'Resumen'!$B$14,'Tramos_red'!I7,"") -> 120 | H44: =IF(E44>'Resumen'!$B$14,'Tramos_red'!K7,"") -> 96.666667 | I44: =IF(E44>'Resumen'!$B$14,'Tramos_red'!L7,"") -> 100 | J44: =IF(E44>'Resumen'!$B$14,'Tramos_red'!Z7,0) -> 1 | K44: =IF(E44>'Resumen'!$B$14,'Tramos_red'!U7,0) -> 0.8 | L44: =J44*'Entradas'!B12 -> 4000 | M44: =K44*'Entradas'!B13 -> 2400 | N44: =IF(E44>'Resumen'!$B$14,'Tramos_red'!P7,0) -> 22 | O44: =IF(E44>'Resumen'!$B$14,'Tramos_red'!Q7,0) -> 23.333333 | P44: =IF(E44>'Resumen'!$B$14,'Tramos_red'!R7,0) -> 22.660129 | Q44: =IF(E44<='Resumen'!$B$14,0,IF('Entradas'!$B$5=0,"sin U",IF(P44=0,"infinita",E44/('Entradas'!$B$5*P44)))) -> sin U
A45: B4-P2-4 | B45: 4 | C45: ='Entradas'!A12 -> H2 | D45: ='Entradas'!A14 -> C4 | E45: ='Tramos_red'!M7*'Tramos_red'!U7*'Tramos_red'!AA7 -> 0 | F45: =IF(E45>'Resumen'!$B$14,'Tramos_red'!J7,"") | G45: =IF(E45>'Resumen'!$B$14,'Tramos_red'!I7,"") | H45: =IF(E45>'Resumen'!$B$14,'Tramos_red'!K7,"") | I45: =IF(E45>'Resumen'!$B$14,'Tramos_red'!L7,"") | J45: =IF(E45>'Resumen'!$B$14,'Tramos_red'!AA7,0) -> 0 | K45: =IF(E45>'Resumen'!$B$14,'Tramos_red'!U7,0) -> 0 | L45: =J45*'Entradas'!B12 -> 0 | M45: =K45*'Entradas'!B14 -> 0 | N45: =IF(E45>'Resumen'!$B$14,'Tramos_red'!P7,0) -> 0 | O45: =IF(E45>'Resumen'!$B$14,'Tramos_red'!Q7,0) -> 0 | P45: =IF(E45>'Resumen'!$B$14,'Tramos_red'!R7,0) -> 0 | Q45: =IF(E45<='Resumen'!$B$14,0,IF('Entradas'!$B$5=0,"sin U",IF(P45=0,"infinita",E45/('Entradas'!$B$5*P45)))) -> 0
A46: B4-P3-1 | B46: 4 | C46: ='Entradas'!A13 -> C3 | D46: ='Entradas'!A11 -> H1 | E46: ='Tramos_red'!M7*'Tramos_red'!V7*'Tramos_red'!X7 -> 0 | F46: =IF(E46>'Resumen'!$B$14,'Tramos_red'!J7,"") | G46: =IF(E46>'Resumen'!$B$14,'Tramos_red'!I7,"") | H46: =IF(E46>'Resumen'!$B$14,'Tramos_red'!K7,"") | I46: =IF(E46>'Resumen'!$B$14,'Tramos_red'!L7,"") | J46: =IF(E46>'Resumen'!$B$14,'Tramos_red'!X7,0) -> 0 | K46: =IF(E46>'Resumen'!$B$14,'Tramos_red'!V7,0) -> 0 | L46: =J46*'Entradas'!B13 -> 0 | M46: =K46*'Entradas'!B11 -> 0 | N46: =IF(E46>'Resumen'!$B$14,'Tramos_red'!P7,0) -> 0 | O46: =IF(E46>'Resumen'!$B$14,'Tramos_red'!Q7,0) -> 0 | P46: =IF(E46>'Resumen'!$B$14,'Tramos_red'!R7,0) -> 0 | Q46: =IF(E46<='Resumen'!$B$14,0,IF('Entradas'!$B$5=0,"sin U",IF(P46=0,"infinita",E46/('Entradas'!$B$5*P46)))) -> 0
A47: B4-P3-2 | B47: 4 | C47: ='Entradas'!A13 -> C3 | D47: ='Entradas'!A12 -> H2 | E47: ='Tramos_red'!M7*'Tramos_red'!V7*'Tramos_red'!Y7 -> 0 | F47: =IF(E47>'Resumen'!$B$14,'Tramos_red'!J7,"") | G47: =IF(E47>'Resumen'!$B$14,'Tramos_red'!I7,"") | H47: =IF(E47>'Resumen'!$B$14,'Tramos_red'!K7,"") | I47: =IF(E47>'Resumen'!$B$14,'Tramos_red'!L7,"") | J47: =IF(E47>'Resumen'!$B$14,'Tramos_red'!Y7,0) -> 0 | K47: =IF(E47>'Resumen'!$B$14,'Tramos_red'!V7,0) -> 0 | L47: =J47*'Entradas'!B13 -> 0 | M47: =K47*'Entradas'!B12 -> 0 | N47: =IF(E47>'Resumen'!$B$14,'Tramos_red'!P7,0) -> 0 | O47: =IF(E47>'Resumen'!$B$14,'Tramos_red'!Q7,0) -> 0 | P47: =IF(E47>'Resumen'!$B$14,'Tramos_red'!R7,0) -> 0 | Q47: =IF(E47<='Resumen'!$B$14,0,IF('Entradas'!$B$5=0,"sin U",IF(P47=0,"infinita",E47/('Entradas'!$B$5*P47)))) -> 0
A48: B4-P3-4 | B48: 4 | C48: ='Entradas'!A13 -> C3 | D48: ='Entradas'!A14 -> C4 | E48: ='Tramos_red'!M7*'Tramos_red'!V7*'Tramos_red'!AA7 -> 0 | F48: =IF(E48>'Resumen'!$B$14,'Tramos_red'!J7,"") | G48: =IF(E48>'Resumen'!$B$14,'Tramos_red'!I7,"") | H48: =IF(E48>'Resumen'!$B$14,'Tramos_red'!K7,"") | I48: =IF(E48>'Resumen'!$B$14,'Tramos_red'!L7,"") | J48: =IF(E48>'Resumen'!$B$14,'Tramos_red'!AA7,0) -> 0 | K48: =IF(E48>'Resumen'!$B$14,'Tramos_red'!V7,0) -> 0 | L48: =J48*'Entradas'!B13 -> 0 | M48: =K48*'Entradas'!B14 -> 0 | N48: =IF(E48>'Resumen'!$B$14,'Tramos_red'!P7,0) -> 0 | O48: =IF(E48>'Resumen'!$B$14,'Tramos_red'!Q7,0) -> 0 | P48: =IF(E48>'Resumen'!$B$14,'Tramos_red'!R7,0) -> 0 | Q48: =IF(E48<='Resumen'!$B$14,0,IF('Entradas'!$B$5=0,"sin U",IF(P48=0,"infinita",E48/('Entradas'!$B$5*P48)))) -> 0
A49: B4-P4-1 | B49: 4 | C49: ='Entradas'!A14 -> C4 | D49: ='Entradas'!A11 -> H1 | E49: ='Tramos_red'!M7*'Tramos_red'!W7*'Tramos_red'!X7 -> 0 | F49: =IF(E49>'Resumen'!$B$14,'Tramos_red'!J7,"") | G49: =IF(E49>'Resumen'!$B$14,'Tramos_red'!I7,"") | H49: =IF(E49>'Resumen'!$B$14,'Tramos_red'!K7,"") | I49: =IF(E49>'Resumen'!$B$14,'Tramos_red'!L7,"") | J49: =IF(E49>'Resumen'!$B$14,'Tramos_red'!X7,0) -> 0 | K49: =IF(E49>'Resumen'!$B$14,'Tramos_red'!W7,0) -> 0 | L49: =J49*'Entradas'!B14 -> 0 | M49: =K49*'Entradas'!B11 -> 0 | N49: =IF(E49>'Resumen'!$B$14,'Tramos_red'!P7,0) -> 0 | O49: =IF(E49>'Resumen'!$B$14,'Tramos_red'!Q7,0) -> 0 | P49: =IF(E49>'Resumen'!$B$14,'Tramos_red'!R7,0) -> 0 | Q49: =IF(E49<='Resumen'!$B$14,0,IF('Entradas'!$B$5=0,"sin U",IF(P49=0,"infinita",E49/('Entradas'!$B$5*P49)))) -> 0
A50: B4-P4-2 | B50: 4 | C50: ='Entradas'!A14 -> C4 | D50: ='Entradas'!A12 -> H2 | E50: ='Tramos_red'!M7*'Tramos_red'!W7*'Tramos_red'!Y7 -> 0 | F50: =IF(E50>'Resumen'!$B$14,'Tramos_red'!J7,"") | G50: =IF(E50>'Resumen'!$B$14,'Tramos_red'!I7,"") | H50: =IF(E50>'Resumen'!$B$14,'Tramos_red'!K7,"") | I50: =IF(E50>'Resumen'!$B$14,'Tramos_red'!L7,"") | J50: =IF(E50>'Resumen'!$B$14,'Tramos_red'!Y7,0) -> 0 | K50: =IF(E50>'Resumen'!$B$14,'Tramos_red'!W7,0) -> 0 | L50: =J50*'Entradas'!B14 -> 0 | M50: =K50*'Entradas'!B12 -> 0 | N50: =IF(E50>'Resumen'!$B$14,'Tramos_red'!P7,0) -> 0 | O50: =IF(E50>'Resumen'!$B$14,'Tramos_red'!Q7,0) -> 0 | P50: =IF(E50>'Resumen'!$B$14,'Tramos_red'!R7,0) -> 0 | Q50: =IF(E50<='Resumen'!$B$14,0,IF('Entradas'!$B$5=0,"sin U",IF(P50=0,"infinita",E50/('Entradas'!$B$5*P50)))) -> 0
A51: B4-P4-3 | B51: 4 | C51: ='Entradas'!A14 -> C4 | D51: ='Entradas'!A13 -> C3 | E51: ='Tramos_red'!M7*'Tramos_red'!W7*'Tramos_red'!Z7 -> 0 | F51: =IF(E51>'Resumen'!$B$14,'Tramos_red'!J7,"") | G51: =IF(E51>'Resumen'!$B$14,'Tramos_red'!I7,"") | H51: =IF(E51>'Resumen'!$B$14,'Tramos_red'!K7,"") | I51: =IF(E51>'Resumen'!$B$14,'Tramos_red'!L7,"") | J51: =IF(E51>'Resumen'!$B$14,'Tramos_red'!Z7,0) -> 0 | K51: =IF(E51>'Resumen'!$B$14,'Tramos_red'!W7,0) -> 0 | L51: =J51*'Entradas'!B14 -> 0 | M51: =K51*'Entradas'!B13 -> 0 | N51: =IF(E51>'Resumen'!$B$14,'Tramos_red'!P7,0) -> 0 | O51: =IF(E51>'Resumen'!$B$14,'Tramos_red'!Q7,0) -> 0 | P51: =IF(E51>'Resumen'!$B$14,'Tramos_red'!R7,0) -> 0 | Q51: =IF(E51<='Resumen'!$B$14,0,IF('Entradas'!$B$5=0,"sin U",IF(P51=0,"infinita",E51/('Entradas'!$B$5*P51)))) -> 0
A52: B5-P1-2 | B52: 5 | C52: ='Entradas'!A11 -> H1 | D52: ='Entradas'!A12 -> H2 | E52: ='Tramos_red'!M8*'Tramos_red'!T8*'Tramos_red'!Y8 -> 0 | F52: =IF(E52>'Resumen'!$B$14,'Tramos_red'!J8,"") | G52: =IF(E52>'Resumen'!$B$14,'Tramos_red'!I8,"") | H52: =IF(E52>'Resumen'!$B$14,'Tramos_red'!K8,"") | I52: =IF(E52>'Resumen'!$B$14,'Tramos_red'!L8,"") | J52: =IF(E52>'Resumen'!$B$14,'Tramos_red'!Y8,0) -> 0 | K52: =IF(E52>'Resumen'!$B$14,'Tramos_red'!T8,0) -> 0 | L52: =J52*'Entradas'!B11 -> 0 | M52: =K52*'Entradas'!B12 -> 0 | N52: =IF(E52>'Resumen'!$B$14,'Tramos_red'!P8,0) -> 0 | O52: =IF(E52>'Resumen'!$B$14,'Tramos_red'!Q8,0) -> 0 | P52: =IF(E52>'Resumen'!$B$14,'Tramos_red'!R8,0) -> 0 | Q52: =IF(E52<='Resumen'!$B$14,0,IF('Entradas'!$B$5=0,"sin U",IF(P52=0,"infinita",E52/('Entradas'!$B$5*P52)))) -> 0
A53: B5-P1-3 | B53: 5 | C53: ='Entradas'!A11 -> H1 | D53: ='Entradas'!A13 -> C3 | E53: ='Tramos_red'!M8*'Tramos_red'!T8*'Tramos_red'!Z8 -> 8000 | F53: =IF(E53>'Resumen'!$B$14,'Tramos_red'!J8,"") -> 130 | G53: =IF(E53>'Resumen'!$B$14,'Tramos_red'!I8,"") -> 122 | H53: =IF(E53>'Resumen'!$B$14,'Tramos_red'!K8,"") -> 100 | I53: =IF(E53>'Resumen'!$B$14,'Tramos_red'!L8,"") -> 113.33333 | J53: =IF(E53>'Resumen'!$B$14,'Tramos_red'!Z8,0) -> 1 | K53: =IF(E53>'Resumen'!$B$14,'Tramos_red'!T8,0) -> 0.2 | L53: =J53*'Entradas'!B11 -> 1000 | M53: =K53*'Entradas'!B13 -> 600 | N53: =IF(E53>'Resumen'!$B$14,'Tramos_red'!P8,0) -> 16.666667 | O53: =IF(E53>'Resumen'!$B$14,'Tramos_red'!Q8,0) -> 22 | P53: =IF(E53>'Resumen'!$B$14,'Tramos_red'!R8,0) -> 19.2101 | Q53: =IF(E53<='Resumen'!$B$14,0,IF('Entradas'!$B$5=0,"sin U",IF(P53=0,"infinita",E53/('Entradas'!$B$5*P53)))) -> sin U
A54: B5-P1-4 | B54: 5 | C54: ='Entradas'!A11 -> H1 | D54: ='Entradas'!A14 -> C4 | E54: ='Tramos_red'!M8*'Tramos_red'!T8*'Tramos_red'!AA8 -> 0 | F54: =IF(E54>'Resumen'!$B$14,'Tramos_red'!J8,"") | G54: =IF(E54>'Resumen'!$B$14,'Tramos_red'!I8,"") | H54: =IF(E54>'Resumen'!$B$14,'Tramos_red'!K8,"") | I54: =IF(E54>'Resumen'!$B$14,'Tramos_red'!L8,"") | J54: =IF(E54>'Resumen'!$B$14,'Tramos_red'!AA8,0) -> 0 | K54: =IF(E54>'Resumen'!$B$14,'Tramos_red'!T8,0) -> 0 | L54: =J54*'Entradas'!B11 -> 0 | M54: =K54*'Entradas'!B14 -> 0 | N54: =IF(E54>'Resumen'!$B$14,'Tramos_red'!P8,0) -> 0 | O54: =IF(E54>'Resumen'!$B$14,'Tramos_red'!Q8,0) -> 0 | P54: =IF(E54>'Resumen'!$B$14,'Tramos_red'!R8,0) -> 0 | Q54: =IF(E54<='Resumen'!$B$14,0,IF('Entradas'!$B$5=0,"sin U",IF(P54=0,"infinita",E54/('Entradas'!$B$5*P54)))) -> 0
A55: B5-P2-1 | B55: 5 | C55: ='Entradas'!A12 -> H2 | D55: ='Entradas'!A11 -> H1 | E55: ='Tramos_red'!M8*'Tramos_red'!U8*'Tramos_red'!X8 -> 0 | F55: =IF(E55>'Resumen'!$B$14,'Tramos_red'!J8,"") | G55: =IF(E55>'Resumen'!$B$14,'Tramos_red'!I8,"") | H55: =IF(E55>'Resumen'!$B$14,'Tramos_red'!K8,"") | I55: =IF(E55>'Resumen'!$B$14,'Tramos_red'!L8,"") | J55: =IF(E55>'Resumen'!$B$14,'Tramos_red'!X8,0) -> 0 | K55: =IF(E55>'Resumen'!$B$14,'Tramos_red'!U8,0) -> 0 | L55: =J55*'Entradas'!B12 -> 0 | M55: =K55*'Entradas'!B11 -> 0 | N55: =IF(E55>'Resumen'!$B$14,'Tramos_red'!P8,0) -> 0 | O55: =IF(E55>'Resumen'!$B$14,'Tramos_red'!Q8,0) -> 0 | P55: =IF(E55>'Resumen'!$B$14,'Tramos_red'!R8,0) -> 0 | Q55: =IF(E55<='Resumen'!$B$14,0,IF('Entradas'!$B$5=0,"sin U",IF(P55=0,"infinita",E55/('Entradas'!$B$5*P55)))) -> 0
A56: B5-P2-3 | B56: 5 | C56: ='Entradas'!A12 -> H2 | D56: ='Entradas'!A13 -> C3 | E56: ='Tramos_red'!M8*'Tramos_red'!U8*'Tramos_red'!Z8 -> 32000 | F56: =IF(E56>'Resumen'!$B$14,'Tramos_red'!J8,"") -> 130 | G56: =IF(E56>'Resumen'!$B$14,'Tramos_red'!I8,"") -> 122 | H56: =IF(E56>'Resumen'!$B$14,'Tramos_red'!K8,"") -> 100 | I56: =IF(E56>'Resumen'!$B$14,'Tramos_red'!L8,"") -> 113.33333 | J56: =IF(E56>'Resumen'!$B$14,'Tramos_red'!Z8,0) -> 1 | K56: =IF(E56>'Resumen'!$B$14,'Tramos_red'!U8,0) -> 0.8 | L56: =J56*'Entradas'!B12 -> 4000 | M56: =K56*'Entradas'!B13 -> 2400 | N56: =IF(E56>'Resumen'!$B$14,'Tramos_red'!P8,0) -> 16.666667 | O56: =IF(E56>'Resumen'!$B$14,'Tramos_red'!Q8,0) -> 22 | P56: =IF(E56>'Resumen'!$B$14,'Tramos_red'!R8,0) -> 19.2101 | Q56: =IF(E56<='Resumen'!$B$14,0,IF('Entradas'!$B$5=0,"sin U",IF(P56=0,"infinita",E56/('Entradas'!$B$5*P56)))) -> sin U
A57: B5-P2-4 | B57: 5 | C57: ='Entradas'!A12 -> H2 | D57: ='Entradas'!A14 -> C4 | E57: ='Tramos_red'!M8*'Tramos_red'!U8*'Tramos_red'!AA8 -> 0 | F57: =IF(E57>'Resumen'!$B$14,'Tramos_red'!J8,"") | G57: =IF(E57>'Resumen'!$B$14,'Tramos_red'!I8,"") | H57: =IF(E57>'Resumen'!$B$14,'Tramos_red'!K8,"") | I57: =IF(E57>'Resumen'!$B$14,'Tramos_red'!L8,"") | J57: =IF(E57>'Resumen'!$B$14,'Tramos_red'!AA8,0) -> 0 | K57: =IF(E57>'Resumen'!$B$14,'Tramos_red'!U8,0) -> 0 | L57: =J57*'Entradas'!B12 -> 0 | M57: =K57*'Entradas'!B14 -> 0 | N57: =IF(E57>'Resumen'!$B$14,'Tramos_red'!P8,0) -> 0 | O57: =IF(E57>'Resumen'!$B$14,'Tramos_red'!Q8,0) -> 0 | P57: =IF(E57>'Resumen'!$B$14,'Tramos_red'!R8,0) -> 0 | Q57: =IF(E57<='Resumen'!$B$14,0,IF('Entradas'!$B$5=0,"sin U",IF(P57=0,"infinita",E57/('Entradas'!$B$5*P57)))) -> 0
A58: B5-P3-1 | B58: 5 | C58: ='Entradas'!A13 -> C3 | D58: ='Entradas'!A11 -> H1 | E58: ='Tramos_red'!M8*'Tramos_red'!V8*'Tramos_red'!X8 -> 0 | F58: =IF(E58>'Resumen'!$B$14,'Tramos_red'!J8,"") | G58: =IF(E58>'Resumen'!$B$14,'Tramos_red'!I8,"") | H58: =IF(E58>'Resumen'!$B$14,'Tramos_red'!K8,"") | I58: =IF(E58>'Resumen'!$B$14,'Tramos_red'!L8,"") | J58: =IF(E58>'Resumen'!$B$14,'Tramos_red'!X8,0) -> 0 | K58: =IF(E58>'Resumen'!$B$14,'Tramos_red'!V8,0) -> 0 | L58: =J58*'Entradas'!B13 -> 0 | M58: =K58*'Entradas'!B11 -> 0 | N58: =IF(E58>'Resumen'!$B$14,'Tramos_red'!P8,0) -> 0 | O58: =IF(E58>'Resumen'!$B$14,'Tramos_red'!Q8,0) -> 0 | P58: =IF(E58>'Resumen'!$B$14,'Tramos_red'!R8,0) -> 0 | Q58: =IF(E58<='Resumen'!$B$14,0,IF('Entradas'!$B$5=0,"sin U",IF(P58=0,"infinita",E58/('Entradas'!$B$5*P58)))) -> 0
A59: B5-P3-2 | B59: 5 | C59: ='Entradas'!A13 -> C3 | D59: ='Entradas'!A12 -> H2 | E59: ='Tramos_red'!M8*'Tramos_red'!V8*'Tramos_red'!Y8 -> 0 | F59: =IF(E59>'Resumen'!$B$14,'Tramos_red'!J8,"") | G59: =IF(E59>'Resumen'!$B$14,'Tramos_red'!I8,"") | H59: =IF(E59>'Resumen'!$B$14,'Tramos_red'!K8,"") | I59: =IF(E59>'Resumen'!$B$14,'Tramos_red'!L8,"") | J59: =IF(E59>'Resumen'!$B$14,'Tramos_red'!Y8,0) -> 0 | K59: =IF(E59>'Resumen'!$B$14,'Tramos_red'!V8,0) -> 0 | L59: =J59*'Entradas'!B13 -> 0 | M59: =K59*'Entradas'!B12 -> 0 | N59: =IF(E59>'Resumen'!$B$14,'Tramos_red'!P8,0) -> 0 | O59: =IF(E59>'Resumen'!$B$14,'Tramos_red'!Q8,0) -> 0 | P59: =IF(E59>'Resumen'!$B$14,'Tramos_red'!R8,0) -> 0 | Q59: =IF(E59<='Resumen'!$B$14,0,IF('Entradas'!$B$5=0,"sin U",IF(P59=0,"infinita",E59/('Entradas'!$B$5*P59)))) -> 0
A60: B5-P3-4 | B60: 5 | C60: ='Entradas'!A13 -> C3 | D60: ='Entradas'!A14 -> C4 | E60: ='Tramos_red'!M8*'Tramos_red'!V8*'Tramos_red'!AA8 -> 0 | F60: =IF(E60>'Resumen'!$B$14,'Tramos_red'!J8,"") | G60: =IF(E60>'Resumen'!$B$14,'Tramos_red'!I8,"") | H60: =IF(E60>'Resumen'!$B$14,'Tramos_red'!K8,"") | I60: =IF(E60>'Resumen'!$B$14,'Tramos_red'!L8,"") | J60: =IF(E60>'Resumen'!$B$14,'Tramos_red'!AA8,0) -> 0 | K60: =IF(E60>'Resumen'!$B$14,'Tramos_red'!V8,0) -> 0 | L60: =J60*'Entradas'!B13 -> 0 | M60: =K60*'Entradas'!B14 -> 0 | N60: =IF(E60>'Resumen'!$B$14,'Tramos_red'!P8,0) -> 0 | O60: =IF(E60>'Resumen'!$B$14,'Tramos_red'!Q8,0) -> 0 | P60: =IF(E60>'Resumen'!$B$14,'Tramos_red'!R8,0) -> 0 | Q60: =IF(E60<='Resumen'!$B$14,0,IF('Entradas'!$B$5=0,"sin U",IF(P60=0,"infinita",E60/('Entradas'!$B$5*P60)))) -> 0
A61: B5-P4-1 | B61: 5 | C61: ='Entradas'!A14 -> C4 | D61: ='Entradas'!A11 -> H1 | E61: ='Tramos_red'!M8*'Tramos_red'!W8*'Tramos_red'!X8 -> 0 | F61: =IF(E61>'Resumen'!$B$14,'Tramos_red'!J8,"") | G61: =IF(E61>'Resumen'!$B$14,'Tramos_red'!I8,"") | H61: =IF(E61>'Resumen'!$B$14,'Tramos_red'!K8,"") | I61: =IF(E61>'Resumen'!$B$14,'Tramos_red'!L8,"") | J61: =IF(E61>'Resumen'!$B$14,'Tramos_red'!X8,0) -> 0 | K61: =IF(E61>'Resumen'!$B$14,'Tramos_red'!W8,0) -> 0 | L61: =J61*'Entradas'!B14 -> 0 | M61: =K61*'Entradas'!B11 -> 0 | N61: =IF(E61>'Resumen'!$B$14,'Tramos_red'!P8,0) -> 0 | O61: =IF(E61>'Resumen'!$B$14,'Tramos_red'!Q8,0) -> 0 | P61: =IF(E61>'Resumen'!$B$14,'Tramos_red'!R8,0) -> 0 | Q61: =IF(E61<='Resumen'!$B$14,0,IF('Entradas'!$B$5=0,"sin U",IF(P61=0,"infinita",E61/('Entradas'!$B$5*P61)))) -> 0
A62: B5-P4-2 | B62: 5 | C62: ='Entradas'!A14 -> C4 | D62: ='Entradas'!A12 -> H2 | E62: ='Tramos_red'!M8*'Tramos_red'!W8*'Tramos_red'!Y8 -> 0 | F62: =IF(E62>'Resumen'!$B$14,'Tramos_red'!J8,"") | G62: =IF(E62>'Resumen'!$B$14,'Tramos_red'!I8,"") | H62: =IF(E62>'Resumen'!$B$14,'Tramos_red'!K8,"") | I62: =IF(E62>'Resumen'!$B$14,'Tramos_red'!L8,"") | J62: =IF(E62>'Resumen'!$B$14,'Tramos_red'!Y8,0) -> 0 | K62: =IF(E62>'Resumen'!$B$14,'Tramos_red'!W8,0) -> 0 | L62: =J62*'Entradas'!B14 -> 0 | M62: =K62*'Entradas'!B12 -> 0 | N62: =IF(E62>'Resumen'!$B$14,'Tramos_red'!P8,0) -> 0 | O62: =IF(E62>'Resumen'!$B$14,'Tramos_red'!Q8,0) -> 0 | P62: =IF(E62>'Resumen'!$B$14,'Tramos_red'!R8,0) -> 0 | Q62: =IF(E62<='Resumen'!$B$14,0,IF('Entradas'!$B$5=0,"sin U",IF(P62=0,"infinita",E62/('Entradas'!$B$5*P62)))) -> 0
A63: B5-P4-3 | B63: 5 | C63: ='Entradas'!A14 -> C4 | D63: ='Entradas'!A13 -> C3 | E63: ='Tramos_red'!M8*'Tramos_red'!W8*'Tramos_red'!Z8 -> 0 | F63: =IF(E63>'Resumen'!$B$14,'Tramos_red'!J8,"") | G63: =IF(E63>'Resumen'!$B$14,'Tramos_red'!I8,"") | H63: =IF(E63>'Resumen'!$B$14,'Tramos_red'!K8,"") | I63: =IF(E63>'Resumen'!$B$14,'Tramos_red'!L8,"") | J63: =IF(E63>'Resumen'!$B$14,'Tramos_red'!Z8,0) -> 0 | K63: =IF(E63>'Resumen'!$B$14,'Tramos_red'!W8,0) -> 0 | L63: =J63*'Entradas'!B14 -> 0 | M63: =K63*'Entradas'!B13 -> 0 | N63: =IF(E63>'Resumen'!$B$14,'Tramos_red'!P8,0) -> 0 | O63: =IF(E63>'Resumen'!$B$14,'Tramos_red'!Q8,0) -> 0 | P63: =IF(E63>'Resumen'!$B$14,'Tramos_red'!R8,0) -> 0 | Q63: =IF(E63<='Resumen'!$B$14,0,IF('Entradas'!$B$5=0,"sin U",IF(P63=0,"infinita",E63/('Entradas'!$B$5*P63)))) -> 0
A64: B6-P1-2 | B64: 6 | C64: ='Entradas'!A11 -> H1 | D64: ='Entradas'!A12 -> H2 | E64: ='Tramos_red'!M9*'Tramos_red'!T9*'Tramos_red'!Y9 -> 0 | F64: =IF(E64>'Resumen'!$B$14,'Tramos_red'!J9,"") | G64: =IF(E64>'Resumen'!$B$14,'Tramos_red'!I9,"") | H64: =IF(E64>'Resumen'!$B$14,'Tramos_red'!K9,"") | I64: =IF(E64>'Resumen'!$B$14,'Tramos_red'!L9,"") | J64: =IF(E64>'Resumen'!$B$14,'Tramos_red'!Y9,0) -> 0 | K64: =IF(E64>'Resumen'!$B$14,'Tramos_red'!T9,0) -> 0 | L64: =J64*'Entradas'!B11 -> 0 | M64: =K64*'Entradas'!B12 -> 0 | N64: =IF(E64>'Resumen'!$B$14,'Tramos_red'!P9,0) -> 0 | O64: =IF(E64>'Resumen'!$B$14,'Tramos_red'!Q9,0) -> 0 | P64: =IF(E64>'Resumen'!$B$14,'Tramos_red'!R9,0) -> 0 | Q64: =IF(E64<='Resumen'!$B$14,0,IF('Entradas'!$B$5=0,"sin U",IF(P64=0,"infinita",E64/('Entradas'!$B$5*P64)))) -> 0
A65: B6-P1-3 | B65: 6 | C65: ='Entradas'!A11 -> H1 | D65: ='Entradas'!A13 -> C3 | E65: ='Tramos_red'!M9*'Tramos_red'!T9*'Tramos_red'!Z9 -> 4000 | F65: =IF(E65>'Resumen'!$B$14,'Tramos_red'!J9,"") -> 134 | G65: =IF(E65>'Resumen'!$B$14,'Tramos_red'!I9,"") -> 130 | H65: =IF(E65>'Resumen'!$B$14,'Tramos_red'!K9,"") -> 113.33333 | I65: =IF(E65>'Resumen'!$B$14,'Tramos_red'!L9,"") -> 120 | J65: =IF(E65>'Resumen'!$B$14,'Tramos_red'!Z9,0) -> 1 | K65: =IF(E65>'Resumen'!$B$14,'Tramos_red'!T9,0) -> 0.2 | L65: =J65*'Entradas'!B11 -> 1000 | M65: =K65*'Entradas'!B13 -> 600 | N65: =IF(E65>'Resumen'!$B$14,'Tramos_red'!P9,0) -> 14 | O65: =IF(E65>'Resumen'!$B$14,'Tramos_red'!Q9,0) -> 16.666667 | P65: =IF(E65>'Resumen'!$B$14,'Tramos_red'!R9,0) -> 15.294608 | Q65: =IF(E65<='Resumen'!$B$14,0,IF('Entradas'!$B$5=0,"sin U",IF(P65=0,"infinita",E65/('Entradas'!$B$5*P65)))) -> sin U
A66: B6-P1-4 | B66: 6 | C66: ='Entradas'!A11 -> H1 | D66: ='Entradas'!A14 -> C4 | E66: ='Tramos_red'!M9*'Tramos_red'!T9*'Tramos_red'!AA9 -> 0 | F66: =IF(E66>'Resumen'!$B$14,'Tramos_red'!J9,"") | G66: =IF(E66>'Resumen'!$B$14,'Tramos_red'!I9,"") | H66: =IF(E66>'Resumen'!$B$14,'Tramos_red'!K9,"") | I66: =IF(E66>'Resumen'!$B$14,'Tramos_red'!L9,"") | J66: =IF(E66>'Resumen'!$B$14,'Tramos_red'!AA9,0) -> 0 | K66: =IF(E66>'Resumen'!$B$14,'Tramos_red'!T9,0) -> 0 | L66: =J66*'Entradas'!B11 -> 0 | M66: =K66*'Entradas'!B14 -> 0 | N66: =IF(E66>'Resumen'!$B$14,'Tramos_red'!P9,0) -> 0 | O66: =IF(E66>'Resumen'!$B$14,'Tramos_red'!Q9,0) -> 0 | P66: =IF(E66>'Resumen'!$B$14,'Tramos_red'!R9,0) -> 0 | Q66: =IF(E66<='Resumen'!$B$14,0,IF('Entradas'!$B$5=0,"sin U",IF(P66=0,"infinita",E66/('Entradas'!$B$5*P66)))) -> 0
A67: B6-P2-1 | B67: 6 | C67: ='Entradas'!A12 -> H2 | D67: ='Entradas'!A11 -> H1 | E67: ='Tramos_red'!M9*'Tramos_red'!U9*'Tramos_red'!X9 -> 0 | F67: =IF(E67>'Resumen'!$B$14,'Tramos_red'!J9,"") | G67: =IF(E67>'Resumen'!$B$14,'Tramos_red'!I9,"") | H67: =IF(E67>'Resumen'!$B$14,'Tramos_red'!K9,"") | I67: =IF(E67>'Resumen'!$B$14,'Tramos_red'!L9,"") | J67: =IF(E67>'Resumen'!$B$14,'Tramos_red'!X9,0) -> 0 | K67: =IF(E67>'Resumen'!$B$14,'Tramos_red'!U9,0) -> 0 | L67: =J67*'Entradas'!B12 -> 0 | M67: =K67*'Entradas'!B11 -> 0 | N67: =IF(E67>'Resumen'!$B$14,'Tramos_red'!P9,0) -> 0 | O67: =IF(E67>'Resumen'!$B$14,'Tramos_red'!Q9,0) -> 0 | P67: =IF(E67>'Resumen'!$B$14,'Tramos_red'!R9,0) -> 0 | Q67: =IF(E67<='Resumen'!$B$14,0,IF('Entradas'!$B$5=0,"sin U",IF(P67=0,"infinita",E67/('Entradas'!$B$5*P67)))) -> 0
A68: B6-P2-3 | B68: 6 | C68: ='Entradas'!A12 -> H2 | D68: ='Entradas'!A13 -> C3 | E68: ='Tramos_red'!M9*'Tramos_red'!U9*'Tramos_red'!Z9 -> 16000 | F68: =IF(E68>'Resumen'!$B$14,'Tramos_red'!J9,"") -> 134 | G68: =IF(E68>'Resumen'!$B$14,'Tramos_red'!I9,"") -> 130 | H68: =IF(E68>'Resumen'!$B$14,'Tramos_red'!K9,"") -> 113.33333 | I68: =IF(E68>'Resumen'!$B$14,'Tramos_red'!L9,"") -> 120 | J68: =IF(E68>'Resumen'!$B$14,'Tramos_red'!Z9,0) -> 1 | K68: =IF(E68>'Resumen'!$B$14,'Tramos_red'!U9,0) -> 0.8 | L68: =J68*'Entradas'!B12 -> 4000 | M68: =K68*'Entradas'!B13 -> 2400 | N68: =IF(E68>'Resumen'!$B$14,'Tramos_red'!P9,0) -> 14 | O68: =IF(E68>'Resumen'!$B$14,'Tramos_red'!Q9,0) -> 16.666667 | P68: =IF(E68>'Resumen'!$B$14,'Tramos_red'!R9,0) -> 15.294608 | Q68: =IF(E68<='Resumen'!$B$14,0,IF('Entradas'!$B$5=0,"sin U",IF(P68=0,"infinita",E68/('Entradas'!$B$5*P68)))) -> sin U
A69: B6-P2-4 | B69: 6 | C69: ='Entradas'!A12 -> H2 | D69: ='Entradas'!A14 -> C4 | E69: ='Tramos_red'!M9*'Tramos_red'!U9*'Tramos_red'!AA9 -> 0 | F69: =IF(E69>'Resumen'!$B$14,'Tramos_red'!J9,"") | G69: =IF(E69>'Resumen'!$B$14,'Tramos_red'!I9,"") | H69: =IF(E69>'Resumen'!$B$14,'Tramos_red'!K9,"") | I69: =IF(E69>'Resumen'!$B$14,'Tramos_red'!L9,"") | J69: =IF(E69>'Resumen'!$B$14,'Tramos_red'!AA9,0) -> 0 | K69: =IF(E69>'Resumen'!$B$14,'Tramos_red'!U9,0) -> 0 | L69: =J69*'Entradas'!B12 -> 0 | M69: =K69*'Entradas'!B14 -> 0 | N69: =IF(E69>'Resumen'!$B$14,'Tramos_red'!P9,0) -> 0 | O69: =IF(E69>'Resumen'!$B$14,'Tramos_red'!Q9,0) -> 0 | P69: =IF(E69>'Resumen'!$B$14,'Tramos_red'!R9,0) -> 0 | Q69: =IF(E69<='Resumen'!$B$14,0,IF('Entradas'!$B$5=0,"sin U",IF(P69=0,"infinita",E69/('Entradas'!$B$5*P69)))) -> 0
A70: B6-P3-1 | B70: 6 | C70: ='Entradas'!A13 -> C3 | D70: ='Entradas'!A11 -> H1 | E70: ='Tramos_red'!M9*'Tramos_red'!V9*'Tramos_red'!X9 -> 0 | F70: =IF(E70>'Resumen'!$B$14,'Tramos_red'!J9,"") | G70: =IF(E70>'Resumen'!$B$14,'Tramos_red'!I9,"") | H70: =IF(E70>'Resumen'!$B$14,'Tramos_red'!K9,"") | I70: =IF(E70>'Resumen'!$B$14,'Tramos_red'!L9,"") | J70: =IF(E70>'Resumen'!$B$14,'Tramos_red'!X9,0) -> 0 | K70: =IF(E70>'Resumen'!$B$14,'Tramos_red'!V9,0) -> 0 | L70: =J70*'Entradas'!B13 -> 0 | M70: =K70*'Entradas'!B11 -> 0 | N70: =IF(E70>'Resumen'!$B$14,'Tramos_red'!P9,0) -> 0 | O70: =IF(E70>'Resumen'!$B$14,'Tramos_red'!Q9,0) -> 0 | P70: =IF(E70>'Resumen'!$B$14,'Tramos_red'!R9,0) -> 0 | Q70: =IF(E70<='Resumen'!$B$14,0,IF('Entradas'!$B$5=0,"sin U",IF(P70=0,"infinita",E70/('Entradas'!$B$5*P70)))) -> 0
A71: B6-P3-2 | B71: 6 | C71: ='Entradas'!A13 -> C3 | D71: ='Entradas'!A12 -> H2 | E71: ='Tramos_red'!M9*'Tramos_red'!V9*'Tramos_red'!Y9 -> 0 | F71: =IF(E71>'Resumen'!$B$14,'Tramos_red'!J9,"") | G71: =IF(E71>'Resumen'!$B$14,'Tramos_red'!I9,"") | H71: =IF(E71>'Resumen'!$B$14,'Tramos_red'!K9,"") | I71: =IF(E71>'Resumen'!$B$14,'Tramos_red'!L9,"") | J71: =IF(E71>'Resumen'!$B$14,'Tramos_red'!Y9,0) -> 0 | K71: =IF(E71>'Resumen'!$B$14,'Tramos_red'!V9,0) -> 0 | L71: =J71*'Entradas'!B13 -> 0 | M71: =K71*'Entradas'!B12 -> 0 | N71: =IF(E71>'Resumen'!$B$14,'Tramos_red'!P9,0) -> 0 | O71: =IF(E71>'Resumen'!$B$14,'Tramos_red'!Q9,0) -> 0 | P71: =IF(E71>'Resumen'!$B$14,'Tramos_red'!R9,0) -> 0 | Q71: =IF(E71<='Resumen'!$B$14,0,IF('Entradas'!$B$5=0,"sin U",IF(P71=0,"infinita",E71/('Entradas'!$B$5*P71)))) -> 0
A72: B6-P3-4 | B72: 6 | C72: ='Entradas'!A13 -> C3 | D72: ='Entradas'!A14 -> C4 | E72: ='Tramos_red'!M9*'Tramos_red'!V9*'Tramos_red'!AA9 -> 0 | F72: =IF(E72>'Resumen'!$B$14,'Tramos_red'!J9,"") | G72: =IF(E72>'Resumen'!$B$14,'Tramos_red'!I9,"") | H72: =IF(E72>'Resumen'!$B$14,'Tramos_red'!K9,"") | I72: =IF(E72>'Resumen'!$B$14,'Tramos_red'!L9,"") | J72: =IF(E72>'Resumen'!$B$14,'Tramos_red'!AA9,0) -> 0 | K72: =IF(E72>'Resumen'!$B$14,'Tramos_red'!V9,0) -> 0 | L72: =J72*'Entradas'!B13 -> 0 | M72: =K72*'Entradas'!B14 -> 0 | N72: =IF(E72>'Resumen'!$B$14,'Tramos_red'!P9,0) -> 0 | O72: =IF(E72>'Resumen'!$B$14,'Tramos_red'!Q9,0) -> 0 | P72: =IF(E72>'Resumen'!$B$14,'Tramos_red'!R9,0) -> 0 | Q72: =IF(E72<='Resumen'!$B$14,0,IF('Entradas'!$B$5=0,"sin U",IF(P72=0,"infinita",E72/('Entradas'!$B$5*P72)))) -> 0
A73: B6-P4-1 | B73: 6 | C73: ='Entradas'!A14 -> C4 | D73: ='Entradas'!A11 -> H1 | E73: ='Tramos_red'!M9*'Tramos_red'!W9*'Tramos_red'!X9 -> 0 | F73: =IF(E73>'Resumen'!$B$14,'Tramos_red'!J9,"") | G73: =IF(E73>'Resumen'!$B$14,'Tramos_red'!I9,"") | H73: =IF(E73>'Resumen'!$B$14,'Tramos_red'!K9,"") | I73: =IF(E73>'Resumen'!$B$14,'Tramos_red'!L9,"") | J73: =IF(E73>'Resumen'!$B$14,'Tramos_red'!X9,0) -> 0 | K73: =IF(E73>'Resumen'!$B$14,'Tramos_red'!W9,0) -> 0 | L73: =J73*'Entradas'!B14 -> 0 | M73: =K73*'Entradas'!B11 -> 0 | N73: =IF(E73>'Resumen'!$B$14,'Tramos_red'!P9,0) -> 0 | O73: =IF(E73>'Resumen'!$B$14,'Tramos_red'!Q9,0) -> 0 | P73: =IF(E73>'Resumen'!$B$14,'Tramos_red'!R9,0) -> 0 | Q73: =IF(E73<='Resumen'!$B$14,0,IF('Entradas'!$B$5=0,"sin U",IF(P73=0,"infinita",E73/('Entradas'!$B$5*P73)))) -> 0
A74: B6-P4-2 | B74: 6 | C74: ='Entradas'!A14 -> C4 | D74: ='Entradas'!A12 -> H2 | E74: ='Tramos_red'!M9*'Tramos_red'!W9*'Tramos_red'!Y9 -> 0 | F74: =IF(E74>'Resumen'!$B$14,'Tramos_red'!J9,"") | G74: =IF(E74>'Resumen'!$B$14,'Tramos_red'!I9,"") | H74: =IF(E74>'Resumen'!$B$14,'Tramos_red'!K9,"") | I74: =IF(E74>'Resumen'!$B$14,'Tramos_red'!L9,"") | J74: =IF(E74>'Resumen'!$B$14,'Tramos_red'!Y9,0) -> 0 | K74: =IF(E74>'Resumen'!$B$14,'Tramos_red'!W9,0) -> 0 | L74: =J74*'Entradas'!B14 -> 0 | M74: =K74*'Entradas'!B12 -> 0 | N74: =IF(E74>'Resumen'!$B$14,'Tramos_red'!P9,0) -> 0 | O74: =IF(E74>'Resumen'!$B$14,'Tramos_red'!Q9,0) -> 0 | P74: =IF(E74>'Resumen'!$B$14,'Tramos_red'!R9,0) -> 0 | Q74: =IF(E74<='Resumen'!$B$14,0,IF('Entradas'!$B$5=0,"sin U",IF(P74=0,"infinita",E74/('Entradas'!$B$5*P74)))) -> 0
A75: B6-P4-3 | B75: 6 | C75: ='Entradas'!A14 -> C4 | D75: ='Entradas'!A13 -> C3 | E75: ='Tramos_red'!M9*'Tramos_red'!W9*'Tramos_red'!Z9 -> 0 | F75: =IF(E75>'Resumen'!$B$14,'Tramos_red'!J9,"") | G75: =IF(E75>'Resumen'!$B$14,'Tramos_red'!I9,"") | H75: =IF(E75>'Resumen'!$B$14,'Tramos_red'!K9,"") | I75: =IF(E75>'Resumen'!$B$14,'Tramos_red'!L9,"") | J75: =IF(E75>'Resumen'!$B$14,'Tramos_red'!Z9,0) -> 0 | K75: =IF(E75>'Resumen'!$B$14,'Tramos_red'!W9,0) -> 0 | L75: =J75*'Entradas'!B14 -> 0 | M75: =K75*'Entradas'!B13 -> 0 | N75: =IF(E75>'Resumen'!$B$14,'Tramos_red'!P9,0) -> 0 | O75: =IF(E75>'Resumen'!$B$14,'Tramos_red'!Q9,0) -> 0 | P75: =IF(E75>'Resumen'!$B$14,'Tramos_red'!R9,0) -> 0 | Q75: =IF(E75<='Resumen'!$B$14,0,IF('Entradas'!$B$5=0,"sin U",IF(P75=0,"infinita",E75/('Entradas'!$B$5*P75)))) -> 0
A76: B7-P1-2 | B76: 7 | C76: ='Entradas'!A11 -> H1 | D76: ='Entradas'!A12 -> H2 | E76: ='Tramos_red'!M10*'Tramos_red'!T10*'Tramos_red'!Y10 -> 0 | F76: =IF(E76>'Resumen'!$B$14,'Tramos_red'!J10,"") | G76: =IF(E76>'Resumen'!$B$14,'Tramos_red'!I10,"") | H76: =IF(E76>'Resumen'!$B$14,'Tramos_red'!K10,"") | I76: =IF(E76>'Resumen'!$B$14,'Tramos_red'!L10,"") | J76: =IF(E76>'Resumen'!$B$14,'Tramos_red'!Y10,0) -> 0 | K76: =IF(E76>'Resumen'!$B$14,'Tramos_red'!T10,0) -> 0 | L76: =J76*'Entradas'!B11 -> 0 | M76: =K76*'Entradas'!B12 -> 0 | N76: =IF(E76>'Resumen'!$B$14,'Tramos_red'!P10,0) -> 0 | O76: =IF(E76>'Resumen'!$B$14,'Tramos_red'!Q10,0) -> 0 | P76: =IF(E76>'Resumen'!$B$14,'Tramos_red'!R10,0) -> 0 | Q76: =IF(E76<='Resumen'!$B$14,0,IF('Entradas'!$B$5=0,"sin U",IF(P76=0,"infinita",E76/('Entradas'!$B$5*P76)))) -> 0
A77: B7-P1-3 | B77: 7 | C77: ='Entradas'!A11 -> H1 | D77: ='Entradas'!A13 -> C3 | E77: ='Tramos_red'!M10*'Tramos_red'!T10*'Tramos_red'!Z10 -> 6000 | F77: =IF(E77>'Resumen'!$B$14,'Tramos_red'!J10,"") -> 140 | G77: =IF(E77>'Resumen'!$B$14,'Tramos_red'!I10,"") -> 134 | H77: =IF(E77>'Resumen'!$B$14,'Tramos_red'!K10,"") -> 120 | I77: =IF(E77>'Resumen'!$B$14,'Tramos_red'!L10,"") -> 130 | J77: =IF(E77>'Resumen'!$B$14,'Tramos_red'!Z10,0) -> 1 | K77: =IF(E77>'Resumen'!$B$14,'Tramos_red'!T10,0) -> 0.2 | L77: =J77*'Entradas'!B11 -> 1000 | M77: =K77*'Entradas'!B13 -> 600 | N77: =IF(E77>'Resumen'!$B$14,'Tramos_red'!P10,0) -> 10 | O77: =IF(E77>'Resumen'!$B$14,'Tramos_red'!Q10,0) -> 14 | P77: =IF(E77>'Resumen'!$B$14,'Tramos_red'!R10,0) -> 11.888054 | Q77: =IF(E77<='Resumen'!$B$14,0,IF('Entradas'!$B$5=0,"sin U",IF(P77=0,"infinita",E77/('Entradas'!$B$5*P77)))) -> sin U
A78: B7-P1-4 | B78: 7 | C78: ='Entradas'!A11 -> H1 | D78: ='Entradas'!A14 -> C4 | E78: ='Tramos_red'!M10*'Tramos_red'!T10*'Tramos_red'!AA10 -> 0 | F78: =IF(E78>'Resumen'!$B$14,'Tramos_red'!J10,"") | G78: =IF(E78>'Resumen'!$B$14,'Tramos_red'!I10,"") | H78: =IF(E78>'Resumen'!$B$14,'Tramos_red'!K10,"") | I78: =IF(E78>'Resumen'!$B$14,'Tramos_red'!L10,"") | J78: =IF(E78>'Resumen'!$B$14,'Tramos_red'!AA10,0) -> 0 | K78: =IF(E78>'Resumen'!$B$14,'Tramos_red'!T10,0) -> 0 | L78: =J78*'Entradas'!B11 -> 0 | M78: =K78*'Entradas'!B14 -> 0 | N78: =IF(E78>'Resumen'!$B$14,'Tramos_red'!P10,0) -> 0 | O78: =IF(E78>'Resumen'!$B$14,'Tramos_red'!Q10,0) -> 0 | P78: =IF(E78>'Resumen'!$B$14,'Tramos_red'!R10,0) -> 0 | Q78: =IF(E78<='Resumen'!$B$14,0,IF('Entradas'!$B$5=0,"sin U",IF(P78=0,"infinita",E78/('Entradas'!$B$5*P78)))) -> 0
A79: B7-P2-1 | B79: 7 | C79: ='Entradas'!A12 -> H2 | D79: ='Entradas'!A11 -> H1 | E79: ='Tramos_red'!M10*'Tramos_red'!U10*'Tramos_red'!X10 -> 0 | F79: =IF(E79>'Resumen'!$B$14,'Tramos_red'!J10,"") | G79: =IF(E79>'Resumen'!$B$14,'Tramos_red'!I10,"") | H79: =IF(E79>'Resumen'!$B$14,'Tramos_red'!K10,"") | I79: =IF(E79>'Resumen'!$B$14,'Tramos_red'!L10,"") | J79: =IF(E79>'Resumen'!$B$14,'Tramos_red'!X10,0) -> 0 | K79: =IF(E79>'Resumen'!$B$14,'Tramos_red'!U10,0) -> 0 | L79: =J79*'Entradas'!B12 -> 0 | M79: =K79*'Entradas'!B11 -> 0 | N79: =IF(E79>'Resumen'!$B$14,'Tramos_red'!P10,0) -> 0 | O79: =IF(E79>'Resumen'!$B$14,'Tramos_red'!Q10,0) -> 0 | P79: =IF(E79>'Resumen'!$B$14,'Tramos_red'!R10,0) -> 0 | Q79: =IF(E79<='Resumen'!$B$14,0,IF('Entradas'!$B$5=0,"sin U",IF(P79=0,"infinita",E79/('Entradas'!$B$5*P79)))) -> 0
A80: B7-P2-3 | B80: 7 | C80: ='Entradas'!A12 -> H2 | D80: ='Entradas'!A13 -> C3 | E80: ='Tramos_red'!M10*'Tramos_red'!U10*'Tramos_red'!Z10 -> 24000 | F80: =IF(E80>'Resumen'!$B$14,'Tramos_red'!J10,"") -> 140 | G80: =IF(E80>'Resumen'!$B$14,'Tramos_red'!I10,"") -> 134 | H80: =IF(E80>'Resumen'!$B$14,'Tramos_red'!K10,"") -> 120 | I80: =IF(E80>'Resumen'!$B$14,'Tramos_red'!L10,"") -> 130 | J80: =IF(E80>'Resumen'!$B$14,'Tramos_red'!Z10,0) -> 1 | K80: =IF(E80>'Resumen'!$B$14,'Tramos_red'!U10,0) -> 0.8 | L80: =J80*'Entradas'!B12 -> 4000 | M80: =K80*'Entradas'!B13 -> 2400 | N80: =IF(E80>'Resumen'!$B$14,'Tramos_red'!P10,0) -> 10 | O80: =IF(E80>'Resumen'!$B$14,'Tramos_red'!Q10,0) -> 14 | P80: =IF(E80>'Resumen'!$B$14,'Tramos_red'!R10,0) -> 11.888054 | Q80: =IF(E80<='Resumen'!$B$14,0,IF('Entradas'!$B$5=0,"sin U",IF(P80=0,"infinita",E80/('Entradas'!$B$5*P80)))) -> sin U
A81: B7-P2-4 | B81: 7 | C81: ='Entradas'!A12 -> H2 | D81: ='Entradas'!A14 -> C4 | E81: ='Tramos_red'!M10*'Tramos_red'!U10*'Tramos_red'!AA10 -> 0 | F81: =IF(E81>'Resumen'!$B$14,'Tramos_red'!J10,"") | G81: =IF(E81>'Resumen'!$B$14,'Tramos_red'!I10,"") | H81: =IF(E81>'Resumen'!$B$14,'Tramos_red'!K10,"") | I81: =IF(E81>'Resumen'!$B$14,'Tramos_red'!L10,"") | J81: =IF(E81>'Resumen'!$B$14,'Tramos_red'!AA10,0) -> 0 | K81: =IF(E81>'Resumen'!$B$14,'Tramos_red'!U10,0) -> 0 | L81: =J81*'Entradas'!B12 -> 0 | M81: =K81*'Entradas'!B14 -> 0 | N81: =IF(E81>'Resumen'!$B$14,'Tramos_red'!P10,0) -> 0 | O81: =IF(E81>'Resumen'!$B$14,'Tramos_red'!Q10,0) -> 0 | P81: =IF(E81>'Resumen'!$B$14,'Tramos_red'!R10,0) -> 0 | Q81: =IF(E81<='Resumen'!$B$14,0,IF('Entradas'!$B$5=0,"sin U",IF(P81=0,"infinita",E81/('Entradas'!$B$5*P81)))) -> 0
A82: B7-P3-1 | B82: 7 | C82: ='Entradas'!A13 -> C3 | D82: ='Entradas'!A11 -> H1 | E82: ='Tramos_red'!M10*'Tramos_red'!V10*'Tramos_red'!X10 -> 0 | F82: =IF(E82>'Resumen'!$B$14,'Tramos_red'!J10,"") | G82: =IF(E82>'Resumen'!$B$14,'Tramos_red'!I10,"") | H82: =IF(E82>'Resumen'!$B$14,'Tramos_red'!K10,"") | I82: =IF(E82>'Resumen'!$B$14,'Tramos_red'!L10,"") | J82: =IF(E82>'Resumen'!$B$14,'Tramos_red'!X10,0) -> 0 | K82: =IF(E82>'Resumen'!$B$14,'Tramos_red'!V10,0) -> 0 | L82: =J82*'Entradas'!B13 -> 0 | M82: =K82*'Entradas'!B11 -> 0 | N82: =IF(E82>'Resumen'!$B$14,'Tramos_red'!P10,0) -> 0 | O82: =IF(E82>'Resumen'!$B$14,'Tramos_red'!Q10,0) -> 0 | P82: =IF(E82>'Resumen'!$B$14,'Tramos_red'!R10,0) -> 0 | Q82: =IF(E82<='Resumen'!$B$14,0,IF('Entradas'!$B$5=0,"sin U",IF(P82=0,"infinita",E82/('Entradas'!$B$5*P82)))) -> 0
A83: B7-P3-2 | B83: 7 | C83: ='Entradas'!A13 -> C3 | D83: ='Entradas'!A12 -> H2 | E83: ='Tramos_red'!M10*'Tramos_red'!V10*'Tramos_red'!Y10 -> 0 | F83: =IF(E83>'Resumen'!$B$14,'Tramos_red'!J10,"") | G83: =IF(E83>'Resumen'!$B$14,'Tramos_red'!I10,"") | H83: =IF(E83>'Resumen'!$B$14,'Tramos_red'!K10,"") | I83: =IF(E83>'Resumen'!$B$14,'Tramos_red'!L10,"") | J83: =IF(E83>'Resumen'!$B$14,'Tramos_red'!Y10,0) -> 0 | K83: =IF(E83>'Resumen'!$B$14,'Tramos_red'!V10,0) -> 0 | L83: =J83*'Entradas'!B13 -> 0 | M83: =K83*'Entradas'!B12 -> 0 | N83: =IF(E83>'Resumen'!$B$14,'Tramos_red'!P10,0) -> 0 | O83: =IF(E83>'Resumen'!$B$14,'Tramos_red'!Q10,0) -> 0 | P83: =IF(E83>'Resumen'!$B$14,'Tramos_red'!R10,0) -> 0 | Q83: =IF(E83<='Resumen'!$B$14,0,IF('Entradas'!$B$5=0,"sin U",IF(P83=0,"infinita",E83/('Entradas'!$B$5*P83)))) -> 0
A84: B7-P3-4 | B84: 7 | C84: ='Entradas'!A13 -> C3 | D84: ='Entradas'!A14 -> C4 | E84: ='Tramos_red'!M10*'Tramos_red'!V10*'Tramos_red'!AA10 -> 0 | F84: =IF(E84>'Resumen'!$B$14,'Tramos_red'!J10,"") | G84: =IF(E84>'Resumen'!$B$14,'Tramos_red'!I10,"") | H84: =IF(E84>'Resumen'!$B$14,'Tramos_red'!K10,"") | I84: =IF(E84>'Resumen'!$B$14,'Tramos_red'!L10,"") | J84: =IF(E84>'Resumen'!$B$14,'Tramos_red'!AA10,0) -> 0 | K84: =IF(E84>'Resumen'!$B$14,'Tramos_red'!V10,0) -> 0 | L84: =J84*'Entradas'!B13 -> 0 | M84: =K84*'Entradas'!B14 -> 0 | N84: =IF(E84>'Resumen'!$B$14,'Tramos_red'!P10,0) -> 0 | O84: =IF(E84>'Resumen'!$B$14,'Tramos_red'!Q10,0) -> 0 | P84: =IF(E84>'Resumen'!$B$14,'Tramos_red'!R10,0) -> 0 | Q84: =IF(E84<='Resumen'!$B$14,0,IF('Entradas'!$B$5=0,"sin U",IF(P84=0,"infinita",E84/('Entradas'!$B$5*P84)))) -> 0
A85: B7-P4-1 | B85: 7 | C85: ='Entradas'!A14 -> C4 | D85: ='Entradas'!A11 -> H1 | E85: ='Tramos_red'!M10*'Tramos_red'!W10*'Tramos_red'!X10 -> 0 | F85: =IF(E85>'Resumen'!$B$14,'Tramos_red'!J10,"") | G85: =IF(E85>'Resumen'!$B$14,'Tramos_red'!I10,"") | H85: =IF(E85>'Resumen'!$B$14,'Tramos_red'!K10,"") | I85: =IF(E85>'Resumen'!$B$14,'Tramos_red'!L10,"") | J85: =IF(E85>'Resumen'!$B$14,'Tramos_red'!X10,0) -> 0 | K85: =IF(E85>'Resumen'!$B$14,'Tramos_red'!W10,0) -> 0 | L85: =J85*'Entradas'!B14 -> 0 | M85: =K85*'Entradas'!B11 -> 0 | N85: =IF(E85>'Resumen'!$B$14,'Tramos_red'!P10,0) -> 0 | O85: =IF(E85>'Resumen'!$B$14,'Tramos_red'!Q10,0) -> 0 | P85: =IF(E85>'Resumen'!$B$14,'Tramos_red'!R10,0) -> 0 | Q85: =IF(E85<='Resumen'!$B$14,0,IF('Entradas'!$B$5=0,"sin U",IF(P85=0,"infinita",E85/('Entradas'!$B$5*P85)))) -> 0
A86: B7-P4-2 | B86: 7 | C86: ='Entradas'!A14 -> C4 | D86: ='Entradas'!A12 -> H2 | E86: ='Tramos_red'!M10*'Tramos_red'!W10*'Tramos_red'!Y10 -> 0 | F86: =IF(E86>'Resumen'!$B$14,'Tramos_red'!J10,"") | G86: =IF(E86>'Resumen'!$B$14,'Tramos_red'!I10,"") | H86: =IF(E86>'Resumen'!$B$14,'Tramos_red'!K10,"") | I86: =IF(E86>'Resumen'!$B$14,'Tramos_red'!L10,"") | J86: =IF(E86>'Resumen'!$B$14,'Tramos_red'!Y10,0) -> 0 | K86: =IF(E86>'Resumen'!$B$14,'Tramos_red'!W10,0) -> 0 | L86: =J86*'Entradas'!B14 -> 0 | M86: =K86*'Entradas'!B12 -> 0 | N86: =IF(E86>'Resumen'!$B$14,'Tramos_red'!P10,0) -> 0 | O86: =IF(E86>'Resumen'!$B$14,'Tramos_red'!Q10,0) -> 0 | P86: =IF(E86>'Resumen'!$B$14,'Tramos_red'!R10,0) -> 0 | Q86: =IF(E86<='Resumen'!$B$14,0,IF('Entradas'!$B$5=0,"sin U",IF(P86=0,"infinita",E86/('Entradas'!$B$5*P86)))) -> 0
A87: B7-P4-3 | B87: 7 | C87: ='Entradas'!A14 -> C4 | D87: ='Entradas'!A13 -> C3 | E87: ='Tramos_red'!M10*'Tramos_red'!W10*'Tramos_red'!Z10 -> 0 | F87: =IF(E87>'Resumen'!$B$14,'Tramos_red'!J10,"") | G87: =IF(E87>'Resumen'!$B$14,'Tramos_red'!I10,"") | H87: =IF(E87>'Resumen'!$B$14,'Tramos_red'!K10,"") | I87: =IF(E87>'Resumen'!$B$14,'Tramos_red'!L10,"") | J87: =IF(E87>'Resumen'!$B$14,'Tramos_red'!Z10,0) -> 0 | K87: =IF(E87>'Resumen'!$B$14,'Tramos_red'!W10,0) -> 0 | L87: =J87*'Entradas'!B14 -> 0 | M87: =K87*'Entradas'!B13 -> 0 | N87: =IF(E87>'Resumen'!$B$14,'Tramos_red'!P10,0) -> 0 | O87: =IF(E87>'Resumen'!$B$14,'Tramos_red'!Q10,0) -> 0 | P87: =IF(E87>'Resumen'!$B$14,'Tramos_red'!R10,0) -> 0 | Q87: =IF(E87<='Resumen'!$B$14,0,IF('Entradas'!$B$5=0,"sin U",IF(P87=0,"infinita",E87/('Entradas'!$B$5*P87)))) -> 0
A88: B8-P1-2 | B88: 8 | C88: ='Entradas'!A11 -> H1 | D88: ='Entradas'!A12 -> H2 | E88: ='Tramos_red'!M11*'Tramos_red'!T11*'Tramos_red'!Y11 -> 0 | F88: =IF(E88>'Resumen'!$B$14,'Tramos_red'!J11,"") | G88: =IF(E88>'Resumen'!$B$14,'Tramos_red'!I11,"") | H88: =IF(E88>'Resumen'!$B$14,'Tramos_red'!K11,"") | I88: =IF(E88>'Resumen'!$B$14,'Tramos_red'!L11,"") | J88: =IF(E88>'Resumen'!$B$14,'Tramos_red'!Y11,0) -> 0 | K88: =IF(E88>'Resumen'!$B$14,'Tramos_red'!T11,0) -> 0 | L88: =J88*'Entradas'!B11 -> 0 | M88: =K88*'Entradas'!B12 -> 0 | N88: =IF(E88>'Resumen'!$B$14,'Tramos_red'!P11,0) -> 0 | O88: =IF(E88>'Resumen'!$B$14,'Tramos_red'!Q11,0) -> 0 | P88: =IF(E88>'Resumen'!$B$14,'Tramos_red'!R11,0) -> 0 | Q88: =IF(E88<='Resumen'!$B$14,0,IF('Entradas'!$B$5=0,"sin U",IF(P88=0,"infinita",E88/('Entradas'!$B$5*P88)))) -> 0
A89: B8-P1-3 | B89: 8 | C89: ='Entradas'!A11 -> H1 | D89: ='Entradas'!A13 -> C3 | E89: ='Tramos_red'!M11*'Tramos_red'!T11*'Tramos_red'!Z11 -> 3333.3333 | F89: =IF(E89>'Resumen'!$B$14,'Tramos_red'!J11,"") -> 150 | G89: =IF(E89>'Resumen'!$B$14,'Tramos_red'!I11,"") -> 140 | H89: =IF(E89>'Resumen'!$B$14,'Tramos_red'!K11,"") -> 130 | I89: =IF(E89>'Resumen'!$B$14,'Tramos_red'!L11,"") -> 135.55556 | J89: =IF(E89>'Resumen'!$B$14,'Tramos_red'!Z11,0) -> 0.33333333 | K89: =IF(E89>'Resumen'!$B$14,'Tramos_red'!T11,0) -> 0.2 | L89: =J89*'Entradas'!B11 -> 333.33333 | M89: =K89*'Entradas'!B13 -> 600 | N89: =IF(E89>'Resumen'!$B$14,'Tramos_red'!P11,0) -> 14.444444 | O89: =IF(E89>'Resumen'!$B$14,'Tramos_red'!Q11,0) -> 10 | P89: =IF(E89>'Resumen'!$B$14,'Tramos_red'!R11,0) -> 12.086334 | Q89: =IF(E89<='Resumen'!$B$14,0,IF('Entradas'!$B$5=0,"sin U",IF(P89=0,"infinita",E89/('Entradas'!$B$5*P89)))) -> sin U
A90: B8-P1-4 | B90: 8 | C90: ='Entradas'!A11 -> H1 | D90: ='Entradas'!A14 -> C4 | E90: ='Tramos_red'!M11*'Tramos_red'!T11*'Tramos_red'!AA11 -> 6666.6667 | F90: =IF(E90>'Resumen'!$B$14,'Tramos_red'!J11,"") -> 150 | G90: =IF(E90>'Resumen'!$B$14,'Tramos_red'!I11,"") -> 140 | H90: =IF(E90>'Resumen'!$B$14,'Tramos_red'!K11,"") -> 130 | I90: =IF(E90>'Resumen'!$B$14,'Tramos_red'!L11,"") -> 135.55556 | J90: =IF(E90>'Resumen'!$B$14,'Tramos_red'!AA11,0) -> 0.66666667 | K90: =IF(E90>'Resumen'!$B$14,'Tramos_red'!T11,0) -> 0.2 | L90: =J90*'Entradas'!B11 -> 666.66667 | M90: =K90*'Entradas'!B14 -> 1200 | N90: =IF(E90>'Resumen'!$B$14,'Tramos_red'!P11,0) -> 14.444444 | O90: =IF(E90>'Resumen'!$B$14,'Tramos_red'!Q11,0) -> 10 | P90: =IF(E90>'Resumen'!$B$14,'Tramos_red'!R11,0) -> 12.086334 | Q90: =IF(E90<='Resumen'!$B$14,0,IF('Entradas'!$B$5=0,"sin U",IF(P90=0,"infinita",E90/('Entradas'!$B$5*P90)))) -> sin U
A91: B8-P2-1 | B91: 8 | C91: ='Entradas'!A12 -> H2 | D91: ='Entradas'!A11 -> H1 | E91: ='Tramos_red'!M11*'Tramos_red'!U11*'Tramos_red'!X11 -> 0 | F91: =IF(E91>'Resumen'!$B$14,'Tramos_red'!J11,"") | G91: =IF(E91>'Resumen'!$B$14,'Tramos_red'!I11,"") | H91: =IF(E91>'Resumen'!$B$14,'Tramos_red'!K11,"") | I91: =IF(E91>'Resumen'!$B$14,'Tramos_red'!L11,"") | J91: =IF(E91>'Resumen'!$B$14,'Tramos_red'!X11,0) -> 0 | K91: =IF(E91>'Resumen'!$B$14,'Tramos_red'!U11,0) -> 0 | L91: =J91*'Entradas'!B12 -> 0 | M91: =K91*'Entradas'!B11 -> 0 | N91: =IF(E91>'Resumen'!$B$14,'Tramos_red'!P11,0) -> 0 | O91: =IF(E91>'Resumen'!$B$14,'Tramos_red'!Q11,0) -> 0 | P91: =IF(E91>'Resumen'!$B$14,'Tramos_red'!R11,0) -> 0 | Q91: =IF(E91<='Resumen'!$B$14,0,IF('Entradas'!$B$5=0,"sin U",IF(P91=0,"infinita",E91/('Entradas'!$B$5*P91)))) -> 0
A92: B8-P2-3 | B92: 8 | C92: ='Entradas'!A12 -> H2 | D92: ='Entradas'!A13 -> C3 | E92: ='Tramos_red'!M11*'Tramos_red'!U11*'Tramos_red'!Z11 -> 13333.333 | F92: =IF(E92>'Resumen'!$B$14,'Tramos_red'!J11,"") -> 150 | G92: =IF(E92>'Resumen'!$B$14,'Tramos_red'!I11,"") -> 140 | H92: =IF(E92>'Resumen'!$B$14,'Tramos_red'!K11,"") -> 130 | I92: =IF(E92>'Resumen'!$B$14,'Tramos_red'!L11,"") -> 135.55556 | J92: =IF(E92>'Resumen'!$B$14,'Tramos_red'!Z11,0) -> 0.33333333 | K92: =IF(E92>'Resumen'!$B$14,'Tramos_red'!U11,0) -> 0.8 | L92: =J92*'Entradas'!B12 -> 1333.3333 | M92: =K92*'Entradas'!B13 -> 2400 | N92: =IF(E92>'Resumen'!$B$14,'Tramos_red'!P11,0) -> 14.444444 | O92: =IF(E92>'Resumen'!$B$14,'Tramos_red'!Q11,0) -> 10 | P92: =IF(E92>'Resumen'!$B$14,'Tramos_red'!R11,0) -> 12.086334 | Q92: =IF(E92<='Resumen'!$B$14,0,IF('Entradas'!$B$5=0,"sin U",IF(P92=0,"infinita",E92/('Entradas'!$B$5*P92)))) -> sin U
A93: B8-P2-4 | B93: 8 | C93: ='Entradas'!A12 -> H2 | D93: ='Entradas'!A14 -> C4 | E93: ='Tramos_red'!M11*'Tramos_red'!U11*'Tramos_red'!AA11 -> 26666.667 | F93: =IF(E93>'Resumen'!$B$14,'Tramos_red'!J11,"") -> 150 | G93: =IF(E93>'Resumen'!$B$14,'Tramos_red'!I11,"") -> 140 | H93: =IF(E93>'Resumen'!$B$14,'Tramos_red'!K11,"") -> 130 | I93: =IF(E93>'Resumen'!$B$14,'Tramos_red'!L11,"") -> 135.55556 | J93: =IF(E93>'Resumen'!$B$14,'Tramos_red'!AA11,0) -> 0.66666667 | K93: =IF(E93>'Resumen'!$B$14,'Tramos_red'!U11,0) -> 0.8 | L93: =J93*'Entradas'!B12 -> 2666.6667 | M93: =K93*'Entradas'!B14 -> 4800 | N93: =IF(E93>'Resumen'!$B$14,'Tramos_red'!P11,0) -> 14.444444 | O93: =IF(E93>'Resumen'!$B$14,'Tramos_red'!Q11,0) -> 10 | P93: =IF(E93>'Resumen'!$B$14,'Tramos_red'!R11,0) -> 12.086334 | Q93: =IF(E93<='Resumen'!$B$14,0,IF('Entradas'!$B$5=0,"sin U",IF(P93=0,"infinita",E93/('Entradas'!$B$5*P93)))) -> sin U
A94: B8-P3-1 | B94: 8 | C94: ='Entradas'!A13 -> C3 | D94: ='Entradas'!A11 -> H1 | E94: ='Tramos_red'!M11*'Tramos_red'!V11*'Tramos_red'!X11 -> 0 | F94: =IF(E94>'Resumen'!$B$14,'Tramos_red'!J11,"") | G94: =IF(E94>'Resumen'!$B$14,'Tramos_red'!I11,"") | H94: =IF(E94>'Resumen'!$B$14,'Tramos_red'!K11,"") | I94: =IF(E94>'Resumen'!$B$14,'Tramos_red'!L11,"") | J94: =IF(E94>'Resumen'!$B$14,'Tramos_red'!X11,0) -> 0 | K94: =IF(E94>'Resumen'!$B$14,'Tramos_red'!V11,0) -> 0 | L94: =J94*'Entradas'!B13 -> 0 | M94: =K94*'Entradas'!B11 -> 0 | N94: =IF(E94>'Resumen'!$B$14,'Tramos_red'!P11,0) -> 0 | O94: =IF(E94>'Resumen'!$B$14,'Tramos_red'!Q11,0) -> 0 | P94: =IF(E94>'Resumen'!$B$14,'Tramos_red'!R11,0) -> 0 | Q94: =IF(E94<='Resumen'!$B$14,0,IF('Entradas'!$B$5=0,"sin U",IF(P94=0,"infinita",E94/('Entradas'!$B$5*P94)))) -> 0
A95: B8-P3-2 | B95: 8 | C95: ='Entradas'!A13 -> C3 | D95: ='Entradas'!A12 -> H2 | E95: ='Tramos_red'!M11*'Tramos_red'!V11*'Tramos_red'!Y11 -> 0 | F95: =IF(E95>'Resumen'!$B$14,'Tramos_red'!J11,"") | G95: =IF(E95>'Resumen'!$B$14,'Tramos_red'!I11,"") | H95: =IF(E95>'Resumen'!$B$14,'Tramos_red'!K11,"") | I95: =IF(E95>'Resumen'!$B$14,'Tramos_red'!L11,"") | J95: =IF(E95>'Resumen'!$B$14,'Tramos_red'!Y11,0) -> 0 | K95: =IF(E95>'Resumen'!$B$14,'Tramos_red'!V11,0) -> 0 | L95: =J95*'Entradas'!B13 -> 0 | M95: =K95*'Entradas'!B12 -> 0 | N95: =IF(E95>'Resumen'!$B$14,'Tramos_red'!P11,0) -> 0 | O95: =IF(E95>'Resumen'!$B$14,'Tramos_red'!Q11,0) -> 0 | P95: =IF(E95>'Resumen'!$B$14,'Tramos_red'!R11,0) -> 0 | Q95: =IF(E95<='Resumen'!$B$14,0,IF('Entradas'!$B$5=0,"sin U",IF(P95=0,"infinita",E95/('Entradas'!$B$5*P95)))) -> 0
A96: B8-P3-4 | B96: 8 | C96: ='Entradas'!A13 -> C3 | D96: ='Entradas'!A14 -> C4 | E96: ='Tramos_red'!M11*'Tramos_red'!V11*'Tramos_red'!AA11 -> 0 | F96: =IF(E96>'Resumen'!$B$14,'Tramos_red'!J11,"") | G96: =IF(E96>'Resumen'!$B$14,'Tramos_red'!I11,"") | H96: =IF(E96>'Resumen'!$B$14,'Tramos_red'!K11,"") | I96: =IF(E96>'Resumen'!$B$14,'Tramos_red'!L11,"") | J96: =IF(E96>'Resumen'!$B$14,'Tramos_red'!AA11,0) -> 0 | K96: =IF(E96>'Resumen'!$B$14,'Tramos_red'!V11,0) -> 0 | L96: =J96*'Entradas'!B13 -> 0 | M96: =K96*'Entradas'!B14 -> 0 | N96: =IF(E96>'Resumen'!$B$14,'Tramos_red'!P11,0) -> 0 | O96: =IF(E96>'Resumen'!$B$14,'Tramos_red'!Q11,0) -> 0 | P96: =IF(E96>'Resumen'!$B$14,'Tramos_red'!R11,0) -> 0 | Q96: =IF(E96<='Resumen'!$B$14,0,IF('Entradas'!$B$5=0,"sin U",IF(P96=0,"infinita",E96/('Entradas'!$B$5*P96)))) -> 0
A97: B8-P4-1 | B97: 8 | C97: ='Entradas'!A14 -> C4 | D97: ='Entradas'!A11 -> H1 | E97: ='Tramos_red'!M11*'Tramos_red'!W11*'Tramos_red'!X11 -> 0 | F97: =IF(E97>'Resumen'!$B$14,'Tramos_red'!J11,"") | G97: =IF(E97>'Resumen'!$B$14,'Tramos_red'!I11,"") | H97: =IF(E97>'Resumen'!$B$14,'Tramos_red'!K11,"") | I97: =IF(E97>'Resumen'!$B$14,'Tramos_red'!L11,"") | J97: =IF(E97>'Resumen'!$B$14,'Tramos_red'!X11,0) -> 0 | K97: =IF(E97>'Resumen'!$B$14,'Tramos_red'!W11,0) -> 0 | L97: =J97*'Entradas'!B14 -> 0 | M97: =K97*'Entradas'!B11 -> 0 | N97: =IF(E97>'Resumen'!$B$14,'Tramos_red'!P11,0) -> 0 | O97: =IF(E97>'Resumen'!$B$14,'Tramos_red'!Q11,0) -> 0 | P97: =IF(E97>'Resumen'!$B$14,'Tramos_red'!R11,0) -> 0 | Q97: =IF(E97<='Resumen'!$B$14,0,IF('Entradas'!$B$5=0,"sin U",IF(P97=0,"infinita",E97/('Entradas'!$B$5*P97)))) -> 0
A98: B8-P4-2 | B98: 8 | C98: ='Entradas'!A14 -> C4 | D98: ='Entradas'!A12 -> H2 | E98: ='Tramos_red'!M11*'Tramos_red'!W11*'Tramos_red'!Y11 -> 0 | F98: =IF(E98>'Resumen'!$B$14,'Tramos_red'!J11,"") | G98: =IF(E98>'Resumen'!$B$14,'Tramos_red'!I11,"") | H98: =IF(E98>'Resumen'!$B$14,'Tramos_red'!K11,"") | I98: =IF(E98>'Resumen'!$B$14,'Tramos_red'!L11,"") | J98: =IF(E98>'Resumen'!$B$14,'Tramos_red'!Y11,0) -> 0 | K98: =IF(E98>'Resumen'!$B$14,'Tramos_red'!W11,0) -> 0 | L98: =J98*'Entradas'!B14 -> 0 | M98: =K98*'Entradas'!B12 -> 0 | N98: =IF(E98>'Resumen'!$B$14,'Tramos_red'!P11,0) -> 0 | O98: =IF(E98>'Resumen'!$B$14,'Tramos_red'!Q11,0) -> 0 | P98: =IF(E98>'Resumen'!$B$14,'Tramos_red'!R11,0) -> 0 | Q98: =IF(E98<='Resumen'!$B$14,0,IF('Entradas'!$B$5=0,"sin U",IF(P98=0,"infinita",E98/('Entradas'!$B$5*P98)))) -> 0
A99: B8-P4-3 | B99: 8 | C99: ='Entradas'!A14 -> C4 | D99: ='Entradas'!A13 -> C3 | E99: ='Tramos_red'!M11*'Tramos_red'!W11*'Tramos_red'!Z11 -> 0 | F99: =IF(E99>'Resumen'!$B$14,'Tramos_red'!J11,"") | G99: =IF(E99>'Resumen'!$B$14,'Tramos_red'!I11,"") | H99: =IF(E99>'Resumen'!$B$14,'Tramos_red'!K11,"") | I99: =IF(E99>'Resumen'!$B$14,'Tramos_red'!L11,"") | J99: =IF(E99>'Resumen'!$B$14,'Tramos_red'!Z11,0) -> 0 | K99: =IF(E99>'Resumen'!$B$14,'Tramos_red'!W11,0) -> 0 | L99: =J99*'Entradas'!B14 -> 0 | M99: =K99*'Entradas'!B13 -> 0 | N99: =IF(E99>'Resumen'!$B$14,'Tramos_red'!P11,0) -> 0 | O99: =IF(E99>'Resumen'!$B$14,'Tramos_red'!Q11,0) -> 0 | P99: =IF(E99>'Resumen'!$B$14,'Tramos_red'!R11,0) -> 0 | Q99: =IF(E99<='Resumen'!$B$14,0,IF('Entradas'!$B$5=0,"sin U",IF(P99=0,"infinita",E99/('Entradas'!$B$5*P99)))) -> 0
A100: B9-P1-2 | B100: 9 | C100: ='Entradas'!A11 -> H1 | D100: ='Entradas'!A12 -> H2 | E100: ='Tramos_red'!M12*'Tramos_red'!T12*'Tramos_red'!Y12 -> 0 | F100: =IF(E100>'Resumen'!$B$14,'Tramos_red'!J12,"") | G100: =IF(E100>'Resumen'!$B$14,'Tramos_red'!I12,"") | H100: =IF(E100>'Resumen'!$B$14,'Tramos_red'!K12,"") | I100: =IF(E100>'Resumen'!$B$14,'Tramos_red'!L12,"") | J100: =IF(E100>'Resumen'!$B$14,'Tramos_red'!Y12,0) -> 0 | K100: =IF(E100>'Resumen'!$B$14,'Tramos_red'!T12,0) -> 0 | L100: =J100*'Entradas'!B11 -> 0 | M100: =K100*'Entradas'!B12 -> 0 | N100: =IF(E100>'Resumen'!$B$14,'Tramos_red'!P12,0) -> 0 | O100: =IF(E100>'Resumen'!$B$14,'Tramos_red'!Q12,0) -> 0 | P100: =IF(E100>'Resumen'!$B$14,'Tramos_red'!R12,0) -> 0 | Q100: =IF(E100<='Resumen'!$B$14,0,IF('Entradas'!$B$5=0,"sin U",IF(P100=0,"infinita",E100/('Entradas'!$B$5*P100)))) -> 0
...

Sheet Cascada
A1: Tabla de intervalos y cascada
A2: T*hot=T−ΔTmin/2; T*cold=T+ΔTmin/2. Los intervalos repetidos tienen anchura cero.
A3: T* sin ordenar | B3: T* descendente | C3: ΔT intervalo | D3: ΣCP hot | E3: ΣCP cold | F3: CP neto | G3: ΔH intervalo | H3: Residual bruto | I3: Residual ajustado | J3: T* pinch | K3: Th pinch | L3: Tc pinch | M3: Posición
A4: ='Entradas'!J11 -> 115 | B4: =LARGE($A$4:$A$11,1) -> 245 | C4: =B4-B5 -> 50 | D4: =SUMPRODUCT(--('Entradas'!$E$11:$E$14="HOT"),--('Entradas'!$J$11:$J$14<=(B4+B5)/2),--('Entradas'!$K$11:$K$14 >=(B4+B5)/2),'Entradas'!$B$11:$B$14) -> 1000 | E4: =SUMPRODUCT(--('Entradas'!$E$11:$E$14="COLD"),--('Entradas'!$J$11:$J$14<=(B4+B5)/2),--('Entradas'!$K$11:$K$14 >=(B4+B5)/2),'Entradas'!$B$11:$B$14) -> 0 | F4: =D4-E4 -> 1000 | G4: =C4*F4 -> 50000 | H4: =0 -> 0 | I4: =H4+'Resumen'!$B$7 -> 70000 | J4: =IF(ABS(I4)<='Resumen'!$B$14,B4,"") | K4: =IF(ISNUMBER(J4),J4+'Entradas'!$B$4/2,"") | L4: =IF(ISNUMBER(J4),J4-'Entradas'!$B$4/2,"") | M4: =IF(ISNUMBER(J4),IF(OR(B4=$B$4,B4=$B$11),"umbral","interior"),"")
A5: ='Entradas'!K11 -> 245 | B5: =LARGE($A$4:$A$11,2) -> 195 | C5: =B5-B6 -> 0 | D5: =SUMPRODUCT(--('Entradas'!$E$11:$E$14="HOT"),--('Entradas'!$J$11:$J$14<=(B5+B6)/2),--('Entradas'!$K$11:$K$14 >=(B5+B6)/2),'Entradas'!$B$11:$B$14) -> 5000 | E5: =SUMPRODUCT(--('Entradas'!$E$11:$E$14="COLD"),--('Entradas'!$J$11:$J$14<=(B5+B6)/2),--('Entradas'!$K$11:$K$14 >=(B5+B6)/2),'Entradas'!$B$11:$B$14) -> 6000 | F5: =D5-E5 -> -1000 | G5: =C5*F5 -> 0 | H5: =H4+G4 -> 50000 | I5: =H5+'Resumen'!$B$7 -> 120000 | J5: =IF(ABS(I5)<='Resumen'!$B$14,B5,"") | K5: =IF(ISNUMBER(J5),J5+'Entradas'!$B$4/2,"") | L5: =IF(ISNUMBER(J5),J5-'Entradas'!$B$4/2,"") | M5: =IF(ISNUMBER(J5),IF(OR(B5=$B$4,B5=$B$11),"umbral","interior"),"")
A6: ='Entradas'!J12 -> 95 | B6: =LARGE($A$4:$A$11,3) -> 195 | C6: =B6-B7 -> 40 | D6: =SUMPRODUCT(--('Entradas'!$E$11:$E$14="HOT"),--('Entradas'!$J$11:$J$14<=(B6+B7)/2),--('Entradas'!$K$11:$K$14 >=(B6+B7)/2),'Entradas'!$B$11:$B$14) -> 5000 | E6: =SUMPRODUCT(--('Entradas'!$E$11:$E$14="COLD"),--('Entradas'!$J$11:$J$14<=(B6+B7)/2),--('Entradas'!$K$11:$K$14 >=(B6+B7)/2),'Entradas'!$B$11:$B$14) -> 6000 | F6: =D6-E6 -> -1000 | G6: =C6*F6 -> -40000 | H6: =H5+G5 -> 50000 | I6: =H6+'Resumen'!$B$7 -> 120000 | J6: =IF(ABS(I6)<='Resumen'!$B$14,B6,"") | K6: =IF(ISNUMBER(J6),J6+'Entradas'!$B$4/2,"") | L6: =IF(ISNUMBER(J6),J6-'Entradas'!$B$4/2,"") | M6: =IF(ISNUMBER(J6),IF(OR(B6=$B$4,B6=$B$11),"umbral","interior"),"")
A7: ='Entradas'!K12 -> 195 | B7: =LARGE($A$4:$A$11,4) -> 155 | C7: =B7-B8 -> 20 | D7: =SUMPRODUCT(--('Entradas'!$E$11:$E$14="HOT"),--('Entradas'!$J$11:$J$14<=(B7+B8)/2),--('Entradas'!$K$11:$K$14 >=(B7+B8)/2),'Entradas'!$B$11:$B$14) -> 5000 | E7: =SUMPRODUCT(--('Entradas'!$E$11:$E$14="COLD"),--('Entradas'!$J$11:$J$14<=(B7+B8)/2),--('Entradas'!$K$11:$K$14 >=(B7+B8)/2),'Entradas'!$B$11:$B$14) -> 9000 | F7: =D7-E7 -> -4000 | G7: =C7*F7 -> -80000 | H7: =H6+G6 -> 10000 | I7: =H7+'Resumen'!$B$7 -> 80000 | J7: =IF(ABS(I7)<='Resumen'!$B$14,B7,"") | K7: =IF(ISNUMBER(J7),J7+'Entradas'!$B$4/2,"") | L7: =IF(ISNUMBER(J7),J7-'Entradas'!$B$4/2,"") | M7: =IF(ISNUMBER(J7),IF(OR(B7=$B$4,B7=$B$11),"umbral","interior"),"")
A8: ='Entradas'!J13 -> 95 | B8: =LARGE($A$4:$A$11,5) -> 135 | C8: =B8-B9 -> 20 | D8: =SUMPRODUCT(--('Entradas'!$E$11:$E$14="HOT"),--('Entradas'!$J$11:$J$14<=(B8+B9)/2),--('Entradas'!$K$11:$K$14 >=(B8+B9)/2),'Entradas'!$B$11:$B$14) -> 5000 | E8: =SUMPRODUCT(--('Entradas'!$E$11:$E$14="COLD"),--('Entradas'!$J$11:$J$14<=(B8+B9)/2),--('Entradas'!$K$11:$K$14 >=(B8+B9)/2),'Entradas'!$B$11:$B$14) -> 3000 | F8: =D8-E8 -> 2000 | G8: =C8*F8 -> 40000 | H8: =H7+G7 -> -70000 | I8: =H8+'Resumen'!$B$7 -> 0 | J8: =IF(ABS(I8)<='Resumen'!$B$14,B8,"") -> 135 | K8: =IF(ISNUMBER(J8),J8+'Entradas'!$B$4/2,"") -> 140 | L8: =IF(ISNUMBER(J8),J8-'Entradas'!$B$4/2,"") -> 130 | M8: =IF(ISNUMBER(J8),IF(OR(B8=$B$4,B8=$B$11),"umbral","interior"),"") -> interior
A9: ='Entradas'!K13 -> 155 | B9: =LARGE($A$4:$A$11,6) -> 115 | C9: =B9-B10 -> 20 | D9: =SUMPRODUCT(--('Entradas'!$E$11:$E$14="HOT"),--('Entradas'!$J$11:$J$14<=(B9+B10)/2),--('Entradas'!$K$11:$K$14 >=(B9+B10)/2),'Entradas'!$B$11:$B$14) -> 4000 | E9: =SUMPRODUCT(--('Entradas'!$E$11:$E$14="COLD"),--('Entradas'!$J$11:$J$14<=(B9+B10)/2),--('Entradas'!$K$11:$K$14 >=(B9+B10)/2),'Entradas'!$B$11:$B$14) -> 3000 | F9: =D9-E9 -> 1000 | G9: =C9*F9 -> 20000 | H9: =H8+G8 -> -30000 | I9: =H9+'Resumen'!$B$7 -> 40000 | J9: =IF(ABS(I9)<='Resumen'!$B$14,B9,"") | K9: =IF(ISNUMBER(J9),J9+'Entradas'!$B$4/2,"") | L9: =IF(ISNUMBER(J9),J9-'Entradas'!$B$4/2,"") | M9: =IF(ISNUMBER(J9),IF(OR(B9=$B$4,B9=$B$11),"umbral","interior"),"")
A10: ='Entradas'!J14 -> 135 | B10: =LARGE($A$4:$A$11,7) -> 95 | C10: =B10-B11 -> 0 | D10: =SUMPRODUCT(--('Entradas'!$E$11:$E$14="HOT"),--('Entradas'!$J$11:$J$14<=(B10+B11)/2),--('Entradas'!$K$11:$K$14 >=(B10+B11)/2),'Entradas'!$B$11:$B$14) -> 4000 | E10: =SUMPRODUCT(--('Entradas'!$E$11:$E$14="COLD"),--('Entradas'!$J$11:$J$14<=(B10+B11)/2),--('Entradas'!$K$11:$K$14 >=(B10+B11)/2),'Entradas'!$B$11:$B$14) -> 3000 | F10: =D10-E10 -> 1000 | G10: =C10*F10 -> 0 | H10: =H9+G9 -> -10000 | I10: =H10+'Resumen'!$B$7 -> 60000 | J10: =IF(ABS(I10)<='Resumen'!$B$14,B10,"") | K10: =IF(ISNUMBER(J10),J10+'Entradas'!$B$4/2,"") | L10: =IF(ISNUMBER(J10),J10-'Entradas'!$B$4/2,"") | M10: =IF(ISNUMBER(J10),IF(OR(B10=$B$4,B10=$B$11),"umbral","interior"),"")
A11: ='Entradas'!K14 -> 195 | B11: =LARGE($A$4:$A$11,8) -> 95 | H11: =H10+G10 -> -10000 | I11: =H11+'Resumen'!$B$7 -> 60000 | J11: =IF(ABS(I11)<='Resumen'!$B$14,B11,"") | K11: =IF(ISNUMBER(J11),J11+'Entradas'!$B$4/2,"") | L11: =IF(ISNUMBER(J11),J11-'Entradas'!$B$4/2,"") | M11: =IF(ISNUMBER(J11),IF(OR(B11=$B$4,B11=$B$11),"umbral","interior"),"")

Sheet Compuestas
A1: Integración de las curvas compuestas
A2: Hhot inicia en 0. Hcold se desplaza QCmin. Segmentos verticales interiores indican huecos sin carga.
A3: T sin ordenar | B3: T ascendente | C3: T media | D3: ΣCP hot | E3: ΣCP cold | F3: ΔH hot | G3: ΔH cold | H3: H hot | I3: H cold origen | J3: H cold ajustada | K3: T hot gráfico | L3: T cold gráfico | M3: T* hot | N3: T* cold | O3: Índice tramo
A4: ='Entradas'!H11 -> 120 | B4: =SMALL($A$4:$A$11,1) -> 90 | C4: =(B4+B5)/2 -> 95 | D4: =SUMPRODUCT(--('Entradas'!$E$11:$E$14="HOT"),--('Entradas'!$H$11:$H$14<=C4),--('Entradas'!$I$11:$I$14>=C4),'Entradas'!$B$11:$B$14) -> 0 | E4: =SUMPRODUCT(--('Entradas'!$E$11:$E$14="COLD"),--('Entradas'!$H$11:$H$14<=C4),--('Entradas'!$I$11:$I$14>=C4),'Entradas'!$B$11:$B$14) -> 3000 | F4: =D4*(B5-B4) -> 0 | G4: =E4*(B5-B4) -> 30000 | H4: =0 -> 0 | I4: =0 -> 0 | J4: =I4+'Resumen'!$B$8 -> 60000 | K4: =IF(OR(H5>H4),B4,"") | L4: =IF(OR(I5>I4),B4,"") -> 90 | M4: =IF(ISNUMBER(K4),K4+-1*'Entradas'!$B$4/2,"") | N4: =IF(ISNUMBER(L4),L4+1*'Entradas'!$B$4/2,"") -> 95 | O4: 1
A5: ='Entradas'!I11 -> 250 | B5: =SMALL($A$4:$A$11,2) -> 100 | C5: =(B5+B6)/2 -> 110 | D5: =SUMPRODUCT(--('Entradas'!$E$11:$E$14="HOT"),--('Entradas'!$H$11:$H$14<=C5),--('Entradas'!$I$11:$I$14>=C5),'Entradas'!$B$11:$B$14) -> 4000 | E5: =SUMPRODUCT(--('Entradas'!$E$11:$E$14="COLD"),--('Entradas'!$H$11:$H$14<=C5),--('Entradas'!$I$11:$I$14>=C5),'Entradas'!$B$11:$B$14) -> 3000 | F5: =D5*(B6-B5) -> 80000 | G5: =E5*(B6-B5) -> 60000 | H5: =H4+F4 -> 0 | I5: =I4+G4 -> 30000 | J5: =I5+'Resumen'!$B$8 -> 90000 | K5: =IF(OR(H5>H4,H6>H5),B5,"") -> 100 | L5: =IF(OR(I5>I4,I6>I5),B5,"") -> 100 | M5: =IF(ISNUMBER(K5),K5+-1*'Entradas'!$B$4/2,"") -> 95 | N5: =IF(ISNUMBER(L5),L5+1*'Entradas'!$B$4/2,"") -> 105 | O5: 2
A6: ='Entradas'!H12 -> 100 | B6: =SMALL($A$4:$A$11,3) -> 120 | C6: =(B6+B7)/2 -> 125 | D6: =SUMPRODUCT(--('Entradas'!$E$11:$E$14="HOT"),--('Entradas'!$H$11:$H$14<=C6),--('Entradas'!$I$11:$I$14>=C6),'Entradas'!$B$11:$B$14) -> 5000 | E6: =SUMPRODUCT(--('Entradas'!$E$11:$E$14="COLD"),--('Entradas'!$H$11:$H$14<=C6),--('Entradas'!$I$11:$I$14>=C6),'Entradas'!$B$11:$B$14) -> 3000 | F6: =D6*(B7-B6) -> 50000 | G6: =E6*(B7-B6) -> 30000 | H6: =H5+F5 -> 80000 | I6: =I5+G5 -> 90000 | J6: =I6+'Resumen'!$B$8 -> 150000 | K6: =IF(OR(H6>H5,H7>H6),B6,"") -> 120 | L6: =IF(OR(I6>I5,I7>I6),B6,"") -> 120 | M6: =IF(ISNUMBER(K6),K6+-1*'Entradas'!$B$4/2,"") -> 115 | N6: =IF(ISNUMBER(L6),L6+1*'Entradas'!$B$4/2,"") -> 125 | O6: 3
A7: ='Entradas'!I12 -> 200 | B7: =SMALL($A$4:$A$11,4) -> 130 | C7: =(B7+B8)/2 -> 140 | D7: =SUMPRODUCT(--('Entradas'!$E$11:$E$14="HOT"),--('Entradas'!$H$11:$H$14<=C7),--('Entradas'!$I$11:$I$14>=C7),'Entradas'!$B$11:$B$14) -> 5000 | E7: =SUMPRODUCT(--('Entradas'!$E$11:$E$14="COLD"),--('Entradas'!$H$11:$H$14<=C7),--('Entradas'!$I$11:$I$14>=C7),'Entradas'!$B$11:$B$14) -> 9000 | F7: =D7*(B8-B7) -> 100000 | G7: =E7*(B8-B7) -> 180000 | H7: =H6+F6 -> 130000 | I7: =I6+G6 -> 120000 | J7: =I7+'Resumen'!$B$8 -> 180000 | K7: =IF(OR(H7>H6,H8>H7),B7,"") -> 130 | L7: =IF(OR(I7>I6,I8>I7),B7,"") -> 130 | M7: =IF(ISNUMBER(K7),K7+-1*'Entradas'!$B$4/2,"") -> 125 | N7: =IF(ISNUMBER(L7),L7+1*'Entradas'!$B$4/2,"") -> 135 | O7: 4
A8: ='Entradas'!H13 -> 90 | B8: =SMALL($A$4:$A$11,5) -> 150 | C8: =(B8+B9)/2 -> 170 | D8: =SUMPRODUCT(--('Entradas'!$E$11:$E$14="HOT"),--('Entradas'!$H$11:$H$14<=C8),--('Entradas'!$I$11:$I$14>=C8),'Entradas'!$B$11:$B$14) -> 5000 | E8: =SUMPRODUCT(--('Entradas'!$E$11:$E$14="COLD"),--('Entradas'!$H$11:$H$14<=C8),--('Entradas'!$I$11:$I$14>=C8),'Entradas'!$B$11:$B$14) -> 6000 | F8: =D8*(B9-B8) -> 200000 | G8: =E8*(B9-B8) -> 240000 | H8: =H7+F7 -> 230000 | I8: =I7+G7 -> 300000 | J8: =I8+'Resumen'!$B$8 -> 360000 | K8: =IF(OR(H8>H7,H9>H8),B8,"") -> 150 | L8: =IF(OR(I8>I7,I9>I8),B8,"") -> 150 | M8: =IF(ISNUMBER(K8),K8+-1*'Entradas'!$B$4/2,"") -> 145 | N8: =IF(ISNUMBER(L8),L8+1*'Entradas'!$B$4/2,"") -> 155 | O8: 5
A9: ='Entradas'!I13 -> 150 | B9: =SMALL($A$4:$A$11,6) -> 190 | C9: =(B9+B10)/2 -> 195 | D9: =SUMPRODUCT(--('Entradas'!$E$11:$E$14="HOT"),--('Entradas'!$H$11:$H$14<=C9),--('Entradas'!$I$11:$I$14>=C9),'Entradas'!$B$11:$B$14) -> 5000 | E9: =SUMPRODUCT(--('Entradas'!$E$11:$E$14="COLD"),--('Entradas'!$H$11:$H$14<=C9),--('Entradas'!$I$11:$I$14>=C9),'Entradas'!$B$11:$B$14) -> 0 | F9: =D9*(B10-B9) -> 50000 | G9: =E9*(B10-B9) -> 0 | H9: =H8+F8 -> 430000 | I9: =I8+G8 -> 540000 | J9: =I9+'Resumen'!$B$8 -> 600000 | K9: =IF(OR(H9>H8,H10>H9),B9,"") -> 190 | L9: =IF(OR(I9>I8,I10>I9),B9,"") -> 190 | M9: =IF(ISNUMBER(K9),K9+-1*'Entradas'!$B$4/2,"") -> 185 | N9: =IF(ISNUMBER(L9),L9+1*'Entradas'!$B$4/2,"") -> 195 | O9: 6
A10: ='Entradas'!H14 -> 130 | B10: =SMALL($A$4:$A$11,7) -> 200 | C10: =(B10+B11)/2 -> 225 | D10: =SUMPRODUCT(--('Entradas'!$E$11:$E$14="HOT"),--('Entradas'!$H$11:$H$14<=C10),--('Entradas'!$I$11:$I$14>=C10),'Entradas'!$B$11:$B$14) -> 1000 | E10: =SUMPRODUCT(--('Entradas'!$E$11:$E$14="COLD"),--('Entradas'!$H$11:$H$14<=C10),--('Entradas'!$I$11:$I$14>=C10),'Entradas'!$B$11:$B$14) -> 0 | F10: =D10*(B11-B10) -> 50000 | G10: =E10*(B11-B10) -> 0 | H10: =H9+F9 -> 480000 | I10: =I9+G9 -> 540000 | J10: =I10+'Resumen'!$B$8 -> 600000 | K10: =IF(OR(H10>H9,H11>H10),B10,"") -> 200 | L10: =IF(OR(I10>I9,I11>I10),B10,"") | M10: =IF(ISNUMBER(K10),K10+-1*'Entradas'!$B$4/2,"") -> 195 | N10: =IF(ISNUMBER(L10),L10+1*'Entradas'!$B$4/2,"") | O10: 7
A11: ='Entradas'!I14 -> 190 | B11: =SMALL($A$4:$A$11,8) -> 250 | H11: =H10+F10 -> 530000 | I11: =I10+G10 -> 540000 | J11: =I11+'Resumen'!$B$8 -> 600000 | K11: =IF(OR(H11>H10),B11,"") -> 250 | L11: =IF(OR(I11>I10),B11,"") | M11: =IF(ISNUMBER(K11),K11+-1*'Entradas'!$B$4/2,"") -> 245 | N11: =IF(ISNUMBER(L11),L11+1*'Entradas'!$B$4/2,"")
A16: Corriente | B16: H local | C16: T real
A17: ='Entradas'!A11 -> H1 | B17: =IF('Entradas'!E11="HOT",1,0)*'Entradas'!F11 -> 130000 | C17: ='Entradas'!C11 -> 250
A18: ='Entradas'!A11 -> H1 | B18: =IF('Entradas'!E11="HOT",0,1)*'Entradas'!F11 -> 0 | C18: ='Entradas'!D11 -> 120
A19: ='Entradas'!A12 -> H2 | B19: =IF('Entradas'!E12="HOT",1,0)*'Entradas'!F12 -> 400000 | C19: ='Entradas'!C12 -> 200
A20: ='Entradas'!A12 -> H2 | B20: =IF('Entradas'!E12="HOT",0,1)*'Entradas'!F12 -> 0 | C20: ='Entradas'!D12 -> 100
A21: ='Entradas'!A13 -> C3 | B21: =IF('Entradas'!E13="HOT",1,0)*'Entradas'!F13 -> 0 | C21: ='Entradas'!C13 -> 90
A22: ='Entradas'!A13 -> C3 | B22: =IF('Entradas'!E13="HOT",0,1)*'Entradas'!F13 -> 180000 | C22: ='Entradas'!D13 -> 150
A23: ='Entradas'!A14 -> C4 | B23: =IF('Entradas'!E14="HOT",1,0)*'Entradas'!F14 -> 0 | C23: ='Entradas'!C14 -> 130
A24: ='Entradas'!A14 -> C4 | B24: =IF('Entradas'!E14="HOT",0,1)*'Entradas'!F14 -> 360000 | C24: ='Entradas'!D14 -> 190

Sheet Tramos_red
A1: Tramos de intercambio y división de corrientes
A2: Cada tramo tiene un intervalo de temperaturas caliente y frío. Las fracciones CP definen las ramas.
A3: H sin ordenar | B3: H ordenada | C3: ΔH tramo | D3: H media | E3: Índice hot | F3: Índice cold | G3: CP hot | H3: CP cold | I3: Th baja | J3: Th alta | K3: Tc baja | L3: Tc alta | M3: Q proceso | N3: Q refrigeración | O3: Q calentamiento | P3: ΔT extremo 1 | Q3: ΔT extremo 2 | R3: ΔT log media | S3: Área proceso | T3: fh H1 | U3: fh H2 | V3: fh C3 | W3: fh C4 | X3: fc H1 | Y3: fc H2 | Z3: fc C3 | AA3: fc C4
A4: ='Compuestas'!H4 -> 0 | B4: =SMALL($A$4:$A$19,1) -> 0 | C4: =B5-B4 -> 0 | D4: =(B4+B5)/2 -> 0 | E4: =IF(C4<='Resumen'!$B$14,0,SUMPRODUCT(--('Compuestas'!$H$4:$H$10<=D4),--('Compuestas'!$H$5:$H$11>D4),'Compuestas'!$O$4:$O$10)) -> 0 | F4: =IF(C4<='Resumen'!$B$14,0,SUMPRODUCT(--('Compuestas'!$J$4:$J$10<=D4),--('Compuestas'!$J$5:$J$11>D4),'Compuestas'!$O$4:$O$10)) -> 0 | G4: =IF(E4>0,INDEX('Compuestas'!$D$4:$D$10,E4),0) -> 0 | H4: =IF(F4>0,INDEX('Compuestas'!$E$4:$E$10,F4),0) -> 0 | I4: =IF(E4>0,INDEX('Compuestas'!$B$4:$B$10,E4)+(B4-INDEX('Compuestas'!$H$4:$H$10,E4))/G4,0) -> 0 | J4: =IF(E4>0,INDEX('Compuestas'!$B$4:$B$10,E4)+(B5-INDEX('Compuestas'!$H$4:$H$10,E4))/G4,0) -> 0 | K4: =IF(F4>0,INDEX('Compuestas'!$B$4:$B$10,F4)+(B4-INDEX('Compuestas'!$J$4:$J$10,F4))/H4,0) -> 0 | L4: =IF(F4>0,INDEX('Compuestas'!$B$4:$B$10,F4)+(B5-INDEX('Compuestas'!$J$4:$J$10,F4))/H4,0) -> 0 | M4: =IF(AND(E4>0,F4>0),C4,0) -> 0 | N4: =IF(AND(E4>0,F4=0),C4,0) -> 0 | O4: =IF(AND(E4=0,F4>0),C4,0) -> 0 | P4: =IF(M4>0,J4-L4,0) -> 0 | Q4: =IF(M4>0,I4-K4,0) -> 0 | R4: =IF(M4=0,0,IF(MIN(P4,Q4)<=0,0,IF(ABS(P4-Q4)<0.00000001,(P4+Q4)/2,(P4-Q4)/LN(P4/Q4)))) -> 0 | S4: =IF(M4=0,0,IF('Entradas'!$B$5=0,"sin U",IF(R4=0,"infinita",M4/('Entradas'!$B$5*R4)))) -> 0 | T4: =IF(AND(E4>0,'Entradas'!E11="HOT",'Entradas'!H11<=(I4+J4)/2,'Entradas'!I11>=(I4+J4)/2),'Entradas'!B11/G4,0) -> 0 | U4: =IF(AND(E4>0,'Entradas'!E12="HOT",'Entradas'!H12<=(I4+J4)/2,'Entradas'!I12>=(I4+J4)/2),'Entradas'!B12/G4,0) -> 0 | V4: =IF(AND(E4>0,'Entradas'!E13="HOT",'Entradas'!H13<=(I4+J4)/2,'Entradas'!I13>=(I4+J4)/2),'Entradas'!B13/G4,0) -> 0 | W4: =IF(AND(E4>0,'Entradas'!E14="HOT",'Entradas'!H14<=(I4+J4)/2,'Entradas'!I14>=(I4+J4)/2),'Entradas'!B14/G4,0) -> 0 | X4: =IF(AND(F4>0,'Entradas'!E11="COLD",'Entradas'!H11<=(K4+L4)/2,'Entradas'!I11>=(K4+L4)/2),'Entradas'!B11/H4,0) -> 0 | Y4: =IF(AND(F4>0,'Entradas'!E12="COLD",'Entradas'!H12<=(K4+L4)/2,'Entradas'!I12>=(K4+L4)/2),'Entradas'!B12/H4,0) -> 0 | Z4: =IF(AND(F4>0,'Entradas'!E13="COLD",'Entradas'!H13<=(K4+L4)/2,'Entradas'!I13>=(K4+L4)/2),'Entradas'!B13/H4,0) -> 0 | AA4: =IF(AND(F4>0,'Entradas'!E14="COLD",'Entradas'!H14<=(K4+L4)/2,'Entradas'!I14>=(K4+L4)/2),'Entradas'!B14/H4,0) -> 0
A5: ='Compuestas'!H5 -> 0 | B5: =SMALL($A$4:$A$19,2) -> 0 | C5: =B6-B5 -> 60000 | D5: =(B5+B6)/2 -> 30000 | E5: =IF(C5<='Resumen'!$B$14,0,SUMPRODUCT(--('Compuestas'!$H$4:$H$10<=D5),--('Compuestas'!$H$5:$H$11>D5),'Compuestas'!$O$4:$O$10)) -> 2 | F5: =IF(C5<='Resumen'!$B$14,0,SUMPRODUCT(--('Compuestas'!$J$4:$J$10<=D5),--('Compuestas'!$J$5:$J$11>D5),'Compuestas'!$O$4:$O$10)) -> 0 | G5: =IF(E5>0,INDEX('Compuestas'!$D$4:$D$10,E5),0) -> 4000 | H5: =IF(F5>0,INDEX('Compuestas'!$E$4:$E$10,F5),0) -> 0 | I5: =IF(E5>0,INDEX('Compuestas'!$B$4:$B$10,E5)+(B5-INDEX('Compuestas'!$H$4:$H$10,E5))/G5,0) -> 100 | J5: =IF(E5>0,INDEX('Compuestas'!$B$4:$B$10,E5)+(B6-INDEX('Compuestas'!$H$4:$H$10,E5))/G5,0) -> 115 | K5: =IF(F5>0,INDEX('Compuestas'!$B$4:$B$10,F5)+(B5-INDEX('Compuestas'!$J$4:$J$10,F5))/H5,0) -> 0 | L5: =IF(F5>0,INDEX('Compuestas'!$B$4:$B$10,F5)+(B6-INDEX('Compuestas'!$J$4:$J$10,F5))/H5,0) -> 0 | M5: =IF(AND(E5>0,F5>0),C5,0) -> 0 | N5: =IF(AND(E5>0,F5=0),C5,0) -> 60000 | O5: =IF(AND(E5=0,F5>0),C5,0) -> 0 | P5: =IF(M5>0,J5-L5,0) -> 0 | Q5: =IF(M5>0,I5-K5,0) -> 0 | R5: =IF(M5=0,0,IF(MIN(P5,Q5)<=0,0,IF(ABS(P5-Q5)<0.00000001,(P5+Q5)/2,(P5-Q5)/LN(P5/Q5)))) -> 0 | S5: =IF(M5=0,0,IF('Entradas'!$B$5=0,"sin U",IF(R5=0,"infinita",M5/('Entradas'!$B$5*R5)))) -> 0 | T5: =IF(AND(E5>0,'Entradas'!E11="HOT",'Entradas'!H11<=(I5+J5)/2,'Entradas'!I11>=(I5+J5)/2),'Entradas'!B11/G5,0) -> 0 | U5: =IF(AND(E5>0,'Entradas'!E12="HOT",'Entradas'!H12<=(I5+J5)/2,'Entradas'!I12>=(I5+J5)/2),'Entradas'!B12/G5,0) -> 1 | V5: =IF(AND(E5>0,'Entradas'!E13="HOT",'Entradas'!H13<=(I5+J5)/2,'Entradas'!I13>=(I5+J5)/2),'Entradas'!B13/G5,0) -> 0 | W5: =IF(AND(E5>0,'Entradas'!E14="HOT",'Entradas'!H14<=(I5+J5)/2,'Entradas'!I14>=(I5+J5)/2),'Entradas'!B14/G5,0) -> 0 | X5: =IF(AND(F5>0,'Entradas'!E11="COLD",'Entradas'!H11<=(K5+L5)/2,'Entradas'!I11>=(K5+L5)/2),'Entradas'!B11/H5,0) -> 0 | Y5: =IF(AND(F5>0,'Entradas'!E12="COLD",'Entradas'!H12<=(K5+L5)/2,'Entradas'!I12>=(K5+L5)/2),'Entradas'!B12/H5,0) -> 0 | Z5: =IF(AND(F5>0,'Entradas'!E13="COLD",'Entradas'!H13<=(K5+L5)/2,'Entradas'!I13>=(K5+L5)/2),'Entradas'!B13/H5,0) -> 0 | AA5: =IF(AND(F5>0,'Entradas'!E14="COLD",'Entradas'!H14<=(K5+L5)/2,'Entradas'!I14>=(K5+L5)/2),'Entradas'!B14/H5,0) -> 0
A6: ='Compuestas'!H6 -> 80000 | B6: =SMALL($A$4:$A$19,3) -> 60000 | C6: =B7-B6 -> 20000 | D6: =(B6+B7)/2 -> 70000 | E6: =IF(C6<='Resumen'!$B$14,0,SUMPRODUCT(--('Compuestas'!$H$4:$H$10<=D6),--('Compuestas'!$H$5:$H$11>D6),'Compuestas'!$O$4:$O$10)) -> 2 | F6: =IF(C6<='Resumen'!$B$14,0,SUMPRODUCT(--('Compuestas'!$J$4:$J$10<=D6),--('Compuestas'!$J$5:$J$11>D6),'Compuestas'!$O$4:$O$10)) -> 1 | G6: =IF(E6>0,INDEX('Compuestas'!$D$4:$D$10,E6),0) -> 4000 | H6: =IF(F6>0,INDEX('Compuestas'!$E$4:$E$10,F6),0) -> 3000 | I6: =IF(E6>0,INDEX('Compuestas'!$B$4:$B$10,E6)+(B6-INDEX('Compuestas'!$H$4:$H$10,E6))/G6,0) -> 115 | J6: =IF(E6>0,INDEX('Compuestas'!$B$4:$B$10,E6)+(B7-INDEX('Compuestas'!$H$4:$H$10,E6))/G6,0) -> 120 | K6: =IF(F6>0,INDEX('Compuestas'!$B$4:$B$10,F6)+(B6-INDEX('Compuestas'!$J$4:$J$10,F6))/H6,0) -> 90 | L6: =IF(F6>0,INDEX('Compuestas'!$B$4:$B$10,F6)+(B7-INDEX('Compuestas'!$J$4:$J$10,F6))/H6,0) -> 96.666667 | M6: =IF(AND(E6>0,F6>0),C6,0) -> 20000 | N6: =IF(AND(E6>0,F6=0),C6,0) -> 0 | O6: =IF(AND(E6=0,F6>0),C6,0) -> 0 | P6: =IF(M6>0,J6-L6,0) -> 23.333333 | Q6: =IF(M6>0,I6-K6,0) -> 25 | R6: =IF(M6=0,0,IF(MIN(P6,Q6)<=0,0,IF(ABS(P6-Q6)<0.00000001,(P6+Q6)/2,(P6-Q6)/LN(P6/Q6)))) -> 24.157085 | S6: =IF(M6=0,0,IF('Entradas'!$B$5=0,"sin U",IF(R6=0,"infinita",M6/('Entradas'!$B$5*R6)))) -> sin U | T6: =IF(AND(E6>0,'Entradas'!E11="HOT",'Entradas'!H11<=(I6+J6)/2,'Entradas'!I11>=(I6+J6)/2),'Entradas'!B11/G6,0) -> 0 | U6: =IF(AND(E6>0,'Entradas'!E12="HOT",'Entradas'!H12<=(I6+J6)/2,'Entradas'!I12>=(I6+J6)/2),'Entradas'!B12/G6,0) -> 1 | V6: =IF(AND(E6>0,'Entradas'!E13="HOT",'Entradas'!H13<=(I6+J6)/2,'Entradas'!I13>=(I6+J6)/2),'Entradas'!B13/G6,0) -> 0 | W6: =IF(AND(E6>0,'Entradas'!E14="HOT",'Entradas'!H14<=(I6+J6)/2,'Entradas'!I14>=(I6+J6)/2),'Entradas'!B14/G6,0) -> 0 | X6: =IF(AND(F6>0,'Entradas'!E11="COLD",'Entradas'!H11<=(K6+L6)/2,'Entradas'!I11>=(K6+L6)/2),'Entradas'!B11/H6,0) -> 0 | Y6: =IF(AND(F6>0,'Entradas'!E12="COLD",'Entradas'!H12<=(K6+L6)/2,'Entradas'!I12>=(K6+L6)/2),'Entradas'!B12/H6,0) -> 0 | Z6: =IF(AND(F6>0,'Entradas'!E13="COLD",'Entradas'!H13<=(K6+L6)/2,'Entradas'!I13>=(K6+L6)/2),'Entradas'!B13/H6,0) -> 1 | AA6: =IF(AND(F6>0,'Entradas'!E14="COLD",'Entradas'!H14<=(K6+L6)/2,'Entradas'!I14>=(K6+L6)/2),'Entradas'!B14/H6,0) -> 0
A7: ='Compuestas'!H7 -> 130000 | B7: =SMALL($A$4:$A$19,4) -> 80000 | C7: =B8-B7 -> 10000 | D7: =(B7+B8)/2 -> 85000 | E7: =IF(C7<='Resumen'!$B$14,0,SUMPRODUCT(--('Compuestas'!$H$4:$H$10<=D7),--('Compuestas'!$H$5:$H$11>D7),'Compuestas'!$O$4:$O$10)) -> 3 | F7: =IF(C7<='Resumen'!$B$14,0,SUMPRODUCT(--('Compuestas'!$J$4:$J$10<=D7),--('Compuestas'!$J$5:$J$11>D7),'Compuestas'!$O$4:$O$10)) -> 1 | G7: =IF(E7>0,INDEX('Compuestas'!$D$4:$D$10,E7),0) -> 5000 | H7: =IF(F7>0,INDEX('Compuestas'!$E$4:$E$10,F7),0) -> 3000 | I7: =IF(E7>0,INDEX('Compuestas'!$B$4:$B$10,E7)+(B7-INDEX('Compuestas'!$H$4:$H$10,E7))/G7,0) -> 120 | J7: =IF(E7>0,INDEX('Compuestas'!$B$4:$B$10,E7)+(B8-INDEX('Compuestas'!$H$4:$H$10,E7))/G7,0) -> 122 | K7: =IF(F7>0,INDEX('Compuestas'!$B$4:$B$10,F7)+(B7-INDEX('Compuestas'!$J$4:$J$10,F7))/H7,0) -> 96.666667 | L7: =IF(F7>0,INDEX('Compuestas'!$B$4:$B$10,F7)+(B8-INDEX('Compuestas'!$J$4:$J$10,F7))/H7,0) -> 100 | M7: =IF(AND(E7>0,F7>0),C7,0) -> 10000 | N7: =IF(AND(E7>0,F7=0),C7,0) -> 0 | O7: =IF(AND(E7=0,F7>0),C7,0) -> 0 | P7: =IF(M7>0,J7-L7,0) -> 22 | Q7: =IF(M7>0,I7-K7,0) -> 23.333333 | R7: =IF(M7=0,0,IF(MIN(P7,Q7)<=0,0,IF(ABS(P7-Q7)<0.00000001,(P7+Q7)/2,(P7-Q7)/LN(P7/Q7)))) -> 22.660129 | S7: =IF(M7=0,0,IF('Entradas'!$B$5=0,"sin U",IF(R7=0,"infinita",M7/('Entradas'!$B$5*R7)))) -> sin U | T7: =IF(AND(E7>0,'Entradas'!E11="HOT",'Entradas'!H11<=(I7+J7)/2,'Entradas'!I11>=(I7+J7)/2),'Entradas'!B11/G7,0) -> 0.2 | U7: =IF(AND(E7>0,'Entradas'!E12="HOT",'Entradas'!H12<=(I7+J7)/2,'Entradas'!I12>=(I7+J7)/2),'Entradas'!B12/G7,0) -> 0.8 | V7: =IF(AND(E7>0,'Entradas'!E13="HOT",'Entradas'!H13<=(I7+J7)/2,'Entradas'!I13>=(I7+J7)/2),'Entradas'!B13/G7,0) -> 0 | W7: =IF(AND(E7>0,'Entradas'!E14="HOT",'Entradas'!H14<=(I7+J7)/2,'Entradas'!I14>=(I7+J7)/2),'Entradas'!B14/G7,0) -> 0 | X7: =IF(AND(F7>0,'Entradas'!E11="COLD",'Entradas'!H11<=(K7+L7)/2,'Entradas'!I11>=(K7+L7)/2),'Entradas'!B11/H7,0) -> 0 | Y7: =IF(AND(F7>0,'Entradas'!E12="COLD",'Entradas'!H12<=(K7+L7)/2,'Entradas'!I12>=(K7+L7)/2),'Entradas'!B12/H7,0) -> 0 | Z7: =IF(AND(F7>0,'Entradas'!E13="COLD",'Entradas'!H13<=(K7+L7)/2,'Entradas'!I13>=(K7+L7)/2),'Entradas'!B13/H7,0) -> 1 | AA7: =IF(AND(F7>0,'Entradas'!E14="COLD",'Entradas'!H14<=(K7+L7)/2,'Entradas'!I14>=(K7+L7)/2),'Entradas'!B14/H7,0) -> 0
A8: ='Compuestas'!H8 -> 230000 | B8: =SMALL($A$4:$A$19,5) -> 90000 | C8: =B9-B8 -> 40000 | D8: =(B8+B9)/2 -> 110000 | E8: =IF(C8<='Resumen'!$B$14,0,SUMPRODUCT(--('Compuestas'!$H$4:$H$10<=D8),--('Compuestas'!$H$5:$H$11>D8),'Compuestas'!$O$4:$O$10)) -> 3 | F8: =IF(C8<='Resumen'!$B$14,0,SUMPRODUCT(--('Compuestas'!$J$4:$J$10<=D8),--('Compuestas'!$J$5:$J$11>D8),'Compuestas'!$O$4:$O$10)) -> 2 | G8: =IF(E8>0,INDEX('Compuestas'!$D$4:$D$10,E8),0) -> 5000 | H8: =IF(F8>0,INDEX('Compuestas'!$E$4:$E$10,F8),0) -> 3000 | I8: =IF(E8>0,INDEX('Compuestas'!$B$4:$B$10,E8)+(B8-INDEX('Compuestas'!$H$4:$H$10,E8))/G8,0) -> 122 | J8: =IF(E8>0,INDEX('Compuestas'!$B$4:$B$10,E8)+(B9-INDEX('Compuestas'!$H$4:$H$10,E8))/G8,0) -> 130 | K8: =IF(F8>0,INDEX('Compuestas'!$B$4:$B$10,F8)+(B8-INDEX('Compuestas'!$J$4:$J$10,F8))/H8,0) -> 100 | L8: =IF(F8>0,INDEX('Compuestas'!$B$4:$B$10,F8)+(B9-INDEX('Compuestas'!$J$4:$J$10,F8))/H8,0) -> 113.33333 | M8: =IF(AND(E8>0,F8>0),C8,0) -> 40000 | N8: =IF(AND(E8>0,F8=0),C8,0) -> 0 | O8: =IF(AND(E8=0,F8>0),C8,0) -> 0 | P8: =IF(M8>0,J8-L8,0) -> 16.666667 | Q8: =IF(M8>0,I8-K8,0) -> 22 | R8: =IF(M8=0,0,IF(MIN(P8,Q8)<=0,0,IF(ABS(P8-Q8)<0.00000001,(P8+Q8)/2,(P8-Q8)/LN(P8/Q8)))) -> 19.2101 | S8: =IF(M8=0,0,IF('Entradas'!$B$5=0,"sin U",IF(R8=0,"infinita",M8/('Entradas'!$B$5*R8)))) -> sin U | T8: =IF(AND(E8>0,'Entradas'!E11="HOT",'Entradas'!H11<=(I8+J8)/2,'Entradas'!I11>=(I8+J8)/2),'Entradas'!B11/G8,0) -> 0.2 | U8: =IF(AND(E8>0,'Entradas'!E12="HOT",'Entradas'!H12<=(I8+J8)/2,'Entradas'!I12>=(I8+J8)/2),'Entradas'!B12/G8,0) -> 0.8 | V8: =IF(AND(E8>0,'Entradas'!E13="HOT",'Entradas'!H13<=(I8+J8)/2,'Entradas'!I13>=(I8+J8)/2),'Entradas'!B13/G8,0) -> 0 | W8: =IF(AND(E8>0,'Entradas'!E14="HOT",'Entradas'!H14<=(I8+J8)/2,'Entradas'!I14>=(I8+J8)/2),'Entradas'!B14/G8,0) -> 0 | X8: =IF(AND(F8>0,'Entradas'!E11="COLD",'Entradas'!H11<=(K8+L8)/2,'Entradas'!I11>=(K8+L8)/2),'Entradas'!B11/H8,0) -> 0 | Y8: =IF(AND(F8>0,'Entradas'!E12="COLD",'Entradas'!H12<=(K8+L8)/2,'Entradas'!I12>=(K8+L8)/2),'Entradas'!B12/H8,0) -> 0 | Z8: =IF(AND(F8>0,'Entradas'!E13="COLD",'Entradas'!H13<=(K8+L8)/2,'Entradas'!I13>=(K8+L8)/2),'Entradas'!B13/H8,0) -> 1 | AA8: =IF(AND(F8>0,'Entradas'!E14="COLD",'Entradas'!H14<=(K8+L8)/2,'Entradas'!I14>=(K8+L8)/2),'Entradas'!B14/H8,0) -> 0
A9: ='Compuestas'!H9 -> 430000 | B9: =SMALL($A$4:$A$19,6) -> 130000 | C9: =B10-B9 -> 20000 | D9: =(B9+B10)/2 -> 140000 | E9: =IF(C9<='Resumen'!$B$14,0,SUMPRODUCT(--('Compuestas'!$H$4:$H$10<=D9),--('Compuestas'!$H$5:$H$11>D9),'Compuestas'!$O$4:$O$10)) -> 4 | F9: =IF(C9<='Resumen'!$B$14,0,SUMPRODUCT(--('Compuestas'!$J$4:$J$10<=D9),--('Compuestas'!$J$5:$J$11>D9),'Compuestas'!$O$4:$O$10)) -> 2 | G9: =IF(E9>0,INDEX('Compuestas'!$D$4:$D$10,E9),0) -> 5000 | H9: =IF(F9>0,INDEX('Compuestas'!$E$4:$E$10,F9),0) -> 3000 | I9: =IF(E9>0,INDEX('Compuestas'!$B$4:$B$10,E9)+(B9-INDEX('Compuestas'!$H$4:$H$10,E9))/G9,0) -> 130 | J9: =IF(E9>0,INDEX('Compuestas'!$B$4:$B$10,E9)+(B10-INDEX('Compuestas'!$H$4:$H$10,E9))/G9,0) -> 134 | K9: =IF(F9>0,INDEX('Compuestas'!$B$4:$B$10,F9)+(B9-INDEX('Compuestas'!$J$4:$J$10,F9))/H9,0) -> 113.33333 | L9: =IF(F9>0,INDEX('Compuestas'!$B$4:$B$10,F9)+(B10-INDEX('Compuestas'!$J$4:$J$10,F9))/H9,0) -> 120 | M9: =IF(AND(E9>0,F9>0),C9,0) -> 20000 | N9: =IF(AND(E9>0,F9=0),C9,0) -> 0 | O9: =IF(AND(E9=0,F9>0),C9,0) -> 0 | P9: =IF(M9>0,J9-L9,0) -> 14 | Q9: =IF(M9>0,I9-K9,0) -> 16.666667 | R9: =IF(M9=0,0,IF(MIN(P9,Q9)<=0,0,IF(ABS(P9-Q9)<0.00000001,(P9+Q9)/2,(P9-Q9)/LN(P9/Q9)))) -> 15.294608 | S9: =IF(M9=0,0,IF('Entradas'!$B$5=0,"sin U",IF(R9=0,"infinita",M9/('Entradas'!$B$5*R9)))) -> sin U | T9: =IF(AND(E9>0,'Entradas'!E11="HOT",'Entradas'!H11<=(I9+J9)/2,'Entradas'!I11>=(I9+J9)/2),'Entradas'!B11/G9,0) -> 0.2 | U9: =IF(AND(E9>0,'Entradas'!E12="HOT",'Entradas'!H12<=(I9+J9)/2,'Entradas'!I12>=(I9+J9)/2),'Entradas'!B12/G9,0) -> 0.8 | V9: =IF(AND(E9>0,'Entradas'!E13="HOT",'Entradas'!H13<=(I9+J9)/2,'Entradas'!I13>=(I9+J9)/2),'Entradas'!B13/G9,0) -> 0 | W9: =IF(AND(E9>0,'Entradas'!E14="HOT",'Entradas'!H14<=(I9+J9)/2,'Entradas'!I14>=(I9+J9)/2),'Entradas'!B14/G9,0) -> 0 | X9: =IF(AND(F9>0,'Entradas'!E11="COLD",'Entradas'!H11<=(K9+L9)/2,'Entradas'!I11>=(K9+L9)/2),'Entradas'!B11/H9,0) -> 0 | Y9: =IF(AND(F9>0,'Entradas'!E12="COLD",'Entradas'!H12<=(K9+L9)/2,'Entradas'!I12>=(K9+L9)/2),'Entradas'!B12/H9,0) -> 0 | Z9: =IF(AND(F9>0,'Entradas'!E13="COLD",'Entradas'!H13<=(K9+L9)/2,'Entradas'!I13>=(K9+L9)/2),'Entradas'!B13/H9,0) -> 1 | AA9: =IF(AND(F9>0,'Entradas'!E14="COLD",'Entradas'!H14<=(K9+L9)/2,'Entradas'!I14>=(K9+L9)/2),'Entradas'!B14/H9,0) -> 0
A10: ='Compuestas'!H10 -> 480000 | B10: =SMALL($A$4:$A$19,7) -> 150000 | C10: =B11-B10 -> 30000 | D10: =(B10+B11)/2 -> 165000 | E10: =IF(C10<='Resumen'!$B$14,0,SUMPRODUCT(--('Compuestas'!$H$4:$H$10<=D10),--('Compuestas'!$H$5:$H$11>D10),'Compuestas'!$O$4:$O$10)) -> 4 | F10: =IF(C10<='Resumen'!$B$14,0,SUMPRODUCT(--('Compuestas'!$J$4:$J$10<=D10),--('Compuestas'!$J$5:$J$11>D10),'Compuestas'!$O$4:$O$10)) -> 3 | G10: =IF(E10>0,INDEX('Compuestas'!$D$4:$D$10,E10),0) -> 5000 | H10: =IF(F10>0,INDEX('Compuestas'!$E$4:$E$10,F10),0) -> 3000 | I10: =IF(E10>0,INDEX('Compuestas'!$B$4:$B$10,E10)+(B10-INDEX('Compuestas'!$H$4:$H$10,E10))/G10,0) -> 134 | J10: =IF(E10>0,INDEX('Compuestas'!$B$4:$B$10,E10)+(B11-INDEX('Compuestas'!$H$4:$H$10,E10))/G10,0) -> 140 | K10: =IF(F10>0,INDEX('Compuestas'!$B$4:$B$10,F10)+(B10-INDEX('Compuestas'!$J$4:$J$10,F10))/H10,0) -> 120 | L10: =IF(F10>0,INDEX('Compuestas'!$B$4:$B$10,F10)+(B11-INDEX('Compuestas'!$J$4:$J$10,F10))/H10,0) -> 130 | M10: =IF(AND(E10>0,F10>0),C10,0) -> 30000 | N10: =IF(AND(E10>0,F10=0),C10,0) -> 0 | O10: =IF(AND(E10=0,F10>0),C10,0) -> 0 | P10: =IF(M10>0,J10-L10,0) -> 10 | Q10: =IF(M10>0,I10-K10,0) -> 14 | R10: =IF(M10=0,0,IF(MIN(P10,Q10)<=0,0,IF(ABS(P10-Q10)<0.00000001,(P10+Q10)/2,(P10-Q10)/LN(P10/Q10)))) -> 11.888054 | S10: =IF(M10=0,0,IF('Entradas'!$B$5=0,"sin U",IF(R10=0,"infinita",M10/('Entradas'!$B$5*R10)))) -> sin U | T10: =IF(AND(E10>0,'Entradas'!E11="HOT",'Entradas'!H11<=(I10+J10)/2,'Entradas'!I11>=(I10+J10)/2),'Entradas'!B11/G10,0) -> 0.2 | U10: =IF(AND(E10>0,'Entradas'!E12="HOT",'Entradas'!H12<=(I10+J10)/2,'Entradas'!I12>=(I10+J10)/2),'Entradas'!B12/G10,0) -> 0.8 | V10: =IF(AND(E10>0,'Entradas'!E13="HOT",'Entradas'!H13<=(I10+J10)/2,'Entradas'!I13>=(I10+J10)/2),'Entradas'!B13/G10,0) -> 0 | W10: =IF(AND(E10>0,'Entradas'!E14="HOT",'Entradas'!H14<=(I10+J10)/2,'Entradas'!I14>=(I10+J10)/2),'Entradas'!B14/G10,0) -> 0 | X10: =IF(AND(F10>0,'Entradas'!E11="COLD",'Entradas'!H11<=(K10+L10)/2,'Entradas'!I11>=(K10+L10)/2),'Entradas'!B11/H10,0) -> 0 | Y10: =IF(AND(F10>0,'Entradas'!E12="COLD",'Entradas'!H12<=(K10+L10)/2,'Entradas'!I12>=(K10+L10)/2),'Entradas'!B12/H10,0) -> 0 | Z10: =IF(AND(F10>0,'Entradas'!E13="COLD",'Entradas'!H13<=(K10+L10)/2,'Entradas'!I13>=(K10+L10)/2),'Entradas'!B13/H10,0) -> 1 | AA10: =IF(AND(F10>0,'Entradas'!E14="COLD",'Entradas'!H14<=(K10+L10)/2,'Entradas'!I14>=(K10+L10)/2),'Entradas'!B14/H10,0) -> 0
A11: ='Compuestas'!H11 -> 530000 | B11: =SMALL($A$4:$A$19,8) -> 180000 | C11: =B12-B11 -> 50000 | D11: =(B11+B12)/2 -> 205000 | E11: =IF(C11<='Resumen'!$B$14,0,SUMPRODUCT(--('Compuestas'!$H$4:$H$10<=D11),--('Compuestas'!$H$5:$H$11>D11),'Compuestas'!$O$4:$O$10)) -> 4 | F11: =IF(C11<='Resumen'!$B$14,0,SUMPRODUCT(--('Compuestas'!$J$4:$J$10<=D11),--('Compuestas'!$J$5:$J$11>D11),'Compuestas'!$O$4:$O$10)) -> 4 | G11: =IF(E11>0,INDEX('Compuestas'!$D$4:$D$10,E11),0) -> 5000 | H11: =IF(F11>0,INDEX('Compuestas'!$E$4:$E$10,F11),0) -> 9000 | I11: =IF(E11>0,INDEX('Compuestas'!$B$4:$B$10,E11)+(B11-INDEX('Compuestas'!$H$4:$H$10,E11))/G11,0) -> 140 | J11: =IF(E11>0,INDEX('Compuestas'!$B$4:$B$10,E11)+(B12-INDEX('Compuestas'!$H$4:$H$10,E11))/G11,0) -> 150 | K11: =IF(F11>0,INDEX('Compuestas'!$B$4:$B$10,F11)+(B11-INDEX('Compuestas'!$J$4:$J$10,F11))/H11,0) -> 130 | L11: =IF(F11>0,INDEX('Compuestas'!$B$4:$B$10,F11)+(B12-INDEX('Compuestas'!$J$4:$J$10,F11))/H11,0) -> 135.55556 | M11: =IF(AND(E11>0,F11>0),C11,0) -> 50000 | N11: =IF(AND(E11>0,F11=0),C11,0) -> 0 | O11: =IF(AND(E11=0,F11>0),C11,0) -> 0 | P11: =IF(M11>0,J11-L11,0) -> 14.444444 | Q11: =IF(M11>0,I11-K11,0) -> 10 | R11: =IF(M11=0,0,IF(MIN(P11,Q11)<=0,0,IF(ABS(P11-Q11)<0.00000001,(P11+Q11)/2,(P11-Q11)/LN(P11/Q11)))) -> 12.086334 | S11: =IF(M11=0,0,IF('Entradas'!$B$5=0,"sin U",IF(R11=0,"infinita",M11/('Entradas'!$B$5*R11)))) -> sin U | T11: =IF(AND(E11>0,'Entradas'!E11="HOT",'Entradas'!H11<=(I11+J11)/2,'Entradas'!I11>=(I11+J11)/2),'Entradas'!B11/G11,0) -> 0.2 | U11: =IF(AND(E11>0,'Entradas'!E12="HOT",'Entradas'!H12<=(I11+J11)/2,'Entradas'!I12>=(I11+J11)/2),'Entradas'!B12/G11,0) -> 0.8 | V11: =IF(AND(E11>0,'Entradas'!E13="HOT",'Entradas'!H13<=(I11+J11)/2,'Entradas'!I13>=(I11+J11)/2),'Entradas'!B13/G11,0) -> 0 | W11: =IF(AND(E11>0,'Entradas'!E14="HOT",'Entradas'!H14<=(I11+J11)/2,'Entradas'!I14>=(I11+J11)/2),'Entradas'!B14/G11,0) -> 0 | X11: =IF(AND(F11>0,'Entradas'!E11="COLD",'Entradas'!H11<=(K11+L11)/2,'Entradas'!I11>=(K11+L11)/2),'Entradas'!B11/H11,0) -> 0 | Y11: =IF(AND(F11>0,'Entradas'!E12="COLD",'Entradas'!H12<=(K11+L11)/2,'Entradas'!I12>=(K11+L11)/2),'Entradas'!B12/H11,0) -> 0 | Z11: =IF(AND(F11>0,'Entradas'!E13="COLD",'Entradas'!H13<=(K11+L11)/2,'Entradas'!I13>=(K11+L11)/2),'Entradas'!B13/H11,0) -> 0.33333333 | AA11: =IF(AND(F11>0,'Entradas'!E14="COLD",'Entradas'!H14<=(K11+L11)/2,'Entradas'!I14>=(K11+L11)/2),'Entradas'!B14/H11,0) -> 0.66666667
A12: ='Compuestas'!J4 -> 60000 | B12: =SMALL($A$4:$A$19,9) -> 230000 | C12: =B13-B12 -> 130000 | D12: =(B12+B13)/2 -> 295000 | E12: =IF(C12<='Resumen'!$B$14,0,SUMPRODUCT(--('Compuestas'!$H$4:$H$10<=D12),--('Compuestas'!$H$5:$H$11>D12),'Compuestas'!$O$4:$O$10)) -> 5 | F12: =IF(C12<='Resumen'!$B$14,0,SUMPRODUCT(--('Compuestas'!$J$4:$J$10<=D12),--('Compuestas'!$J$5:$J$11>D12),'Compuestas'!$O$4:$O$10)) -> 4 | G12: =IF(E12>0,INDEX('Compuestas'!$D$4:$D$10,E12),0) -> 5000 | H12: =IF(F12>0,INDEX('Compuestas'!$E$4:$E$10,F12),0) -> 9000 | I12: =IF(E12>0,INDEX('Compuestas'!$B$4:$B$10,E12)+(B12-INDEX('Compuestas'!$H$4:$H$10,E12))/G12,0) -> 150 | J12: =IF(E12>0,INDEX('Compuestas'!$B$4:$B$10,E12)+(B13-INDEX('Compuestas'!$H$4:$H$10,E12))/G12,0) -> 176 | K12: =IF(F12>0,INDEX('Compuestas'!$B$4:$B$10,F12)+(B12-INDEX('Compuestas'!$J$4:$J$10,F12))/H12,0) -> 135.55556 | L12: =IF(F12>0,INDEX('Compuestas'!$B$4:$B$10,F12)+(B13-INDEX('Compuestas'!$J$4:$J$10,F12))/H12,0) -> 150 | M12: =IF(AND(E12>0,F12>0),C12,0) -> 130000 | N12: =IF(AND(E12>0,F12=0),C12,0) -> 0 | O12: =IF(AND(E12=0,F12>0),C12,0) -> 0 | P12: =IF(M12>0,J12-L12,0) -> 26 | Q12: =IF(M12>0,I12-K12,0) -> 14.444444 | R12: =IF(M12=0,0,IF(MIN(P12,Q12)<=0,0,IF(ABS(P12-Q12)<0.00000001,(P12+Q12)/2,(P12-Q12)/LN(P12/Q12)))) -> 19.659438 | S12: =IF(M12=0,0,IF('Entradas'!$B$5=0,"sin U",IF(R12=0,"infinita",M12/('Entradas'!$B$5*R12)))) -> sin U | T12: =IF(AND(E12>0,'Entradas'!E11="HOT",'Entradas'!H11<=(I12+J12)/2,'Entradas'!I11>=(I12+J12)/2),'Entradas'!B11/G12,0) -> 0.2 | U12: =IF(AND(E12>0,'Entradas'!E12="HOT",'Entradas'!H12<=(I12+J12)/2,'Entradas'!I12>=(I12+J12)/2),'Entradas'!B12/G12,0) -> 0.8 | V12: =IF(AND(E12>0,'Entradas'!E13="HOT",'Entradas'!H13<=(I12+J12)/2,'Entradas'!I13>=(I12+J12)/2),'Entradas'!B13/G12,0) -> 0 | W12: =IF(AND(E12>0,'Entradas'!E14="HOT",'Entradas'!H14<=(I12+J12)/2,'Entradas'!I14>=(I12+J12)/2),'Entradas'!B14/G12,0) -> 0 | X12: =IF(AND(F12>0,'Entradas'!E11="COLD",'Entradas'!H11<=(K12+L12)/2,'Entradas'!I11>=(K12+L12)/2),'Entradas'!B11/H12,0) -> 0 | Y12: =IF(AND(F12>0,'Entradas'!E12="COLD",'Entradas'!H12<=(K12+L12)/2,'Entradas'!I12>=(K12+L12)/2),'Entradas'!B12/H12,0) -> 0 | Z12: =IF(AND(F12>0,'Entradas'!E13="COLD",'Entradas'!H13<=(K12+L12)/2,'Entradas'!I13>=(K12+L12)/2),'Entradas'!B13/H12,0) -> 0.33333333 | AA12: =IF(AND(F12>0,'Entradas'!E14="COLD",'Entradas'!H14<=(K12+L12)/2,'Entradas'!I14>=(K12+L12)/2),'Entradas'!B14/H12,0) -> 0.66666667
A13: ='Compuestas'!J5 -> 90000 | B13: =SMALL($A$4:$A$19,10) -> 360000 | C13: =B14-B13 -> 70000 | D13: =(B13+B14)/2 -> 395000 | E13: =IF(C13<='Resumen'!$B$14,0,SUMPRODUCT(--('Compuestas'!$H$4:$H$10<=D13),--('Compuestas'!$H$5:$H$11>D13),'Compuestas'!$O$4:$O$10)) -> 5 | F13: =IF(C13<='Resumen'!$B$14,0,SUMPRODUCT(--('Compuestas'!$J$4:$J$10<=D13),--('Compuestas'!$J$5:$J$11>D13),'Compuestas'!$O$4:$O$10)) -> 5 | G13: =IF(E13>0,INDEX('Compuestas'!$D$4:$D$10,E13),0) -> 5000 | H13: =IF(F13>0,INDEX('Compuestas'!$E$4:$E$10,F13),0) -> 6000 | I13: =IF(E13>0,INDEX('Compuestas'!$B$4:$B$10,E13)+(B13-INDEX('Compuestas'!$H$4:$H$10,E13))/G13,0) -> 176 | J13: =IF(E13>0,INDEX('Compuestas'!$B$4:$B$10,E13)+(B14-INDEX('Compuestas'!$H$4:$H$10,E13))/G13,0) -> 190 | K13: =IF(F13>0,INDEX('Compuestas'!$B$4:$B$10,F13)+(B13-INDEX('Compuestas'!$J$4:$J$10,F13))/H13,0) -> 150 | L13: =IF(F13>0,INDEX('Compuestas'!$B$4:$B$10,F13)+(B14-INDEX('Compuestas'!$J$4:$J$10,F13))/H13,0) -> 161.66667 | M13: =IF(AND(E13>0,F13>0),C13,0) -> 70000 | N13: =IF(AND(E13>0,F13=0),C13,0) -> 0 | O13: =IF(AND(E13=0,F13>0),C13,0) -> 0 | P13: =IF(M13>0,J13-L13,0) -> 28.333333 | Q13: =IF(M13>0,I13-K13,0) -> 26 | R13: =IF(M13=0,0,IF(MIN(P13,Q13)<=0,0,IF(ABS(P13-Q13)<0.00000001,(P13+Q13)/2,(P13-Q13)/LN(P13/Q13)))) -> 27.149958 | S13: =IF(M13=0,0,IF('Entradas'!$B$5=0,"sin U",IF(R13=0,"infinita",M13/('Entradas'!$B$5*R13)))) -> sin U | T13: =IF(AND(E13>0,'Entradas'!E11="HOT",'Entradas'!H11<=(I13+J13)/2,'Entradas'!I11>=(I13+J13)/2),'Entradas'!B11/G13,0) -> 0.2 | U13: =IF(AND(E13>0,'Entradas'!E12="HOT",'Entradas'!H12<=(I13+J13)/2,'Entradas'!I12>=(I13+J13)/2),'Entradas'!B12/G13,0) -> 0.8 | V13: =IF(AND(E13>0,'Entradas'!E13="HOT",'Entradas'!H13<=(I13+J13)/2,'Entradas'!I13>=(I13+J13)/2),'Entradas'!B13/G13,0) -> 0 | W13: =IF(AND(E13>0,'Entradas'!E14="HOT",'Entradas'!H14<=(I13+J13)/2,'Entradas'!I14>=(I13+J13)/2),'Entradas'!B14/G13,0) -> 0 | X13: =IF(AND(F13>0,'Entradas'!E11="COLD",'Entradas'!H11<=(K13+L13)/2,'Entradas'!I11>=(K13+L13)/2),'Entradas'!B11/H13,0) -> 0 | Y13: =IF(AND(F13>0,'Entradas'!E12="COLD",'Entradas'!H12<=(K13+L13)/2,'Entradas'!I12>=(K13+L13)/2),'Entradas'!B12/H13,0) -> 0 | Z13: =IF(AND(F13>0,'Entradas'!E13="COLD",'Entradas'!H13<=(K13+L13)/2,'Entradas'!I13>=(K13+L13)/2),'Entradas'!B13/H13,0) -> 0 | AA13: =IF(AND(F13>0,'Entradas'!E14="COLD",'Entradas'!H14<=(K13+L13)/2,'Entradas'!I14>=(K13+L13)/2),'Entradas'!B14/H13,0) -> 1
A14: ='Compuestas'!J6 -> 150000 | B14: =SMALL($A$4:$A$19,11) -> 430000 | C14: =B15-B14 -> 50000 | D14: =(B14+B15)/2 -> 455000 | E14: =IF(C14<='Resumen'!$B$14,0,SUMPRODUCT(--('Compuestas'!$H$4:$H$10<=D14),--('Compuestas'!$H$5:$H$11>D14),'Compuestas'!$O$4:$O$10)) -> 6 | F14: =IF(C14<='Resumen'!$B$14,0,SUMPRODUCT(--('Compuestas'!$J$4:$J$10<=D14),--('Compuestas'!$J$5:$J$11>D14),'Compuestas'!$O$4:$O$10)) -> 5 | G14: =IF(E14>0,INDEX('Compuestas'!$D$4:$D$10,E14),0) -> 5000 | H14: =IF(F14>0,INDEX('Compuestas'!$E$4:$E$10,F14),0) -> 6000 | I14: =IF(E14>0,INDEX('Compuestas'!$B$4:$B$10,E14)+(B14-INDEX('Compuestas'!$H$4:$H$10,E14))/G14,0) -> 190 | J14: =IF(E14>0,INDEX('Compuestas'!$B$4:$B$10,E14)+(B15-INDEX('Compuestas'!$H$4:$H$10,E14))/G14,0) -> 200 | K14: =IF(F14>0,INDEX('Compuestas'!$B$4:$B$10,F14)+(B14-INDEX('Compuestas'!$J$4:$J$10,F14))/H14,0) -> 161.66667 | L14: =IF(F14>0,INDEX('Compuestas'!$B$4:$B$10,F14)+(B15-INDEX('Compuestas'!$J$4:$J$10,F14))/H14,0) -> 170 | M14: =IF(AND(E14>0,F14>0),C14,0) -> 50000 | N14: =IF(AND(E14>0,F14=0),C14,0) -> 0 | O14: =IF(AND(E14=0,F14>0),C14,0) -> 0 | P14: =IF(M14>0,J14-L14,0) -> 30 | Q14: =IF(M14>0,I14-K14,0) -> 28.333333 | R14: =IF(M14=0,0,IF(MIN(P14,Q14)<=0,0,IF(ABS(P14-Q14)<0.00000001,(P14+Q14)/2,(P14-Q14)/LN(P14/Q14)))) -> 29.158728 | S14: =IF(M14=0,0,IF('Entradas'!$B$5=0,"sin U",IF(R14=0,"infinita",M14/('Entradas'!$B$5*R14)))) -> sin U | T14: =IF(AND(E14>0,'Entradas'!E11="HOT",'Entradas'!H11<=(I14+J14)/2,'Entradas'!I11>=(I14+J14)/2),'Entradas'!B11/G14,0) -> 0.2 | U14: =IF(AND(E14>0,'Entradas'!E12="HOT",'Entradas'!H12<=(I14+J14)/2,'Entradas'!I12>=(I14+J14)/2),'Entradas'!B12/G14,0) -> 0.8 | V14: =IF(AND(E14>0,'Entradas'!E13="HOT",'Entradas'!H13<=(I14+J14)/2,'Entradas'!I13>=(I14+J14)/2),'Entradas'!B13/G14,0) -> 0 | W14: =IF(AND(E14>0,'Entradas'!E14="HOT",'Entradas'!H14<=(I14+J14)/2,'Entradas'!I14>=(I14+J14)/2),'Entradas'!B14/G14,0) -> 0 | X14: =IF(AND(F14>0,'Entradas'!E11="COLD",'Entradas'!H11<=(K14+L14)/2,'Entradas'!I11>=(K14+L14)/2),'Entradas'!B11/H14,0) -> 0 | Y14: =IF(AND(F14>0,'Entradas'!E12="COLD",'Entradas'!H12<=(K14+L14)/2,'Entradas'!I12>=(K14+L14)/2),'Entradas'!B12/H14,0) -> 0 | Z14: =IF(AND(F14>0,'Entradas'!E13="COLD",'Entradas'!H13<=(K14+L14)/2,'Entradas'!I13>=(K14+L14)/2),'Entradas'!B13/H14,0) -> 0 | AA14: =IF(AND(F14>0,'Entradas'!E14="COLD",'Entradas'!H14<=(K14+L14)/2,'Entradas'!I14>=(K14+L14)/2),'Entradas'!B14/H14,0) -> 1
A15: ='Compuestas'!J7 -> 180000 | B15: =SMALL($A$4:$A$19,12) -> 480000 | C15: =B16-B15 -> 50000 | D15: =(B15+B16)/2 -> 505000 | E15: =IF(C15<='Resumen'!$B$14,0,SUMPRODUCT(--('Compuestas'!$H$4:$H$10<=D15),--('Compuestas'!$H$5:$H$11>D15),'Compuestas'!$O$4:$O$10)) -> 7 | F15: =IF(C15<='Resumen'!$B$14,0,SUMPRODUCT(--('Compuestas'!$J$4:$J$10<=D15),--('Compuestas'!$J$5:$J$11>D15),'Compuestas'!$O$4:$O$10)) -> 5 | G15: =IF(E15>0,INDEX('Compuestas'!$D$4:$D$10,E15),0) -> 1000 | H15: =IF(F15>0,INDEX('Compuestas'!$E$4:$E$10,F15),0) -> 6000 | I15: =IF(E15>0,INDEX('Compuestas'!$B$4:$B$10,E15)+(B15-INDEX('Compuestas'!$H$4:$H$10,E15))/G15,0) -> 200 | J15: =IF(E15>0,INDEX('Compuestas'!$B$4:$B$10,E15)+(B16-INDEX('Compuestas'!$H$4:$H$10,E15))/G15,0) -> 250 | K15: =IF(F15>0,INDEX('Compuestas'!$B$4:$B$10,F15)+(B15-INDEX('Compuestas'!$J$4:$J$10,F15))/H15,0) -> 170 | L15: =IF(F15>0,INDEX('Compuestas'!$B$4:$B$10,F15)+(B16-INDEX('Compuestas'!$J$4:$J$10,F15))/H15,0) -> 178.33333 | M15: =IF(AND(E15>0,F15>0),C15,0) -> 50000 | N15: =IF(AND(E15>0,F15=0),C15,0) -> 0 | O15: =IF(AND(E15=0,F15>0),C15,0) -> 0 | P15: =IF(M15>0,J15-L15,0) -> 71.666667 | Q15: =IF(M15>0,I15-K15,0) -> 30 | R15: =IF(M15=0,0,IF(MIN(P15,Q15)<=0,0,IF(ABS(P15-Q15)<0.00000001,(P15+Q15)/2,(P15-Q15)/LN(P15/Q15)))) -> 47.847163 | S15: =IF(M15=0,0,IF('Entradas'!$B$5=0,"sin U",IF(R15=0,"infinita",M15/('Entradas'!$B$5*R15)))) -> sin U | T15: =IF(AND(E15>0,'Entradas'!E11="HOT",'Entradas'!H11<=(I15+J15)/2,'Entradas'!I11>=(I15+J15)/2),'Entradas'!B11/G15,0) -> 1 | U15: =IF(AND(E15>0,'Entradas'!E12="HOT",'Entradas'!H12<=(I15+J15)/2,'Entradas'!I12>=(I15+J15)/2),'Entradas'!B12/G15,0) -> 0 | V15: =IF(AND(E15>0,'Entradas'!E13="HOT",'Entradas'!H13<=(I15+J15)/2,'Entradas'!I13>=(I15+J15)/2),'Entradas'!B13/G15,0) -> 0 | W15: =IF(AND(E15>0,'Entradas'!E14="HOT",'Entradas'!H14<=(I15+J15)/2,'Entradas'!I14>=(I15+J15)/2),'Entradas'!B14/G15,0) -> 0 | X15: =IF(AND(F15>0,'Entradas'!E11="COLD",'Entradas'!H11<=(K15+L15)/2,'Entradas'!I11>=(K15+L15)/2),'Entradas'!B11/H15,0) -> 0 | Y15: =IF(AND(F15>0,'Entradas'!E12="COLD",'Entradas'!H12<=(K15+L15)/2,'Entradas'!I12>=(K15+L15)/2),'Entradas'!B12/H15,0) -> 0 | Z15: =IF(AND(F15>0,'Entradas'!E13="COLD",'Entradas'!H13<=(K15+L15)/2,'Entradas'!I13>=(K15+L15)/2),'Entradas'!B13/H15,0) -> 0 | AA15: =IF(AND(F15>0,'Entradas'!E14="COLD",'Entradas'!H14<=(K15+L15)/2,'Entradas'!I14>=(K15+L15)/2),'Entradas'!B14/H15,0) -> 1
A16: ='Compuestas'!J8 -> 360000 | B16: =SMALL($A$4:$A$19,13) -> 530000 | C16: =B17-B16 -> 70000 | D16: =(B16+B17)/2 -> 565000 | E16: =IF(C16<='Resumen'!$B$14,0,SUMPRODUCT(--('Compuestas'!$H$4:$H$10<=D16),--('Compuestas'!$H$5:$H$11>D16),'Compuestas'!$O$4:$O$10)) -> 0 | F16: =IF(C16<='Resumen'!$B$14,0,SUMPRODUCT(--('Compuestas'!$J$4:$J$10<=D16),--('Compuestas'!$J$5:$J$11>D16),'Compuestas'!$O$4:$O$10)) -> 5 | G16: =IF(E16>0,INDEX('Compuestas'!$D$4:$D$10,E16),0) -> 0 | H16: =IF(F16>0,INDEX('Compuestas'!$E$4:$E$10,F16),0) -> 6000 | I16: =IF(E16>0,INDEX('Compuestas'!$B$4:$B$10,E16)+(B16-INDEX('Compuestas'!$H$4:$H$10,E16))/G16,0) -> 0 | J16: =IF(E16>0,INDEX('Compuestas'!$B$4:$B$10,E16)+(B17-INDEX('Compuestas'!$H$4:$H$10,E16))/G16,0) -> 0 | K16: =IF(F16>0,INDEX('Compuestas'!$B$4:$B$10,F16)+(B16-INDEX('Compuestas'!$J$4:$J$10,F16))/H16,0) -> 178.33333 | L16: =IF(F16>0,INDEX('Compuestas'!$B$4:$B$10,F16)+(B17-INDEX('Compuestas'!$J$4:$J$10,F16))/H16,0) -> 190 | M16: =IF(AND(E16>0,F16>0),C16,0) -> 0 | N16: =IF(AND(E16>0,F16=0),C16,0) -> 0 | O16: =IF(AND(E16=0,F16>0),C16,0) -> 70000 | P16: =IF(M16>0,J16-L16,0) -> 0 | Q16: =IF(M16>0,I16-K16,0) -> 0 | R16: =IF(M16=0,0,IF(MIN(P16,Q16)<=0,0,IF(ABS(P16-Q16)<0.00000001,(P16+Q16)/2,(P16-Q16)/LN(P16/Q16)))) -> 0 | S16: =IF(M16=0,0,IF('Entradas'!$B$5=0,"sin U",IF(R16=0,"infinita",M16/('Entradas'!$B$5*R16)))) -> 0 | T16: =IF(AND(E16>0,'Entradas'!E11="HOT",'Entradas'!H11<=(I16+J16)/2,'Entradas'!I11>=(I16+J16)/2),'Entradas'!B11/G16,0) -> 0 | U16: =IF(AND(E16>0,'Entradas'!E12="HOT",'Entradas'!H12<=(I16+J16)/2,'Entradas'!I12>=(I16+J16)/2),'Entradas'!B12/G16,0) -> 0 | V16: =IF(AND(E16>0,'Entradas'!E13="HOT",'Entradas'!H13<=(I16+J16)/2,'Entradas'!I13>=(I16+J16)/2),'Entradas'!B13/G16,0) -> 0 | W16: =IF(AND(E16>0,'Entradas'!E14="HOT",'Entradas'!H14<=(I16+J16)/2,'Entradas'!I14>=(I16+J16)/2),'Entradas'!B14/G16,0) -> 0 | X16: =IF(AND(F16>0,'Entradas'!E11="COLD",'Entradas'!H11<=(K16+L16)/2,'Entradas'!I11>=(K16+L16)/2),'Entradas'!B11/H16,0) -> 0 | Y16: =IF(AND(F16>0,'Entradas'!E12="COLD",'Entradas'!H12<=(K16+L16)/2,'Entradas'!I12>=(K16+L16)/2),'Entradas'!B12/H16,0) -> 0 | Z16: =IF(AND(F16>0,'Entradas'!E13="COLD",'Entradas'!H13<=(K16+L16)/2,'Entradas'!I13>=(K16+L16)/2),'Entradas'!B13/H16,0) -> 0 | AA16: =IF(AND(F16>0,'Entradas'!E14="COLD",'Entradas'!H14<=(K16+L16)/2,'Entradas'!I14>=(K16+L16)/2),'Entradas'!B14/H16,0) -> 1
A17: ='Compuestas'!J9 -> 600000 | B17: =SMALL($A$4:$A$19,14) -> 600000 | C17: =B18-B17 -> 0 | D17: =(B17+B18)/2 -> 600000 | E17: =IF(C17<='Resumen'!$B$14,0,SUMPRODUCT(--('Compuestas'!$H$4:$H$10<=D17),--('Compuestas'!$H$5:$H$11>D17),'Compuestas'!$O$4:$O$10)) -> 0 | F17: =IF(C17<='Resumen'!$B$14,0,SUMPRODUCT(--('Compuestas'!$J$4:$J$10<=D17),--('Compuestas'!$J$5:$J$11>D17),'Compuestas'!$O$4:$O$10)) -> 0 | G17: =IF(E17>0,INDEX('Compuestas'!$D$4:$D$10,E17),0) -> 0 | H17: =IF(F17>0,INDEX('Compuestas'!$E$4:$E$10,F17),0) -> 0 | I17: =IF(E17>0,INDEX('Compuestas'!$B$4:$B$10,E17)+(B17-INDEX('Compuestas'!$H$4:$H$10,E17))/G17,0) -> 0 | J17: =IF(E17>0,INDEX('Compuestas'!$B$4:$B$10,E17)+(B18-INDEX('Compuestas'!$H$4:$H$10,E17))/G17,0) -> 0 | K17: =IF(F17>0,INDEX('Compuestas'!$B$4:$B$10,F17)+(B17-INDEX('Compuestas'!$J$4:$J$10,F17))/H17,0) -> 0 | L17: =IF(F17>0,INDEX('Compuestas'!$B$4:$B$10,F17)+(B18-INDEX('Compuestas'!$J$4:$J$10,F17))/H17,0) -> 0 | M17: =IF(AND(E17>0,F17>0),C17,0) -> 0 | N17: =IF(AND(E17>0,F17=0),C17,0) -> 0 | O17: =IF(AND(E17=0,F17>0),C17,0) -> 0 | P17: =IF(M17>0,J17-L17,0) -> 0 | Q17: =IF(M17>0,I17-K17,0) -> 0 | R17: =IF(M17=0,0,IF(MIN(P17,Q17)<=0,0,IF(ABS(P17-Q17)<0.00000001,(P17+Q17)/2,(P17-Q17)/LN(P17/Q17)))) -> 0 | S17: =IF(M17=0,0,IF('Entradas'!$B$5=0,"sin U",IF(R17=0,"infinita",M17/('Entradas'!$B$5*R17)))) -> 0 | T17: =IF(AND(E17>0,'Entradas'!E11="HOT",'Entradas'!H11<=(I17+J17)/2,'Entradas'!I11>=(I17+J17)/2),'Entradas'!B11/G17,0) -> 0 | U17: =IF(AND(E17>0,'Entradas'!E12="HOT",'Entradas'!H12<=(I17+J17)/2,'Entradas'!I12>=(I17+J17)/2),'Entradas'!B12/G17,0) -> 0 | V17: =IF(AND(E17>0,'Entradas'!E13="HOT",'Entradas'!H13<=(I17+J17)/2,'Entradas'!I13>=(I17+J17)/2),'Entradas'!B13/G17,0) -> 0 | W17: =IF(AND(E17>0,'Entradas'!E14="HOT",'Entradas'!H14<=(I17+J17)/2,'Entradas'!I14>=(I17+J17)/2),'Entradas'!B14/G17,0) -> 0 | X17: =IF(AND(F17>0,'Entradas'!E11="COLD",'Entradas'!H11<=(K17+L17)/2,'Entradas'!I11>=(K17+L17)/2),'Entradas'!B11/H17,0) -> 0 | Y17: =IF(AND(F17>0,'Entradas'!E12="COLD",'Entradas'!H12<=(K17+L17)/2,'Entradas'!I12>=(K17+L17)/2),'Entradas'!B12/H17,0) -> 0 | Z17: =IF(AND(F17>0,'Entradas'!E13="COLD",'Entradas'!H13<=(K17+L17)/2,'Entradas'!I13>=(K17+L17)/2),'Entradas'!B13/H17,0) -> 0 | AA17: =IF(AND(F17>0,'Entradas'!E14="COLD",'Entradas'!H14<=(K17+L17)/2,'Entradas'!I14>=(K17+L17)/2),'Entradas'!B14/H17,0) -> 0
A18: ='Compuestas'!J10 -> 600000 | B18: =SMALL($A$4:$A$19,15) -> 600000 | C18: =B19-B18 -> 0 | D18: =(B18+B19)/2 -> 600000 | E18: =IF(C18<='Resumen'!$B$14,0,SUMPRODUCT(--('Compuestas'!$H$4:$H$10<=D18),--('Compuestas'!$H$5:$H$11>D18),'Compuestas'!$O$4:$O$10)) -> 0 | F18: =IF(C18<='Resumen'!$B$14,0,SUMPRODUCT(--('Compuestas'!$J$4:$J$10<=D18),--('Compuestas'!$J$5:$J$11>D18),'Compuestas'!$O$4:$O$10)) -> 0 | G18: =IF(E18>0,INDEX('Compuestas'!$D$4:$D$10,E18),0) -> 0 | H18: =IF(F18>0,INDEX('Compuestas'!$E$4:$E$10,F18),0) -> 0 | I18: =IF(E18>0,INDEX('Compuestas'!$B$4:$B$10,E18)+(B18-INDEX('Compuestas'!$H$4:$H$10,E18))/G18,0) -> 0 | J18: =IF(E18>0,INDEX('Compuestas'!$B$4:$B$10,E18)+(B19-INDEX('Compuestas'!$H$4:$H$10,E18))/G18,0) -> 0 | K18: =IF(F18>0,INDEX('Compuestas'!$B$4:$B$10,F18)+(B18-INDEX('Compuestas'!$J$4:$J$10,F18))/H18,0) -> 0 | L18: =IF(F18>0,INDEX('Compuestas'!$B$4:$B$10,F18)+(B19-INDEX('Compuestas'!$J$4:$J$10,F18))/H18,0) -> 0 | M18: =IF(AND(E18>0,F18>0),C18,0) -> 0 | N18: =IF(AND(E18>0,F18=0),C18,0) -> 0 | O18: =IF(AND(E18=0,F18>0),C18,0) -> 0 | P18: =IF(M18>0,J18-L18,0) -> 0 | Q18: =IF(M18>0,I18-K18,0) -> 0 | R18: =IF(M18=0,0,IF(MIN(P18,Q18)<=0,0,IF(ABS(P18-Q18)<0.00000001,(P18+Q18)/2,(P18-Q18)/LN(P18/Q18)))) -> 0 | S18: =IF(M18=0,0,IF('Entradas'!$B$5=0,"sin U",IF(R18=0,"infinita",M18/('Entradas'!$B$5*R18)))) -> 0 | T18: =IF(AND(E18>0,'Entradas'!E11="HOT",'Entradas'!H11<=(I18+J18)/2,'Entradas'!I11>=(I18+J18)/2),'Entradas'!B11/G18,0) -> 0 | U18: =IF(AND(E18>0,'Entradas'!E12="HOT",'Entradas'!H12<=(I18+J18)/2,'Entradas'!I12>=(I18+J18)/2),'Entradas'!B12/G18,0) -> 0 | V18: =IF(AND(E18>0,'Entradas'!E13="HOT",'Entradas'!H13<=(I18+J18)/2,'Entradas'!I13>=(I18+J18)/2),'Entradas'!B13/G18,0) -> 0 | W18: =IF(AND(E18>0,'Entradas'!E14="HOT",'Entradas'!H14<=(I18+J18)/2,'Entradas'!I14>=(I18+J18)/2),'Entradas'!B14/G18,0) -> 0 | X18: =IF(AND(F18>0,'Entradas'!E11="COLD",'Entradas'!H11<=(K18+L18)/2,'Entradas'!I11>=(K18+L18)/2),'Entradas'!B11/H18,0) -> 0 | Y18: =IF(AND(F18>0,'Entradas'!E12="COLD",'Entradas'!H12<=(K18+L18)/2,'Entradas'!I12>=(K18+L18)/2),'Entradas'!B12/H18,0) -> 0 | Z18: =IF(AND(F18>0,'Entradas'!E13="COLD",'Entradas'!H13<=(K18+L18)/2,'Entradas'!I13>=(K18+L18)/2),'Entradas'!B13/H18,0) -> 0 | AA18: =IF(AND(F18>0,'Entradas'!E14="COLD",'Entradas'!H14<=(K18+L18)/2,'Entradas'!I14>=(K18+L18)/2),'Entradas'!B14/H18,0) -> 0
A19: ='Compuestas'!J11 -> 600000 | B19: =SMALL($A$4:$A$19,16) -> 600000

Sheet Sensibilidad
A1: Efecto de ΔT mínimo
A2: Escenarios recalculados mediante cascadas independientes. Cambia los ΔT azules o las corrientes de Entradas.
A3: ΔT mínimo (K) | B3: QH mínimo | C3: QC mínimo | D3: Q recuperada
A4: 0 | B4: =MAX(0,-MIN(H18:H25)) -> 20000 | C4: =H25+B4 -> 10000 | D4: ='Resumen'!$B$5-C4 -> 520000
A5: 5 | B5: =MAX(0,-MIN(H30:H37)) -> 45000 | C5: =H37+B5 -> 35000 | D5: ='Resumen'!$B$5-C5 -> 495000
A6: 10 | B6: =MAX(0,-MIN(H42:H49)) -> 70000 | C6: =H49+B6 -> 60000 | D6: ='Resumen'!$B$5-C6 -> 470000
A7: 15 | B7: =MAX(0,-MIN(H54:H61)) -> 95000 | C7: =H61+B7 -> 85000 | D7: ='Resumen'!$B$5-C7 -> 445000
A8: 20 | B8: =MAX(0,-MIN(H66:H73)) -> 120000 | C8: =H73+B8 -> 110000 | D8: ='Resumen'!$B$5-C8 -> 420000
A9: 25 | B9: =MAX(0,-MIN(H78:H85)) -> 145000 | C9: =H85+B9 -> 135000 | D9: ='Resumen'!$B$5-C9 -> 395000
A10: 30 | B10: =MAX(0,-MIN(H90:H97)) -> 170000 | C10: =H97+B10 -> 160000 | D10: ='Resumen'!$B$5-C10 -> 370000
A11: 35 | B11: =MAX(0,-MIN(H102:H109)) -> 195000 | C11: =H109+B11 -> 185000 | D11: ='Resumen'!$B$5-C11 -> 345000
A12: 40 | B12: =MAX(0,-MIN(H114:H121)) -> 220000 | C12: =H121+B12 -> 210000 | D12: ='Resumen'!$B$5-C12 -> 320000
A16: Cascada del escenario 1 · ΔT en A4
A17: T* sin ordenar | B17: T* ordenada | C17: ΔT intervalo | D17: CP hot | E17: CP cold | F17: CP neto | G17: ΔH | H17: Residual bruto
A18: ='Entradas'!H11+IF('Entradas'!E11="HOT",-$A$4/2,$A$4/2) -> 120 | B18: =LARGE($A$18:$A$25,1) -> 250 | C18: =B18-B19 -> 50 | D18: =SUMPRODUCT(--('Entradas'!$E$11:$E$14="HOT"),--('Entradas'!$H$11:$H$14-$A$4/2<=(B18+B19)/2),--('Entradas'!$I$11:$I$14-$A$4/2>=(B18+B19)/2),'Entradas'!$B$11:$B$14) -> 1000 | E18: =SUMPRODUCT(--('Entradas'!$E$11:$E$14="COLD"),--('Entradas'!$H$11:$H$14+$A$4/2<=(B18+B19)/2),--('Entradas'!$I$11:$I$14+$A$4/2>=(B18+B19)/2),'Entradas'!$B$11:$B$14) -> 0 | F18: =D18-E18 -> 1000 | G18: =C18*F18 -> 50000 | H18: =0 -> 0
A19: ='Entradas'!I11+IF('Entradas'!E11="HOT",-$A$4/2,$A$4/2) -> 250 | B19: =LARGE($A$18:$A$25,2) -> 200 | C19: =B19-B20 -> 10 | D19: =SUMPRODUCT(--('Entradas'!$E$11:$E$14="HOT"),--('Entradas'!$H$11:$H$14-$A$4/2<=(B19+B20)/2),--('Entradas'!$I$11:$I$14-$A$4/2>=(B19+B20)/2),'Entradas'!$B$11:$B$14) -> 5000 | E19: =SUMPRODUCT(--('Entradas'!$E$11:$E$14="COLD"),--('Entradas'!$H$11:$H$14+$A$4/2<=(B19+B20)/2),--('Entradas'!$I$11:$I$14+$A$4/2>=(B19+B20)/2),'Entradas'!$B$11:$B$14) -> 0 | F19: =D19-E19 -> 5000 | G19: =C19*F19 -> 50000 | H19: =H18+G18 -> 50000
A20: ='Entradas'!H12+IF('Entradas'!E12="HOT",-$A$4/2,$A$4/2) -> 100 | B20: =LARGE($A$18:$A$25,3) -> 190 | C20: =B20-B21 -> 40 | D20: =SUMPRODUCT(--('Entradas'!$E$11:$E$14="HOT"),--('Entradas'!$H$11:$H$14-$A$4/2<=(B20+B21)/2),--('Entradas'!$I$11:$I$14-$A$4/2>=(B20+B21)/2),'Entradas'!$B$11:$B$14) -> 5000 | E20: =SUMPRODUCT(--('Entradas'!$E$11:$E$14="COLD"),--('Entradas'!$H$11:$H$14+$A$4/2<=(B20+B21)/2),--('Entradas'!$I$11:$I$14+$A$4/2>=(B20+B21)/2),'Entradas'!$B$11:$B$14) -> 6000 | F20: =D20-E20 -> -1000 | G20: =C20*F20 -> -40000 | H20: =H19+G19 -> 100000
A21: ='Entradas'!I12+IF('Entradas'!E12="HOT",-$A$4/2,$A$4/2) -> 200 | B21: =LARGE($A$18:$A$25,4) -> 150 | C21: =B21-B22 -> 20 | D21: =SUMPRODUCT(--('Entradas'!$E$11:$E$14="HOT"),--('Entradas'!$H$11:$H$14-$A$4/2<=(B21+B22)/2),--('Entradas'!$I$11:$I$14-$A$4/2>=(B21+B22)/2),'Entradas'!$B$11:$B$14) -> 5000 | E21: =SUMPRODUCT(--('Entradas'!$E$11:$E$14="COLD"),--('Entradas'!$H$11:$H$14+$A$4/2<=(B21+B22)/2),--('Entradas'!$I$11:$I$14+$A$4/2>=(B21+B22)/2),'Entradas'!$B$11:$B$14) -> 9000 | F21: =D21-E21 -> -4000 | G21: =C21*F21 -> -80000 | H21: =H20+G20 -> 60000
A22: ='Entradas'!H13+IF('Entradas'!E13="HOT",-$A$4/2,$A$4/2) -> 90 | B22: =LARGE($A$18:$A$25,5) -> 130 | C22: =B22-B23 -> 10 | D22: =SUMPRODUCT(--('Entradas'!$E$11:$E$14="HOT"),--('Entradas'!$H$11:$H$14-$A$4/2<=(B22+B23)/2),--('Entradas'!$I$11:$I$14-$A$4/2>=(B22+B23)/2),'Entradas'!$B$11:$B$14) -> 5000 | E22: =SUMPRODUCT(--('Entradas'!$E$11:$E$14="COLD"),--('Entradas'!$H$11:$H$14+$A$4/2<=(B22+B23)/2),--('Entradas'!$I$11:$I$14+$A$4/2>=(B22+B23)/2),'Entradas'!$B$11:$B$14) -> 3000 | F22: =D22-E22 -> 2000 | G22: =C22*F22 -> 20000 | H22: =H21+G21 -> -20000
A23: ='Entradas'!I13+IF('Entradas'!E13="HOT",-$A$4/2,$A$4/2) -> 150 | B23: =LARGE($A$18:$A$25,6) -> 120 | C23: =B23-B24 -> 20 | D23: =SUMPRODUCT(--('Entradas'!$E$11:$E$14="HOT"),--('Entradas'!$H$11:$H$14-$A$4/2<=(B23+B24)/2),--('Entradas'!$I$11:$I$14-$A$4/2>=(B23+B24)/2),'Entradas'!$B$11:$B$14) -> 4000 | E23: =SUMPRODUCT(--('Entradas'!$E$11:$E$14="COLD"),--('Entradas'!$H$11:$H$14+$A$4/2<=(B23+B24)/2),--('Entradas'!$I$11:$I$14+$A$4/2>=(B23+B24)/2),'Entradas'!$B$11:$B$14) -> 3000 | F23: =D23-E23 -> 1000 | G23: =C23*F23 -> 20000 | H23: =H22+G22 -> 0
A24: ='Entradas'!H14+IF('Entradas'!E14="HOT",-$A$4/2,$A$4/2) -> 130 | B24: =LARGE($A$18:$A$25,7) -> 100 | C24: =B24-B25 -> 10 | D24: =SUMPRODUCT(--('Entradas'!$E$11:$E$14="HOT"),--('Entradas'!$H$11:$H$14-$A$4/2<=(B24+B25)/2),--('Entradas'!$I$11:$I$14-$A$4/2>=(B24+B25)/2),'Entradas'!$B$11:$B$14) -> 0 | E24: =SUMPRODUCT(--('Entradas'!$E$11:$E$14="COLD"),--('Entradas'!$H$11:$H$14+$A$4/2<=(B24+B25)/2),--('Entradas'!$I$11:$I$14+$A$4/2>=(B24+B25)/2),'Entradas'!$B$11:$B$14) -> 3000 | F24: =D24-E24 -> -3000 | G24: =C24*F24 -> -30000 | H24: =H23+G23 -> 20000
A25: ='Entradas'!I14+IF('Entradas'!E14="HOT",-$A$4/2,$A$4/2) -> 190 | B25: =LARGE($A$18:$A$25,8) -> 90 | H25: =H24+G24 -> -10000
A28: Cascada del escenario 2 · ΔT en A5
A29: T* sin ordenar | B29: T* ordenada | C29: ΔT intervalo | D29: CP hot | E29: CP cold | F29: CP neto | G29: ΔH | H29: Residual bruto
A30: ='Entradas'!H11+IF('Entradas'!E11="HOT",-$A$5/2,$A$5/2) -> 117.5 | B30: =LARGE($A$30:$A$37,1) -> 247.5 | C30: =B30-B31 -> 50 | D30: =SUMPRODUCT(--('Entradas'!$E$11:$E$14="HOT"),--('Entradas'!$H$11:$H$14-$A$5/2<=(B30+B31)/2),--('Entradas'!$I$11:$I$14-$A$5/2>=(B30+B31)/2),'Entradas'!$B$11:$B$14) -> 1000 | E30: =SUMPRODUCT(--('Entradas'!$E$11:$E$14="COLD"),--('Entradas'!$H$11:$H$14+$A$5/2<=(B30+B31)/2),--('Entradas'!$I$11:$I$14+$A$5/2>=(B30+B31)/2),'Entradas'!$B$11:$B$14) -> 0 | F30: =D30-E30 -> 1000 | G30: =C30*F30 -> 50000 | H30: =0 -> 0
A31: ='Entradas'!I11+IF('Entradas'!E11="HOT",-$A$5/2,$A$5/2) -> 247.5 | B31: =LARGE($A$30:$A$37,2) -> 197.5 | C31: =B31-B32 -> 5 | D31: =SUMPRODUCT(--('Entradas'!$E$11:$E$14="HOT"),--('Entradas'!$H$11:$H$14-$A$5/2<=(B31+B32)/2),--('Entradas'!$I$11:$I$14-$A$5/2>=(B31+B32)/2),'Entradas'!$B$11:$B$14) -> 5000 | E31: =SUMPRODUCT(--('Entradas'!$E$11:$E$14="COLD"),--('Entradas'!$H$11:$H$14+$A$5/2<=(B31+B32)/2),--('Entradas'!$I$11:$I$14+$A$5/2>=(B31+B32)/2),'Entradas'!$B$11:$B$14) -> 0 | F31: =D31-E31 -> 5000 | G31: =C31*F31 -> 25000 | H31: =H30+G30 -> 50000
A32: ='Entradas'!H12+IF('Entradas'!E12="HOT",-$A$5/2,$A$5/2) -> 97.5 | B32: =LARGE($A$30:$A$37,3) -> 192.5 | C32: =B32-B33 -> 40 | D32: =SUMPRODUCT(--('Entradas'!$E$11:$E$14="HOT"),--('Entradas'!$H$11:$H$14-$A$5/2<=(B32+B33)/2),--('Entradas'!$I$11:$I$14-$A$5/2>=(B32+B33)/2),'Entradas'!$B$11:$B$14) -> 5000 | E32: =SUMPRODUCT(--('Entradas'!$E$11:$E$14="COLD"),--('Entradas'!$H$11:$H$14+$A$5/2<=(B32+B33)/2),--('Entradas'!$I$11:$I$14+$A$5/2>=(B32+B33)/2),'Entradas'!$B$11:$B$14) -> 6000 | F32: =D32-E32 -> -1000 | G32: =C32*F32 -> -40000 | H32: =H31+G31 -> 75000
A33: ='Entradas'!I12+IF('Entradas'!E12="HOT",-$A$5/2,$A$5/2) -> 197.5 | B33: =LARGE($A$30:$A$37,4) -> 152.5 | C33: =B33-B34 -> 20 | D33: =SUMPRODUCT(--('Entradas'!$E$11:$E$14="HOT"),--('Entradas'!$H$11:$H$14-$A$5/2<=(B33+B34)/2),--('Entradas'!$I$11:$I$14-$A$5/2>=(B33+B34)/2),'Entradas'!$B$11:$B$14) -> 5000 | E33: =SUMPRODUCT(--('Entradas'!$E$11:$E$14="COLD"),--('Entradas'!$H$11:$H$14+$A$5/2<=(B33+B34)/2),--('Entradas'!$I$11:$I$14+$A$5/2>=(B33+B34)/2),'Entradas'!$B$11:$B$14) -> 9000 | F33: =D33-E33 -> -4000 | G33: =C33*F33 -> -80000 | H33: =H32+G32 -> 35000
A34: ='Entradas'!H13+IF('Entradas'!E13="HOT",-$A$5/2,$A$5/2) -> 92.5 | B34: =LARGE($A$30:$A$37,5) -> 132.5 | C34: =B34-B35 -> 15 | D34: =SUMPRODUCT(--('Entradas'!$E$11:$E$14="HOT"),--('Entradas'!$H$11:$H$14-$A$5/2<=(B34+B35)/2),--('Entradas'!$I$11:$I$14-$A$5/2>=(B34+B35)/2),'Entradas'!$B$11:$B$14) -> 5000 | E34: =SUMPRODUCT(--('Entradas'!$E$11:$E$14="COLD"),--('Entradas'!$H$11:$H$14+$A$5/2<=(B34+B35)/2),--('Entradas'!$I$11:$I$14+$A$5/2>=(B34+B35)/2),'Entradas'!$B$11:$B$14) -> 3000 | F34: =D34-E34 -> 2000 | G34: =C34*F34 -> 30000 | H34: =H33+G33 -> -45000
A35: ='Entradas'!I13+IF('Entradas'!E13="HOT",-$A$5/2,$A$5/2) -> 152.5 | B35: =LARGE($A$30:$A$37,6) -> 117.5 | C35: =B35-B36 -> 20 | D35: =SUMPRODUCT(--('Entradas'!$E$11:$E$14="HOT"),--('Entradas'!$H$11:$H$14-$A$5/2<=(B35+B36)/2),--('Entradas'!$I$11:$I$14-$A$5/2>=(B35+B36)/2),'Entradas'!$B$11:$B$14) -> 4000 | E35: =SUMPRODUCT(--('Entradas'!$E$11:$E$14="COLD"),--('Entradas'!$H$11:$H$14+$A$5/2<=(B35+B36)/2),--('Entradas'!$I$11:$I$14+$A$5/2>=(B35+B36)/2),'Entradas'!$B$11:$B$14) -> 3000 | F35: =D35-E35 -> 1000 | G35: =C35*F35 -> 20000 | H35: =H34+G34 -> -15000
A36: ='Entradas'!H14+IF('Entradas'!E14="HOT",-$A$5/2,$A$5/2) -> 132.5 | B36: =LARGE($A$30:$A$37,7) -> 97.5 | C36: =B36-B37 -> 5 | D36: =SUMPRODUCT(--('Entradas'!$E$11:$E$14="HOT"),--('Entradas'!$H$11:$H$14-$A$5/2<=(B36+B37)/2),--('Entradas'!$I$11:$I$14-$A$5/2>=(B36+B37)/2),'Entradas'!$B$11:$B$14) -> 0 | E36: =SUMPRODUCT(--('Entradas'!$E$11:$E$14="COLD"),--('Entradas'!$H$11:$H$14+$A$5/2<=(B36+B37)/2),--('Entradas'!$I$11:$I$14+$A$5/2>=(B36+B37)/2),'Entradas'!$B$11:$B$14) -> 3000 | F36: =D36-E36 -> -3000 | G36: =C36*F36 -> -15000 | H36: =H35+G35 -> 5000
A37: ='Entradas'!I14+IF('Entradas'!E14="HOT",-$A$5/2,$A$5/2) -> 192.5 | B37: =LARGE($A$30:$A$37,8) -> 92.5 | H37: =H36+G36 -> -10000
A40: Cascada del escenario 3 · ΔT en A6
A41: T* sin ordenar | B41: T* ordenada | C41: ΔT intervalo | D41: CP hot | E41: CP cold | F41: CP neto | G41: ΔH | H41: Residual bruto
A42: ='Entradas'!H11+IF('Entradas'!E11="HOT",-$A$6/2,$A$6/2) -> 115 | B42: =LARGE($A$42:$A$49,1) -> 245 | C42: =B42-B43 -> 50 | D42: =SUMPRODUCT(--('Entradas'!$E$11:$E$14="HOT"),--('Entradas'!$H$11:$H$14-$A$6/2<=(B42+B43)/2),--('Entradas'!$I$11:$I$14-$A$6/2>=(B42+B43)/2),'Entradas'!$B$11:$B$14) -> 1000 | E42: =SUMPRODUCT(--('Entradas'!$E$11:$E$14="COLD"),--('Entradas'!$H$11:$H$14+$A$6/2<=(B42+B43)/2),--('Entradas'!$I$11:$I$14+$A$6/2>=(B42+B43)/2),'Entradas'!$B$11:$B$14) -> 0 | F42: =D42-E42 -> 1000 | G42: =C42*F42 -> 50000 | H42: =0 -> 0
A43: ='Entradas'!I11+IF('Entradas'!E11="HOT",-$A$6/2,$A$6/2) -> 245 | B43: =LARGE($A$42:$A$49,2) -> 195 | C43: =B43-B44 -> 0 | D43: =SUMPRODUCT(--('Entradas'!$E$11:$E$14="HOT"),--('Entradas'!$H$11:$H$14-$A$6/2<=(B43+B44)/2),--('Entradas'!$I$11:$I$14-$A$6/2>=(B43+B44)/2),'Entradas'!$B$11:$B$14) -> 5000 | E43: =SUMPRODUCT(--('Entradas'!$E$11:$E$14="COLD"),--('Entradas'!$H$11:$H$14+$A$6/2<=(B43+B44)/2),--('Entradas'!$I$11:$I$14+$A$6/2>=(B43+B44)/2),'Entradas'!$B$11:$B$14) -> 6000 | F43: =D43-E43 -> -1000 | G43: =C43*F43 -> 0 | H43: =H42+G42 -> 50000
A44: ='Entradas'!H12+IF('Entradas'!E12="HOT",-$A$6/2,$A$6/2) -> 95 | B44: =LARGE($A$42:$A$49,3) -> 195 | C44: =B44-B45 -> 40 | D44: =SUMPRODUCT(--('Entradas'!$E$11:$E$14="HOT"),--('Entradas'!$H$11:$H$14-$A$6/2<=(B44+B45)/2),--('Entradas'!$I$11:$I$14-$A$6/2>=(B44+B45)/2),'Entradas'!$B$11:$B$14) -> 5000 | E44: =SUMPRODUCT(--('Entradas'!$E$11:$E$14="COLD"),--('Entradas'!$H$11:$H$14+$A$6/2<=(B44+B45)/2),--('Entradas'!$I$11:$I$14+$A$6/2>=(B44+B45)/2),'Entradas'!$B$11:$B$14) -> 6000 | F44: =D44-E44 -> -1000 | G44: =C44*F44 -> -40000 | H44: =H43+G43 -> 50000
A45: ='Entradas'!I12+IF('Entradas'!E12="HOT",-$A$6/2,$A$6/2) -> 195 | B45: =LARGE($A$42:$A$49,4) -> 155 | C45: =B45-B46 -> 20 | D45: =SUMPRODUCT(--('Entradas'!$E$11:$E$14="HOT"),--('Entradas'!$H$11:$H$14-$A$6/2<=(B45+B46)/2),--('Entradas'!$I$11:$I$14-$A$6/2>=(B45+B46)/2),'Entradas'!$B$11:$B$14) -> 5000 | E45: =SUMPRODUCT(--('Entradas'!$E$11:$E$14="COLD"),--('Entradas'!$H$11:$H$14+$A$6/2<=(B45+B46)/2),--('Entradas'!$I$11:$I$14+$A$6/2>=(B45+B46)/2),'Entradas'!$B$11:$B$14) -> 9000 | F45: =D45-E45 -> -4000 | G45: =C45*F45 -> -80000 | H45: =H44+G44 -> 10000
A46: ='Entradas'!H13+IF('Entradas'!E13="HOT",-$A$6/2,$A$6/2) -> 95 | B46: =LARGE($A$42:$A$49,5) -> 135 | C46: =B46-B47 -> 20 | D46: =SUMPRODUCT(--('Entradas'!$E$11:$E$14="HOT"),--('Entradas'!$H$11:$H$14-$A$6/2<=(B46+B47)/2),--('Entradas'!$I$11:$I$14-$A$6/2>=(B46+B47)/2),'Entradas'!$B$11:$B$14) -> 5000 | E46: =SUMPRODUCT(--('Entradas'!$E$11:$E$14="COLD"),--('Entradas'!$H$11:$H$14+$A$6/2<=(B46+B47)/2),--('Entradas'!$I$11:$I$14+$A$6/2>=(B46+B47)/2),'Entradas'!$B$11:$B$14) -> 3000 | F46: =D46-E46 -> 2000 | G46: =C46*F46 -> 40000 | H46: =H45+G45 -> -70000
A47: ='Entradas'!I13+IF('Entradas'!E13="HOT",-$A$6/2,$A$6/2) -> 155 | B47: =LARGE($A$42:$A$49,6) -> 115 | C47: =B47-B48 -> 20 | D47: =SUMPRODUCT(--('Entradas'!$E$11:$E$14="HOT"),--('Entradas'!$H$11:$H$14-$A$6/2<=(B47+B48)/2),--('Entradas'!$I$11:$I$14-$A$6/2>=(B47+B48)/2),'Entradas'!$B$11:$B$14) -> 4000 | E47: =SUMPRODUCT(--('Entradas'!$E$11:$E$14="COLD"),--('Entradas'!$H$11:$H$14+$A$6/2<=(B47+B48)/2),--('Entradas'!$I$11:$I$14+$A$6/2>=(B47+B48)/2),'Entradas'!$B$11:$B$14) -> 3000 | F47: =D47-E47 -> 1000 | G47: =C47*F47 -> 20000 | H47: =H46+G46 -> -30000
A48: ='Entradas'!H14+IF('Entradas'!E14="HOT",-$A$6/2,$A$6/2) -> 135 | B48: =LARGE($A$42:$A$49,7) -> 95 | C48: =B48-B49 -> 0 | D48: =SUMPRODUCT(--('Entradas'!$E$11:$E$14="HOT"),--('Entradas'!$H$11:$H$14-$A$6/2<=(B48+B49)/2),--('Entradas'!$I$11:$I$14-$A$6/2>=(B48+B49)/2),'Entradas'!$B$11:$B$14) -> 4000 | E48: =SUMPRODUCT(--('Entradas'!$E$11:$E$14="COLD"),--('Entradas'!$H$11:$H$14+$A$6/2<=(B48+B49)/2),--('Entradas'!$I$11:$I$14+$A$6/2>=(B48+B49)/2),'Entradas'!$B$11:$B$14) -> 3000 | F48: =D48-E48 -> 1000 | G48: =C48*F48 -> 0 | H48: =H47+G47 -> -10000
A49: ='Entradas'!I14+IF('Entradas'!E14="HOT",-$A$6/2,$A$6/2) -> 195 | B49: =LARGE($A$42:$A$49,8) -> 95 | H49: =H48+G48 -> -10000
A52: Cascada del escenario 4 · ΔT en A7
A53: T* sin ordenar | B53: T* ordenada | C53: ΔT intervalo | D53: CP hot | E53: CP cold | F53: CP neto | G53: ΔH | H53: Residual bruto
A54: ='Entradas'!H11+IF('Entradas'!E11="HOT",-$A$7/2,$A$7/2) -> 112.5 | B54: =LARGE($A$54:$A$61,1) -> 242.5 | C54: =B54-B55 -> 45 | D54: =SUMPRODUCT(--('Entradas'!$E$11:$E$14="HOT"),--('Entradas'!$H$11:$H$14-$A$7/2<=(B54+B55)/2),--('Entradas'!$I$11:$I$14-$A$7/2>=(B54+B55)/2),'Entradas'!$B$11:$B$14) -> 1000 | E54: =SUMPRODUCT(--('Entradas'!$E$11:$E$14="COLD"),--('Entradas'!$H$11:$H$14+$A$7/2<=(B54+B55)/2),--('Entradas'!$I$11:$I$14+$A$7/2>=(B54+B55)/2),'Entradas'!$B$11:$B$14) -> 0 | F54: =D54-E54 -> 1000 | G54: =C54*F54 -> 45000 | H54: =0 -> 0
A55: ='Entradas'!I11+IF('Entradas'!E11="HOT",-$A$7/2,$A$7/2) -> 242.5 | B55: =LARGE($A$54:$A$61,2) -> 197.5 | C55: =B55-B56 -> 5 | D55: =SUMPRODUCT(--('Entradas'!$E$11:$E$14="HOT"),--('Entradas'!$H$11:$H$14-$A$7/2<=(B55+B56)/2),--('Entradas'!$I$11:$I$14-$A$7/2>=(B55+B56)/2),'Entradas'!$B$11:$B$14) -> 1000 | E55: =SUMPRODUCT(--('Entradas'!$E$11:$E$14="COLD"),--('Entradas'!$H$11:$H$14+$A$7/2<=(B55+B56)/2),--('Entradas'!$I$11:$I$14+$A$7/2>=(B55+B56)/2),'Entradas'!$B$11:$B$14) -> 6000 | F55: =D55-E55 -> -5000 | G55: =C55*F55 -> -25000 | H55: =H54+G54 -> 45000
A56: ='Entradas'!H12+IF('Entradas'!E12="HOT",-$A$7/2,$A$7/2) -> 92.5 | B56: =LARGE($A$54:$A$61,3) -> 192.5 | C56: =B56-B57 -> 35 | D56: =SUMPRODUCT(--('Entradas'!$E$11:$E$14="HOT"),--('Entradas'!$H$11:$H$14-$A$7/2<=(B56+B57)/2),--('Entradas'!$I$11:$I$14-$A$7/2>=(B56+B57)/2),'Entradas'!$B$11:$B$14) -> 5000 | E56: =SUMPRODUCT(--('Entradas'!$E$11:$E$14="COLD"),--('Entradas'!$H$11:$H$14+$A$7/2<=(B56+B57)/2),--('Entradas'!$I$11:$I$14+$A$7/2>=(B56+B57)/2),'Entradas'!$B$11:$B$14) -> 6000 | F56: =D56-E56 -> -1000 | G56: =C56*F56 -> -35000 | H56: =H55+G55 -> 20000
A57: ='Entradas'!I12+IF('Entradas'!E12="HOT",-$A$7/2,$A$7/2) -> 192.5 | B57: =LARGE($A$54:$A$61,4) -> 157.5 | C57: =B57-B58 -> 20 | D57: =SUMPRODUCT(--('Entradas'!$E$11:$E$14="HOT"),--('Entradas'!$H$11:$H$14-$A$7/2<=(B57+B58)/2),--('Entradas'!$I$11:$I$14-$A$7/2>=(B57+B58)/2),'Entradas'!$B$11:$B$14) -> 5000 | E57: =SUMPRODUCT(--('Entradas'!$E$11:$E$14="COLD"),--('Entradas'!$H$11:$H$14+$A$7/2<=(B57+B58)/2),--('Entradas'!$I$11:$I$14+$A$7/2>=(B57+B58)/2),'Entradas'!$B$11:$B$14) -> 9000 | F57: =D57-E57 -> -4000 | G57: =C57*F57 -> -80000 | H57: =H56+G56 -> -15000
A58: ='Entradas'!H13+IF('Entradas'!E13="HOT",-$A$7/2,$A$7/2) -> 97.5 | B58: =LARGE($A$54:$A$61,5) -> 137.5 | C58: =B58-B59 -> 25 | D58: =SUMPRODUCT(--('Entradas'!$E$11:$E$14="HOT"),--('Entradas'!$H$11:$H$14-$A$7/2<=(B58+B59)/2),--('Entradas'!$I$11:$I$14-$A$7/2>=(B58+B59)/2),'Entradas'!$B$11:$B$14) -> 5000 | E58: =SUMPRODUCT(--('Entradas'!$E$11:$E$14="COLD"),--('Entradas'!$H$11:$H$14+$A$7/2<=(B58+B59)/2),--('Entradas'!$I$11:$I$14+$A$7/2>=(B58+B59)/2),'Entradas'!$B$11:$B$14) -> 3000 | F58: =D58-E58 -> 2000 | G58: =C58*F58 -> 50000 | H58: =H57+G57 -> -95000
A59: ='Entradas'!I13+IF('Entradas'!E13="HOT",-$A$7/2,$A$7/2) -> 157.5 | B59: =LARGE($A$54:$A$61,6) -> 112.5 | C59: =B59-B60 -> 15 | D59: =SUMPRODUCT(--('Entradas'!$E$11:$E$14="HOT"),--('Entradas'!$H$11:$H$14-$A$7/2<=(B59+B60)/2),--('Entradas'!$I$11:$I$14-$A$7/2>=(B59+B60)/2),'Entradas'!$B$11:$B$14) -> 4000 | E59: =SUMPRODUCT(--('Entradas'!$E$11:$E$14="COLD"),--('Entradas'!$H$11:$H$14+$A$7/2<=(B59+B60)/2),--('Entradas'!$I$11:$I$14+$A$7/2>=(B59+B60)/2),'Entradas'!$B$11:$B$14) -> 3000 | F59: =D59-E59 -> 1000 | G59: =C59*F59 -> 15000 | H59: =H58+G58 -> -45000
A60: ='Entradas'!H14+IF('Entradas'!E14="HOT",-$A$7/2,$A$7/2) -> 137.5 | B60: =LARGE($A$54:$A$61,7) -> 97.5 | C60: =B60-B61 -> 5 | D60: =SUMPRODUCT(--('Entradas'!$E$11:$E$14="HOT"),--('Entradas'!$H$11:$H$14-$A$7/2<=(B60+B61)/2),--('Entradas'!$I$11:$I$14-$A$7/2>=(B60+B61)/2),'Entradas'!$B$11:$B$14) -> 4000 | E60: =SUMPRODUCT(--('Entradas'!$E$11:$E$14="COLD"),--('Entradas'!$H$11:$H$14+$A$7/2<=(B60+B61)/2),--('Entradas'!$I$11:$I$14+$A$7/2>=(B60+B61)/2),'Entradas'!$B$11:$B$14) -> 0 | F60: =D60-E60 -> 4000 | G60: =C60*F60 -> 20000 | H60: =H59+G59 -> -30000
A61: ='Entradas'!I14+IF('Entradas'!E14="HOT",-$A$7/2,$A$7/2) -> 197.5 | B61: =LARGE($A$54:$A$61,8) -> 92.5 | H61: =H60+G60 -> -10000
A64: Cascada del escenario 5 · ΔT en A8
A65: T* sin ordenar | B65: T* ordenada | C65: ΔT intervalo | D65: CP hot | E65: CP cold | F65: CP neto | G65: ΔH | H65: Residual bruto
A66: ='Entradas'!H11+IF('Entradas'!E11="HOT",-$A$8/2,$A$8/2) -> 110 | B66: =LARGE($A$66:$A$73,1) -> 240 | C66: =B66-B67 -> 40 | D66: =SUMPRODUCT(--('Entradas'!$E$11:$E$14="HOT"),--('Entradas'!$H$11:$H$14-$A$8/2<=(B66+B67)/2),--('Entradas'!$I$11:$I$14-$A$8/2>=(B66+B67)/2),'Entradas'!$B$11:$B$14) -> 1000 | E66: =SUMPRODUCT(--('Entradas'!$E$11:$E$14="COLD"),--('Entradas'!$H$11:$H$14+$A$8/2<=(B66+B67)/2),--('Entradas'!$I$11:$I$14+$A$8/2>=(B66+B67)/2),'Entradas'!$B$11:$B$14) -> 0 | F66: =D66-E66 -> 1000 | G66: =C66*F66 -> 40000 | H66: =0 -> 0
A67: ='Entradas'!I11+IF('Entradas'!E11="HOT",-$A$8/2,$A$8/2) -> 240 | B67: =LARGE($A$66:$A$73,2) -> 200 | C67: =B67-B68 -> 10 | D67: =SUMPRODUCT(--('Entradas'!$E$11:$E$14="HOT"),--('Entradas'!$H$11:$H$14-$A$8/2<=(B67+B68)/2),--('Entradas'!$I$11:$I$14-$A$8/2>=(B67+B68)/2),'Entradas'!$B$11:$B$14) -> 1000 | E67: =SUMPRODUCT(--('Entradas'!$E$11:$E$14="COLD"),--('Entradas'!$H$11:$H$14+$A$8/2<=(B67+B68)/2),--('Entradas'!$I$11:$I$14+$A$8/2>=(B67+B68)/2),'Entradas'!$B$11:$B$14) -> 6000 | F67: =D67-E67 -> -5000 | G67: =C67*F67 -> -50000 | H67: =H66+G66 -> 40000
A68: ='Entradas'!H12+IF('Entradas'!E12="HOT",-$A$8/2,$A$8/2) -> 90 | B68: =LARGE($A$66:$A$73,3) -> 190 | C68: =B68-B69 -> 30 | D68: =SUMPRODUCT(--('Entradas'!$E$11:$E$14="HOT"),--('Entradas'!$H$11:$H$14-$A$8/2<=(B68+B69)/2),--('Entradas'!$I$11:$I$14-$A$8/2>=(B68+B69)/2),'Entradas'!$B$11:$B$14) -> 5000 | E68: =SUMPRODUCT(--('Entradas'!$E$11:$E$14="COLD"),--('Entradas'!$H$11:$H$14+$A$8/2<=(B68+B69)/2),--('Entradas'!$I$11:$I$14+$A$8/2>=(B68+B69)/2),'Entradas'!$B$11:$B$14) -> 6000 | F68: =D68-E68 -> -1000 | G68: =C68*F68 -> -30000 | H68: =H67+G67 -> -10000
A69: ='Entradas'!I12+IF('Entradas'!E12="HOT",-$A$8/2,$A$8/2) -> 190 | B69: =LARGE($A$66:$A$73,4) -> 160 | C69: =B69-B70 -> 20 | D69: =SUMPRODUCT(--('Entradas'!$E$11:$E$14="HOT"),--('Entradas'!$H$11:$H$14-$A$8/2<=(B69+B70)/2),--('Entradas'!$I$11:$I$14-$A$8/2>=(B69+B70)/2),'Entradas'!$B$11:$B$14) -> 5000 | E69: =SUMPRODUCT(--('Entradas'!$E$11:$E$14="COLD"),--('Entradas'!$H$11:$H$14+$A$8/2<=(B69+B70)/2),--('Entradas'!$I$11:$I$14+$A$8/2>=(B69+B70)/2),'Entradas'!$B$11:$B$14) -> 9000 | F69: =D69-E69 -> -4000 | G69: =C69*F69 -> -80000 | H69: =H68+G68 -> -40000
A70: ='Entradas'!H13+IF('Entradas'!E13="HOT",-$A$8/2,$A$8/2) -> 100 | B70: =LARGE($A$66:$A$73,5) -> 140 | C70: =B70-B71 -> 30 | D70: =SUMPRODUCT(--('Entradas'!$E$11:$E$14="HOT"),--('Entradas'!$H$11:$H$14-$A$8/2<=(B70+B71)/2),--('Entradas'!$I$11:$I$14-$A$8/2>=(B70+B71)/2),'Entradas'!$B$11:$B$14) -> 5000 | E70: =SUMPRODUCT(--('Entradas'!$E$11:$E$14="COLD"),--('Entradas'!$H$11:$H$14+$A$8/2<=(B70+B71)/2),--('Entradas'!$I$11:$I$14+$A$8/2>=(B70+B71)/2),'Entradas'!$B$11:$B$14) -> 3000 | F70: =D70-E70 -> 2000 | G70: =C70*F70 -> 60000 | H70: =H69+G69 -> -120000
A71: ='Entradas'!I13+IF('Entradas'!E13="HOT",-$A$8/2,$A$8/2) -> 160 | B71: =LARGE($A$66:$A$73,6) -> 110 | C71: =B71-B72 -> 10 | D71: =SUMPRODUCT(--('Entradas'!$E$11:$E$14="HOT"),--('Entradas'!$H$11:$H$14-$A$8/2<=(B71+B72)/2),--('Entradas'!$I$11:$I$14-$A$8/2>=(B71+B72)/2),'Entradas'!$B$11:$B$14) -> 4000 | E71: =SUMPRODUCT(--('Entradas'!$E$11:$E$14="COLD"),--('Entradas'!$H$11:$H$14+$A$8/2<=(B71+B72)/2),--('Entradas'!$I$11:$I$14+$A$8/2>=(B71+B72)/2),'Entradas'!$B$11:$B$14) -> 3000 | F71: =D71-E71 -> 1000 | G71: =C71*F71 -> 10000 | H71: =H70+G70 -> -60000
A72: ='Entradas'!H14+IF('Entradas'!E14="HOT",-$A$8/2,$A$8/2) -> 140 | B72: =LARGE($A$66:$A$73,7) -> 100 | C72: =B72-B73 -> 10 | D72: =SUMPRODUCT(--('Entradas'!$E$11:$E$14="HOT"),--('Entradas'!$H$11:$H$14-$A$8/2<=(B72+B73)/2),--('Entradas'!$I$11:$I$14-$A$8/2>=(B72+B73)/2),'Entradas'!$B$11:$B$14) -> 4000 | E72: =SUMPRODUCT(--('Entradas'!$E$11:$E$14="COLD"),--('Entradas'!$H$11:$H$14+$A$8/2<=(B72+B73)/2),--('Entradas'!$I$11:$I$14+$A$8/2>=(B72+B73)/2),'Entradas'!$B$11:$B$14) -> 0 | F72: =D72-E72 -> 4000 | G72: =C72*F72 -> 40000 | H72: =H71+G71 -> -50000
A73: ='Entradas'!I14+IF('Entradas'!E14="HOT",-$A$8/2,$A$8/2) -> 200 | B73: =LARGE($A$66:$A$73,8) -> 90 | H73: =H72+G72 -> -10000
A76: Cascada del escenario 6 · ΔT en A9
A77: T* sin ordenar | B77: T* ordenada | C77: ΔT intervalo | D77: CP hot | E77: CP cold | F77: CP neto | G77: ΔH | H77: Residual bruto
A78: ='Entradas'!H11+IF('Entradas'!E11="HOT",-$A$9/2,$A$9/2) -> 107.5 | B78: =LARGE($A$78:$A$85,1) -> 237.5 | C78: =B78-B79 -> 35 | D78: =SUMPRODUCT(--('Entradas'!$E$11:$E$14="HOT"),--('Entradas'!$H$11:$H$14-$A$9/2<=(B78+B79)/2),--('Entradas'!$I$11:$I$14-$A$9/2>=(B78+B79)/2),'Entradas'!$B$11:$B$14) -> 1000 | E78: =SUMPRODUCT(--('Entradas'!$E$11:$E$14="COLD"),--('Entradas'!$H$11:$H$14+$A$9/2<=(B78+B79)/2),--('Entradas'!$I$11:$I$14+$A$9/2>=(B78+B79)/2),'Entradas'!$B$11:$B$14) -> 0 | F78: =D78-E78 -> 1000 | G78: =C78*F78 -> 35000 | H78: =0 -> 0
A79: ='Entradas'!I11+IF('Entradas'!E11="HOT",-$A$9/2,$A$9/2) -> 237.5 | B79: =LARGE($A$78:$A$85,2) -> 202.5 | C79: =B79-B80 -> 15 | D79: =SUMPRODUCT(--('Entradas'!$E$11:$E$14="HOT"),--('Entradas'!$H$11:$H$14-$A$9/2<=(B79+B80)/2),--('Entradas'!$I$11:$I$14-$A$9/2>=(B79+B80)/2),'Entradas'!$B$11:$B$14) -> 1000 | E79: =SUMPRODUCT(--('Entradas'!$E$11:$E$14="COLD"),--('Entradas'!$H$11:$H$14+$A$9/2<=(B79+B80)/2),--('Entradas'!$I$11:$I$14+$A$9/2>=(B79+B80)/2),'Entradas'!$B$11:$B$14) -> 6000 | F79: =D79-E79 -> -5000 | G79: =C79*F79 -> -75000 | H79: =H78+G78 -> 35000
A80: ='Entradas'!H12+IF('Entradas'!E12="HOT",-$A$9/2,$A$9/2) -> 87.5 | B80: =LARGE($A$78:$A$85,3) -> 187.5 | C80: =B80-B81 -> 25 | D80: =SUMPRODUCT(--('Entradas'!$E$11:$E$14="HOT"),--('Entradas'!$H$11:$H$14-$A$9/2<=(B80+B81)/2),--('Entradas'!$I$11:$I$14-$A$9/2>=(B80+B81)/2),'Entradas'!$B$11:$B$14) -> 5000 | E80: =SUMPRODUCT(--('Entradas'!$E$11:$E$14="COLD"),--('Entradas'!$H$11:$H$14+$A$9/2<=(B80+B81)/2),--('Entradas'!$I$11:$I$14+$A$9/2>=(B80+B81)/2),'Entradas'!$B$11:$B$14) -> 6000 | F80: =D80-E80 -> -1000 | G80: =C80*F80 -> -25000 | H80: =H79+G79 -> -40000
A81: ='Entradas'!I12+IF('Entradas'!E12="HOT",-$A$9/2,$A$9/2) -> 187.5 | B81: =LARGE($A$78:$A$85,4) -> 162.5 | C81: =B81-B82 -> 20 | D81: =SUMPRODUCT(--('Entradas'!$E$11:$E$14="HOT"),--('Entradas'!$H$11:$H$14-$A$9/2<=(B81+B82)/2),--('Entradas'!$I$11:$I$14-$A$9/2>=(B81+B82)/2),'Entradas'!$B$11:$B$14) -> 5000 | E81: =SUMPRODUCT(--('Entradas'!$E$11:$E$14="COLD"),--('Entradas'!$H$11:$H$14+$A$9/2<=(B81+B82)/2),--('Entradas'!$I$11:$I$14+$A$9/2>=(B81+B82)/2),'Entradas'!$B$11:$B$14) -> 9000 | F81: =D81-E81 -> -4000 | G81: =C81*F81 -> -80000 | H81: =H80+G80 -> -65000
A82: ='Entradas'!H13+IF('Entradas'!E13="HOT",-$A$9/2,$A$9/2) -> 102.5 | B82: =LARGE($A$78:$A$85,5) -> 142.5 | C82: =B82-B83 -> 35 | D82: =SUMPRODUCT(--('Entradas'!$E$11:$E$14="HOT"),--('Entradas'!$H$11:$H$14-$A$9/2<=(B82+B83)/2),--('Entradas'!$I$11:$I$14-$A$9/2>=(B82+B83)/2),'Entradas'!$B$11:$B$14) -> 5000 | E82: =SUMPRODUCT(--('Entradas'!$E$11:$E$14="COLD"),--('Entradas'!$H$11:$H$14+$A$9/2<=(B82+B83)/2),--('Entradas'!$I$11:$I$14+$A$9/2>=(B82+B83)/2),'Entradas'!$B$11:$B$14) -> 3000 | F82: =D82-E82 -> 2000 | G82: =C82*F82 -> 70000 | H82: =H81+G81 -> -145000
A83: ='Entradas'!I13+IF('Entradas'!E13="HOT",-$A$9/2,$A$9/2) -> 162.5 | B83: =LARGE($A$78:$A$85,6) -> 107.5 | C83: =B83-B84 -> 5 | D83: =SUMPRODUCT(--('Entradas'!$E$11:$E$14="HOT"),--('Entradas'!$H$11:$H$14-$A$9/2<=(B83+B84)/2),--('Entradas'!$I$11:$I$14-$A$9/2>=(B83+B84)/2),'Entradas'!$B$11:$B$14) -> 4000 | E83: =SUMPRODUCT(--('Entradas'!$E$11:$E$14="COLD"),--('Entradas'!$H$11:$H$14+$A$9/2<=(B83+B84)/2),--('Entradas'!$I$11:$I$14+$A$9/2>=(B83+B84)/2),'Entradas'!$B$11:$B$14) -> 3000 | F83: =D83-E83 -> 1000 | G83: =C83*F83 -> 5000 | H83: =H82+G82 -> -75000
A84: ='Entradas'!H14+IF('Entradas'!E14="HOT",-$A$9/2,$A$9/2) -> 142.5 | B84: =LARGE($A$78:$A$85,7) -> 102.5 | C84: =B84-B85 -> 15 | D84: =SUMPRODUCT(--('Entradas'!$E$11:$E$14="HOT"),--('Entradas'!$H$11:$H$14-$A$9/2<=(B84+B85)/2),--('Entradas'!$I$11:$I$14-$A$9/2>=(B84+B85)/2),'Entradas'!$B$11:$B$14) -> 4000 | E84: =SUMPRODUCT(--('Entradas'!$E$11:$E$14="COLD"),--('Entradas'!$H$11:$H$14+$A$9/2<=(B84+B85)/2),--('Entradas'!$I$11:$I$14+$A$9/2>=(B84+B85)/2),'Entradas'!$B$11:$B$14) -> 0 | F84: =D84-E84 -> 4000 | G84: =C84*F84 -> 60000 | H84: =H83+G83 -> -70000
A85: ='Entradas'!I14+IF('Entradas'!E14="HOT",-$A$9/2,$A$9/2) -> 202.5 | B85: =LARGE($A$78:$A$85,8) -> 87.5 | H85: =H84+G84 -> -10000
A88: Cascada del escenario 7 · ΔT en A10
A89: T* sin ordenar | B89: T* ordenada | C89: ΔT intervalo | D89: CP hot | E89: CP cold | F89: CP neto | G89: ΔH | H89: Residual bruto
A90: ='Entradas'!H11+IF('Entradas'!E11="HOT",-$A$10/2,$A$10/2) -> 105 | B90: =LARGE($A$90:$A$97,1) -> 235 | C90: =B90-B91 -> 30 | D90: =SUMPRODUCT(--('Entradas'!$E$11:$E$14="HOT"),--('Entradas'!$H$11:$H$14-$A$10/2<=(B90+B91)/2),--('Entradas'!$I$11:$I$14-$A$10/2>=(B90+B91)/2),'Entradas'!$B$11:$B$14) -> 1000 | E90: =SUMPRODUCT(--('Entradas'!$E$11:$E$14="COLD"),--('Entradas'!$H$11:$H$14+$A$10/2<=(B90+B91)/2),--('Entradas'!$I$11:$I$14+$A$10/2>=(B90+B91)/2),'Entradas'!$B$11:$B$14) -> 0 | F90: =D90-E90 -> 1000 | G90: =C90*F90 -> 30000 | H90: =0 -> 0
A91: ='Entradas'!I11+IF('Entradas'!E11="HOT",-$A$10/2,$A$10/2) -> 235 | B91: =LARGE($A$90:$A$97,2) -> 205 | C91: =B91-B92 -> 20 | D91: =SUMPRODUCT(--('Entradas'!$E$11:$E$14="HOT"),--('Entradas'!$H$11:$H$14-$A$10/2<=(B91+B92)/2),--('Entradas'!$I$11:$I$14-$A$10/2>=(B91+B92)/2),'Entradas'!$B$11:$B$14) -> 1000 | E91: =SUMPRODUCT(--('Entradas'!$E$11:$E$14="COLD"),--('Entradas'!$H$11:$H$14+$A$10/2<=(B91+B92)/2),--('Entradas'!$I$11:$I$14+$A$10/2>=(B91+B92)/2),'Entradas'!$B$11:$B$14) -> 6000 | F91: =D91-E91 -> -5000 | G91: =C91*F91 -> -100000 | H91: =H90+G90 -> 30000
A92: ='Entradas'!H12+IF('Entradas'!E12="HOT",-$A$10/2,$A$10/2) -> 85 | B92: =LARGE($A$90:$A$97,3) -> 185 | C92: =B92-B93 -> 20 | D92: =SUMPRODUCT(--('Entradas'!$E$11:$E$14="HOT"),--('Entradas'!$H$11:$H$14-$A$10/2<=(B92+B93)/2),--('Entradas'!$I$11:$I$14-$A$10/2>=(B92+B93)/2),'Entradas'!$B$11:$B$14) -> 5000 | E92: =SUMPRODUCT(--('Entradas'!$E$11:$E$14="COLD"),--('Entradas'!$H$11:$H$14+$A$10/2<=(B92+B93)/2),--('Entradas'!$I$11:$I$14+$A$10/2>=(B92+B93)/2),'Entradas'!$B$11:$B$14) -> 6000 | F92: =D92-E92 -> -1000 | G92: =C92*F92 -> -20000 | H92: =H91+G91 -> -70000
A93: ='Entradas'!I12+IF('Entradas'!E12="HOT",-$A$10/2,$A$10/2) -> 185 | B93: =LARGE($A$90:$A$97,4) -> 165 | C93: =B93-B94 -> 20 | D93: =SUMPRODUCT(--('Entradas'!$E$11:$E$14="HOT"),--('Entradas'!$H$11:$H$14-$A$10/2<=(B93+B94)/2),--('Entradas'!$I$11:$I$14-$A$10/2>=(B93+B94)/2),'Entradas'!$B$11:$B$14) -> 5000 | E93: =SUMPRODUCT(--('Entradas'!$E$11:$E$14="COLD"),--('Entradas'!$H$11:$H$14+$A$10/2<=(B93+B94)/2),--('Entradas'!$I$11:$I$14+$A$10/2>=(B93+B94)/2),'Entradas'!$B$11:$B$14) -> 9000 | F93: =D93-E93 -> -4000 | G93: =C93*F93 -> -80000 | H93: =H92+G92 -> -90000
A94: ='Entradas'!H13+IF('Entradas'!E13="HOT",-$A$10/2,$A$10/2) -> 105 | B94: =LARGE($A$90:$A$97,5) -> 145 | C94: =B94-B95 -> 40 | D94: =SUMPRODUCT(--('Entradas'!$E$11:$E$14="HOT"),--('Entradas'!$H$11:$H$14-$A$10/2<=(B94+B95)/2),--('Entradas'!$I$11:$I$14-$A$10/2>=(B94+B95)/2),'Entradas'!$B$11:$B$14) -> 5000 | E94: =SUMPRODUCT(--('Entradas'!$E$11:$E$14="COLD"),--('Entradas'!$H$11:$H$14+$A$10/2<=(B94+B95)/2),--('Entradas'!$I$11:$I$14+$A$10/2>=(B94+B95)/2),'Entradas'!$B$11:$B$14) -> 3000 | F94: =D94-E94 -> 2000 | G94: =C94*F94 -> 80000 | H94: =H93+G93 -> -170000
A95: ='Entradas'!I13+IF('Entradas'!E13="HOT",-$A$10/2,$A$10/2) -> 165 | B95: =LARGE($A$90:$A$97,6) -> 105 | C95: =B95-B96 -> 0 | D95: =SUMPRODUCT(--('Entradas'!$E$11:$E$14="HOT"),--('Entradas'!$H$11:$H$14-$A$10/2<=(B95+B96)/2),--('Entradas'!$I$11:$I$14-$A$10/2>=(B95+B96)/2),'Entradas'!$B$11:$B$14) -> 5000 | E95: =SUMPRODUCT(--('Entradas'!$E$11:$E$14="COLD"),--('Entradas'!$H$11:$H$14+$A$10/2<=(B95+B96)/2),--('Entradas'!$I$11:$I$14+$A$10/2>=(B95+B96)/2),'Entradas'!$B$11:$B$14) -> 3000 | F95: =D95-E95 -> 2000 | G95: =C95*F95 -> 0 | H95: =H94+G94 -> -90000
A96: ='Entradas'!H14+IF('Entradas'!E14="HOT",-$A$10/2,$A$10/2) -> 145 | B96: =LARGE($A$90:$A$97,7) -> 105 | C96: =B96-B97 -> 20 | D96: =SUMPRODUCT(--('Entradas'!$E$11:$E$14="HOT"),--('Entradas'!$H$11:$H$14-$A$10/2<=(B96+B97)/2),--('Entradas'!$I$11:$I$14-$A$10/2>=(B96+B97)/2),'Entradas'!$B$11:$B$14) -> 4000 | E96: =SUMPRODUCT(--('Entradas'!$E$11:$E$14="COLD"),--('Entradas'!$H$11:$H$14+$A$10/2<=(B96+B97)/2),--('Entradas'!$I$11:$I$14+$A$10/2>=(B96+B97)/2),'Entradas'!$B$11:$B$14) -> 0 | F96: =D96-E96 -> 4000 | G96: =C96*F96 -> 80000 | H96: =H95+G95 -> -90000
A97: ='Entradas'!I14+IF('Entradas'!E14="HOT",-$A$10/2,$A$10/2) -> 205 | B97: =LARGE($A$90:$A$97,8) -> 85 | H97: =H96+G96 -> -10000
A100: Cascada del escenario 8 · ΔT en A11
A101: T* sin ordenar | B101: T* ordenada | C101: ΔT intervalo | D101: CP hot | E101: CP cold | F101: CP neto | G101: ΔH | H101: Residual bruto
A102: ='Entradas'!H11+IF('Entradas'!E11="HOT",-$A$11/2,$A$11/2) -> 102.5 | B102: =LARGE($A$102:$A$109,1) -> 232.5 | C102: =B102-B103 -> 25 | D102: =SUMPRODUCT(--('Entradas'!$E$11:$E$14="HOT"),--('Entradas'!$H$11:$H$14-$A$11/2<=(B102+B103)/2),--('Entradas'!$I$11:$I$14-$A$11/2>=(B102+B103)/2),'Entradas'!$B$11:$B$14) -> 1000 | E102: =SUMPRODUCT(--('Entradas'!$E$11:$E$14="COLD"),--('Entradas'!$H$11:$H$14+$A$11/2<=(B102+B103)/2),--('Entradas'!$I$11:$I$14+$A$11/2>=(B102+B103)/2),'Entradas'!$B$11:$B$14) -> 0 | F102: =D102-E102 -> 1000 | G102: =C102*F102 -> 25000 | H102: =0 -> 0
A103: ='Entradas'!I11+IF('Entradas'!E11="HOT",-$A$11/2,$A$11/2) -> 232.5 | B103: =LARGE($A$102:$A$109,2) -> 207.5 | C103: =B103-B104 -> 25 | D103: =SUMPRODUCT(--('Entradas'!$E$11:$E$14="HOT"),--('Entradas'!$H$11:$H$14-$A$11/2<=(B103+B104)/2),--('Entradas'!$I$11:$I$14-$A$11/2>=(B103+B104)/2),'Entradas'!$B$11:$B$14) -> 1000 | E103: =SUMPRODUCT(--('Entradas'!$E$11:$E$14="COLD"),--('Entradas'!$H$11:$H$14+$A$11/2<=(B103+B104)/2),--('Entradas'!$I$11:$I$14+$A$11/2>=(B103+B104)/2),'Entradas'!$B$11:$B$14) -> 6000 | F103: =D103-E103 -> -5000 | G103: =C103*F103 -> -125000 | H103: =H102+G102 -> 25000
A104: ='Entradas'!H12+IF('Entradas'!E12="HOT",-$A$11/2,$A$11/2) -> 82.5 | B104: =LARGE($A$102:$A$109,3) -> 182.5 | C104: =B104-B105 -> 15 | D104: =SUMPRODUCT(--('Entradas'!$E$11:$E$14="HOT"),--('Entradas'!$H$11:$H$14-$A$11/2<=(B104+B105)/2),--('Entradas'!$I$11:$I$14-$A$11/2>=(B104+B105)/2),'Entradas'!$B$11:$B$14) -> 5000 | E104: =SUMPRODUCT(--('Entradas'!$E$11:$E$14="COLD"),--('Entradas'!$H$11:$H$14+$A$11/2<=(B104+B105)/2),--('Entradas'!$I$11:$I$14+$A$11/2>=(B104+B105)/2),'Entradas'!$B$11:$B$14) -> 6000 | F104: =D104-E104 -> -1000 | G104: =C104*F104 -> -15000 | H104: =H103+G103 -> -100000
A105: ='Entradas'!I12+IF('Entradas'!E12="HOT",-$A$11/2,$A$11/2) -> 182.5 | B105: =LARGE($A$102:$A$109,4) -> 167.5 | C105: =B105-B106 -> 20 | D105: =SUMPRODUCT(--('Entradas'!$E$11:$E$14="HOT"),--('Entradas'!$H$11:$H$14-$A$11/2<=(B105+B106)/2),--('Entradas'!$I$11:$I$14-$A$11/2>=(B105+B106)/2),'Entradas'!$B$11:$B$14) -> 5000 | E105: =SUMPRODUCT(--('Entradas'!$E$11:$E$14="COLD"),--('Entradas'!$H$11:$H$14+$A$11/2<=(B105+B106)/2),--('Entradas'!$I$11:$I$14+$A$11/2>=(B105+B106)/2),'Entradas'!$B$11:$B$14) -> 9000 | F105: =D105-E105 -> -4000 | G105: =C105*F105 -> -80000 | H105: =H104+G104 -> -115000
A106: ='Entradas'!H13+IF('Entradas'!E13="HOT",-$A$11/2,$A$11/2) -> 107.5 | B106: =LARGE($A$102:$A$109,5) -> 147.5 | C106: =B106-B107 -> 40 | D106: =SUMPRODUCT(--('Entradas'!$E$11:$E$14="HOT"),--('Entradas'!$H$11:$H$14-$A$11/2<=(B106+B107)/2),--('Entradas'!$I$11:$I$14-$A$11/2>=(B106+B107)/2),'Entradas'!$B$11:$B$14) -> 5000 | E106: =SUMPRODUCT(--('Entradas'!$E$11:$E$14="COLD"),--('Entradas'!$H$11:$H$14+$A$11/2<=(B106+B107)/2),--('Entradas'!$I$11:$I$14+$A$11/2>=(B106+B107)/2),'Entradas'!$B$11:$B$14) -> 3000 | F106: =D106-E106 -> 2000 | G106: =C106*F106 -> 80000 | H106: =H105+G105 -> -195000
A107: ='Entradas'!I13+IF('Entradas'!E13="HOT",-$A$11/2,$A$11/2) -> 167.5 | B107: =LARGE($A$102:$A$109,6) -> 107.5 | C107: =B107-B108 -> 5 | D107: =SUMPRODUCT(--('Entradas'!$E$11:$E$14="HOT"),--('Entradas'!$H$11:$H$14-$A$11/2<=(B107+B108)/2),--('Entradas'!$I$11:$I$14-$A$11/2>=(B107+B108)/2),'Entradas'!$B$11:$B$14) -> 5000 | E107: =SUMPRODUCT(--('Entradas'!$E$11:$E$14="COLD"),--('Entradas'!$H$11:$H$14+$A$11/2<=(B107+B108)/2),--('Entradas'!$I$11:$I$14+$A$11/2>=(B107+B108)/2),'Entradas'!$B$11:$B$14) -> 0 | F107: =D107-E107 -> 5000 | G107: =C107*F107 -> 25000 | H107: =H106+G106 -> -115000
A108: ='Entradas'!H14+IF('Entradas'!E14="HOT",-$A$11/2,$A$11/2) -> 147.5 | B108: =LARGE($A$102:$A$109,7) -> 102.5 | C108: =B108-B109 -> 20 | D108: =SUMPRODUCT(--('Entradas'!$E$11:$E$14="HOT"),--('Entradas'!$H$11:$H$14-$A$11/2<=(B108+B109)/2),--('Entradas'!$I$11:$I$14-$A$11/2>=(B108+B109)/2),'Entradas'!$B$11:$B$14) -> 4000 | E108: =SUMPRODUCT(--('Entradas'!$E$11:$E$14="COLD"),--('Entradas'!$H$11:$H$14+$A$11/2<=(B108+B109)/2),--('Entradas'!$I$11:$I$14+$A$11/2>=(B108+B109)/2),'Entradas'!$B$11:$B$14) -> 0 | F108: =D108-E108 -> 4000 | G108: =C108*F108 -> 80000 | H108: =H107+G107 -> -90000
A109: ='Entradas'!I14+IF('Entradas'!E14="HOT",-$A$11/2,$A$11/2) -> 207.5 | B109: =LARGE($A$102:$A$109,8) -> 82.5 | H109: =H108+G108 -> -10000
A112: Cascada del escenario 9 · ΔT en A12
A113: T* sin ordenar | B113: T* ordenada | C113: ΔT intervalo | D113: CP hot | E113: CP cold | F113: CP neto | G113: ΔH | H113: Residual bruto
A114: ='Entradas'!H11+IF('Entradas'!E11="HOT",-$A$12/2,$A$12/2) -> 100 | B114: =LARGE($A$114:$A$121,1) -> 230 | C114: =B114-B115 -> 20 | D114: =SUMPRODUCT(--('Entradas'!$E$11:$E$14="HOT"),--('Entradas'!$H$11:$H$14-$A$12/2<=(B114+B115)/2),--('Entradas'!$I$11:$I$14-$A$12/2>=(B114+B115)/2),'Entradas'!$B$11:$B$14) -> 1000 | E114: =SUMPRODUCT(--('Entradas'!$E$11:$E$14="COLD"),--('Entradas'!$H$11:$H$14+$A$12/2<=(B114+B115)/2),--('Entradas'!$I$11:$I$14+$A$12/2>=(B114+B115)/2),'Entradas'!$B$11:$B$14) -> 0 | F114: =D114-E114 -> 1000 | G114: =C114*F114 -> 20000 | H114: =0 -> 0
A115: ='Entradas'!I11+IF('Entradas'!E11="HOT",-$A$12/2,$A$12/2) -> 230 | B115: =LARGE($A$114:$A$121,2) -> 210 | C115: =B115-B116 -> 30 | D115: =SUMPRODUCT(--('Entradas'!$E$11:$E$14="HOT"),--('Entradas'!$H$11:$H$14-$A$12/2<=(B115+B116)/2),--('Entradas'!$I$11:$I$14-$A$12/2>=(B115+B116)/2),'Entradas'!$B$11:$B$14) -> 1000 | E115: =SUMPRODUCT(--('Entradas'!$E$11:$E$14="COLD"),--('Entradas'!$H$11:$H$14+$A$12/2<=(B115+B116)/2),--('Entradas'!$I$11:$I$14+$A$12/2>=(B115+B116)/2),'Entradas'!$B$11:$B$14) -> 6000 | F115: =D115-E115 -> -5000 | G115: =C115*F115 -> -150000 | H115: =H114+G114 -> 20000
A116: ='Entradas'!H12+IF('Entradas'!E12="HOT",-$A$12/2,$A$12/2) -> 80 | B116: =LARGE($A$114:$A$121,3) -> 180 | C116: =B116-B117 -> 10 | D116: =SUMPRODUCT(--('Entradas'!$E$11:$E$14="HOT"),--('Entradas'!$H$11:$H$14-$A$12/2<=(B116+B117)/2),--('Entradas'!$I$11:$I$14-$A$12/2>=(B116+B117)/2),'Entradas'!$B$11:$B$14) -> 5000 | E116: =SUMPRODUCT(--('Entradas'!$E$11:$E$14="COLD"),--('Entradas'!$H$11:$H$14+$A$12/2<=(B116+B117)/2),--('Entradas'!$I$11:$I$14+$A$12/2>=(B116+B117)/2),'Entradas'!$B$11:$B$14) -> 6000 | F116: =D116-E116 -> -1000 | G116: =C116*F116 -> -10000 | H116: =H115+G115 -> -130000
A117: ='Entradas'!I12+IF('Entradas'!E12="HOT",-$A$12/2,$A$12/2) -> 180 | B117: =LARGE($A$114:$A$121,4) -> 170 | C117: =B117-B118 -> 20 | D117: =SUMPRODUCT(--('Entradas'!$E$11:$E$14="HOT"),--('Entradas'!$H$11:$H$14-$A$12/2<=(B117+B118)/2),--('Entradas'!$I$11:$I$14-$A$12/2>=(B117+B118)/2),'Entradas'!$B$11:$B$14) -> 5000 | E117: =SUMPRODUCT(--('Entradas'!$E$11:$E$14="COLD"),--('Entradas'!$H$11:$H$14+$A$12/2<=(B117+B118)/2),--('Entradas'!$I$11:$I$14+$A$12/2>=(B117+B118)/2),'Entradas'!$B$11:$B$14) -> 9000 | F117: =D117-E117 -> -4000 | G117: =C117*F117 -> -80000 | H117: =H116+G116 -> -140000
A118: ='Entradas'!H13+IF('Entradas'!E13="HOT",-$A$12/2,$A$12/2) -> 110 | B118: =LARGE($A$114:$A$121,5) -> 150 | C118: =B118-B119 -> 40 | D118: =SUMPRODUCT(--('Entradas'!$E$11:$E$14="HOT"),--('Entradas'!$H$11:$H$14-$A$12/2<=(B118+B119)/2),--('Entradas'!$I$11:$I$14-$A$12/2>=(B118+B119)/2),'Entradas'!$B$11:$B$14) -> 5000 | E118: =SUMPRODUCT(--('Entradas'!$E$11:$E$14="COLD"),--('Entradas'!$H$11:$H$14+$A$12/2<=(B118+B119)/2),--('Entradas'!$I$11:$I$14+$A$12/2>=(B118+B119)/2),'Entradas'!$B$11:$B$14) -> 3000 | F118: =D118-E118 -> 2000 | G118: =C118*F118 -> 80000 | H118: =H117+G117 -> -220000
A119: ='Entradas'!I13+IF('Entradas'!E13="HOT",-$A$12/2,$A$12/2) -> 170 | B119: =LARGE($A$114:$A$121,6) -> 110 | C119: =B119-B120 -> 10 | D119: =SUMPRODUCT(--('Entradas'!$E$11:$E$14="HOT"),--('Entradas'!$H$11:$H$14-$A$12/2<=(B119+B120)/2),--('Entradas'!$I$11:$I$14-$A$12/2>=(B119+B120)/2),'Entradas'!$B$11:$B$14) -> 5000 | E119: =SUMPRODUCT(--('Entradas'!$E$11:$E$14="COLD"),--('Entradas'!$H$11:$H$14+$A$12/2<=(B119+B120)/2),--('Entradas'!$I$11:$I$14+$A$12/2>=(B119+B120)/2),'Entradas'!$B$11:$B$14) -> 0 | F119: =D119-E119 -> 5000 | G119: =C119*F119 -> 50000 | H119: =H118+G118 -> -140000
...

Sheet Guia
A1: Cómo leer y modificar el modelo
A2: Este archivo contiene fórmulas editables. No requiere ejecutar Python para cambiar valores de las corrientes existentes.
A4: 1. Datos | B4: CP=m·cp en kJ/(h·K), temperaturas en °C. Q en kJ/h. Para trabajar en kW, divide CP y Q por 3600; este archivo conserva las unidades originales.
A7: 2. ΔT mínimo y pinch | B7: Eliges ΔT mínimo; el pinch se obtiene de los ceros de la cascada ajustada. No es una temperatura de entrada independiente. Revisa Cascada J:L.
A10: 3. Cascada | B10: Ordenar T*; ΔH=(ΣCP_hot−ΣCP_cold)ΔT*. QHmin=max(0,−min residual bruto); QCmin=residual final+QHmin.
A13: 4. Curvas | B13: Compuestas integra CP por intervalos. La curva fría se desplaza QCmin sobre el eje H. La gran compuesta representa el residual de la cascada frente a T*.
A16: 5. Red por tramos | B16: Se unen los nodos de entalpía de ambas curvas. En cada intervalo se calculan Th y Tc en los dos extremos. Se asigna Qij=ΔH·fh_i·fc_j.
A19: 6. Fracciones de rama | B19: fh_i=CP_i/ΣCP_hot; fc_j=CP_j/ΣCP_cold. La rama caliente i hacia j usa fracción fc_j. La rama fría j desde i usa fracción fh_i. Consultar Equipos J:M.
A22: 7. Servicios externos | B22: Las colas no solapadas determinan refrigeración y calentamiento. La matriz muestra servicios por corriente. Elegir utilidades reales exige temperaturas compatibles con ΔT mínimo.
A25: 8. Área opcional | B25: A=Q/(U·ΔTlm). U es un supuesto del usuario y debe ser compatible con las unidades. ΔTlm=(ΔT1−ΔT2)/ln(ΔT1/ΔT2). Si ambas diferencias son iguales se usa ese valor. Con ΔT extremo cero, área infinita.
A28: 9. Modificaciones | B28: Cambiar celdas azules en Entradas actualiza tablas, equipos y gráficos. Para más/menos corrientes, regenerar desde Python. Si aplicaste filtros, vuelve a aplicarlos tras modificar los datos.
A31: 10. Límites | B31: CP constante, régimen estacionario, calor sensible, sin pérdidas térmicas ni restricciones de mezcla de ramas de una misma corriente. La red minimiza servicios, no número de equipos ni coste total.
A34: 11. Excel | B34: Fórmulas convencionales; gráficos XY nativos. Usa cálculo automático. En Excel de escritorio puedes forzar recálculo con Ctrl+Alt+F9. Vista previa sin motor de cálculo puede mostrar solo la caché inicial.
A37: 12. Fuente | B37: Datos y ΔT mínimo: PDF del usuario, diapositivas 27/30. Método de cascada y temperaturas desplazadas explicado en el código y en LEEME.md. No se supone un U ni temperaturas de servicios no aportados.
